Workbook
Name ______DAT1: #REF!
Name ______DAT1: #REF!
Name ______DAT1: #REF!
Name ______DAT1: #REF!
Name ______DAT2: #REF!
Name ______DAT2: #REF!
Name ______DAT2: #REF!
Name ______DAT2: #REF!
Name ______DAT3: #REF!
Name ______DAT3: #REF!
Name ______DAT3: #REF!
Name ______DAT3: #REF!
Name ______DAT4: #REF!
Name ______DAT4: #REF!
Name ______DAT4: #REF!
Name ______DAT4: #REF!
Name ______DAT5: #REF!
Name ______DAT5: #REF!
Name ______DAT5: #REF!
Name ______DAT5: #REF!
Name ______DAT6: #REF!
Name ______DAT6: #REF!
Name ______DAT6: #REF!
Name ______DAT6: #REF!
Name ______DAT7: #REF!
Name ______DAT7: #REF!
Name ______DAT7: #REF!
Name ______DAT7: #REF!
Name ______DAT8: #REF!
Name ______DAT8: #REF!
Name ______DAT8: #REF!
Name ______DAT8: #REF!
Name _____DAT1: #REF!
Name _____DAT1: #REF!
Name _____DAT1: #REF!
Name _____DAT1: #REF!
Name _____DAT2: #REF!
Name _____DAT2: #REF!
Name _____DAT2: #REF!
Name _____DAT2: #REF!
Name _____DAT3: #REF!
Name _____DAT3: #REF!
Name _____DAT3: #REF!
Name _____DAT3: #REF!
Name _____DAT4: #REF!
Name _____DAT4: #REF!
Name _____DAT4: #REF!
Name _____DAT4: #REF!
Name _____DAT5: #REF!
Name _____DAT5: #REF!
Name _____DAT5: #REF!
Name _____DAT5: #REF!
Name _____DAT6: #REF!
Name _____DAT6: #REF!
Name _____DAT6: #REF!
Name _____DAT6: #REF!
Name _____DAT7: #REF!
Name _____DAT7: #REF!
Name _____DAT7: #REF!
Name _____DAT7: #REF!

Sheet FuzzyLookup_AddIn_Undo_Sheet
A1: Softdel Systems Private Limited
A2: Refund of ITC on Export of Services without payment of taxes
A3: Period: April-25 to September-25
A5: Computation of Refund to be claimed
A6: Tax Head | B6: Turnover of zero rated supply of Goods & Services | C6: Adjusted total Turnover | D6: Net Input tax credit | E6: Maximum refund amount to be claimed
B7: 1 | C7: 2 | D7: 3 | E7: 4 = (1*3)/2
A8: IGST | B8: 286017566 | C8: 306200706 | D8: =SUM(#REF!) -> #REF! | E8: =B8*D8/C8 -> #REF!
A9: CGST
A10: SGST
A12: Total | B12: 286017566 | C12: 306200706 | D12: 11261464 | E12: =E8 -> #REF!
A15: Head | B15: Balance in Credit ledger at the end of tax period for which refund is claim i.e September 25 | C15: Balance in Electronic Credit ledger at the time of filing of refund application | D15: Maximum Refund allowed to be claimed | E15: Refund to be Claimed | F15: Balance available after applying for refund
A16: IGST | B16: 0 | C16: 93683 | D16: =IF(B16>C16,C16,B16) -> 0 | E16: 0 | F16: 0
A17: CGST | B17: 5650921 | C17: 4862011 | D17: =IF(B17>C17,C17,B17) -> 4862011 | F17: 4861746
A18: SGST | B18: 5195231 | C18: 4406323 | D18: =IF(B18>C18,C18,B18) -> 4406323 | F18: 4596559
B19: =SUM(B16:B18) -> 10846152 | C19: =SUM(C16:C18) -> 9362017 | D19: =SUM(D16:D18) -> 9268334 | E19: 0 | F19: 9458305

Sheet Working
A2: Export without payment of tax | G2: Total outward Supply B2B | M2: Total outward Supply Exempt | S2: Credite note | Y2: Total | AE2: Adjusted total Turnover
B3: Taxable value | C3: IGST | D3: CGST | E3: SGST | H3: Taxable value | I3: IGST | J3: CGST | K3: SGST | N3: Taxable value | O3: IGST | P3: CGST | Q3: SGST | T3: Taxable value | U3: IGST | V3: CGST | W3: SGST | Z3: Taxable value | AA3: IGST | AB3: CGST | AC3: SGST | AF3: Taxable value | AG3: IGST | AH3: CGST | AI3: SGST
A4: April | B4: 50268400 | F4: o | G4: April | H4: 3265 | I4: 0 | J4: 293.85 | K4: 293.85 | M4: April | N4: 0 | O4: 0 | P4: 0 | Q4: 0 | S4: April | T4: 7000 | U4: 0 | V4: 630 | W4: 630 | Y4: April | Z4: =B4+H4+N4-T4 -> 50264665 | AA4: =C4+I4+O4-U4 -> 0 | AB4: =D4+J4+P4-V4 -> -336.15 | AC4: =E4+K4+Q4-W4 -> -336.15 | AE4: April | AF4: =B4+H4-T4 -> 50264665 | AG4: =C4+I4+U4 -> 0 | AH4: =D4+J4+V4 -> 923.85 | AI4: =E4+K4+W4 -> 923.85
A5: May | B5: 47861150 | G5: May | H5: 5418956 | I5: 0 | J5: 487706.04 | K5: 487706.04 | L5: x | M5: May | N5: 0 | O5: 0 | P5: 0 | Q5: 0 | S5: May | T5: 0 | U5: 0 | V5: 0 | W5: 0 | Y5: May | Z5: =B5+H5+N5-T5 -> 53280106 | AA5: =C5+I5+O5-U5 -> 0 | AB5: =D5+J5+P5-V5 -> 487706.04 | AC5: =E5+K5+Q5-W5 -> 487706.04 | AE5: May | AF5: =B5+H5-T5 -> 53280106 | AG5: =C5+I5+U5 -> 0 | AH5: =D5+J5+V5 -> 487706.04 | AI5: =E5+K5+W5 -> 487706.04
A6: June | B6: 41651400 | G6: June | H6: 3629285 | I6: 0 | J6: 326635.65 | K6: 326635.65 | M6: June | N6: 12980000 | O6: 0 | P6: 0 | Q6: 0 | R6: x | S6: June | T6: 0 | U6: 0 | V6: 0 | W6: 0 | Y6: June | Z6: =B6+H6+N6-T6 -> 58260685 | AA6: =C6+I6+O6-U6 -> 0 | AB6: =D6+J6+P6-V6 -> 326635.65 | AC6: =E6+K6+Q6-W6 -> 326635.65 | AE6: June | AF6: =B6+H6-T6 -> 45280685 | AG6: =C6+I6+U6 -> 0 | AH6: =D6+J6+V6 -> 326635.65 | AI6: =E6+K6+W6 -> 326635.65
A7: July | B7: 45000950 | G7: July | H7: 2656980 | I7: 91216.8 | J7: 193519.8 | K7: 193519.8 | M7: July | N7: 11800000 | O7: 0 | P7: 0 | Q7: 0 | S7: July | T7: 0 | U7: 0 | V7: 0 | W7: 0 | X7: x | Y7: July | Z7: =B7+H7+N7-T7 -> 59457930 | AA7: =C7+I7+O7-U7 -> 91216.8 | AB7: =D7+J7+P7-V7 -> 193519.8 | AC7: =E7+K7+Q7-W7 -> 193519.8 | AE7: July | AF7: =B7+H7-T7 -> 47657930 | AG7: =C7+I7+U7 -> 91216.8 | AH7: =D7+J7+V7 -> 193519.8 | AI7: =E7+K7+W7 -> 193519.8
A8: Aug | B8: 50676633 | G8: Aug | H8: 3184838 | I8: 78687.36 | J8: 247291.74 | K8: 247291.74 | M8: Aug | N8: 0 | O8: 0 | P8: 0 | Q8: 0 | S8: Aug | T8: 0 | U8: 0 | V8: 0 | W8: 0 | Y8: Aug | Z8: =B8+H8+N8-T8 -> 53861471 | AA8: =C8+I8+O8-U8 -> 78687.36 | AB8: =D8+J8+P8-V8 -> 247291.74 | AC8: =E8+K8+Q8-W8 -> 247291.74 | AD8: x | AE8: Aug | AF8: =B8+H8-T8 -> 53861471 | AG8: =C8+I8+U8 -> 78687.36 | AH8: =D8+J8+V8 -> 247291.74 | AI8: =E8+K8+W8 -> 247291.74
A9: Sep | B9: 50559033 | G9: Sep | H9: 5296816 | I9: 182554.56 | J9: 385436.16 | K9: 385436.16 | M9: Sep | N9: 21706541 | O9: 0 | P9: 0 | Q9: 0 | S9: Sep | T9: 0 | U9: 0 | V9: 0 | W9: 0 | Y9: Sep | Z9: =B9+H9+N9-T9 -> 77562390 | AA9: =C9+I9+O9-U9 -> 182554.56 | AB9: =D9+J9+P9-V9 -> 385436.16 | AC9: =E9+K9+Q9-W9 -> 385436.16 | AE9: Sep | AF9: =B9+H9-T9 -> 55855849 | AG9: =C9+I9+U9 -> 182554.56 | AH9: =D9+J9+V9 -> 385436.16 | AI9: =E9+K9+W9 -> 385436.16
B10: =SUM(B4:B9) -> 286017566 | C10: =SUM(C4:C9) -> 0 | D10: =SUM(D4:D9) -> 0 | E10: =SUM(E4:E9) -> 0 | H10: =SUM(H4:H9) -> 20190140 | I10: =SUM(I4:I9) -> 352458.72 | J10: =SUM(J4:J9) -> 1640883.2 | K10: =SUM(K4:K9) -> 1640883.2 | N10: =SUM(N4:N9) -> 46486541 | O10: =SUM(O4:O9) -> 0 | P10: =SUM(P4:P9) -> 0 | Q10: =SUM(Q4:Q9) -> 0 | T10: =SUM(T4:T9) -> 7000 | U10: =SUM(U4:U9) -> 0 | V10: =SUM(V4:V9) -> 630 | W10: =SUM(W4:W9) -> 630 | Z10: =SUM(Z4:Z9) -> 352687247 | AA10: =SUM(AA4:AA9) -> 352458.72 | AB10: =SUM(AB4:AB9) -> 1640253.2 | AC10: =SUM(AC4:AC9) -> 1640253.2 | AF10: =SUM(AF4:AF9) -> 306200706 | AG10: =SUM(AG4:AG9) -> 352458.72 | AH10: =SUM(AH4:AH9) -> 1641513.2 | AI10: =SUM(AI4:AI9) -> 1641513.2
AA11: 352458.72 | AB11: 1640253.2 | AC11: 1640253.2
AA12: =AA10-AA11 -> 0 | AB12: =AB10-AB11 -> 0 | AC12: =AC10-AC11 -> 0 | AG12: =AG10-AA11 -> 0 | AH12: =AH10-AB11 -> 1260 | AI12: =AI10-AC11 -> 1260
B13: Net Input tax credit
B14: IGST | C14: CGST | D14: SGST
A15: April | B15: 298393 | C15: 834858 | D15: 834858 | E15: o
A16: May | B16: 301365.25 | C16: 592983.28 | D16: 592983.28
A17: June | B17: 142598 | C17: 872360 | D17: 872360
A18: July | B18: -18581 | C18: 711279 | D18: 711279
A19: Aug | B19: 382768 | C19: 789175 | D19: 789175
A20: Sep | B20: 291986 | C20: 1130812 | D20: 1130812
B21: =SUM(B15:B20) -> 1398529.2 | C21: =SUM(C15:C20) -> 4931467.3 | D21: =SUM(D15:D20) -> 4931467.3 | E21: =SUM(B21:D21) -> 11261464
E22: 11261464

Sheet Max Refund can be claimed
A1: Softdel Systems Private Limited
A2: Refund of ITC on Export of Services without payment of taxes
A3: Period: October 25 to December-25
A5: Computation of Refund to be claimed
A6: Tax Head | B6: Turnover of zero rated supply of Goods & Services | C6: Adjusted total Turnover | D6: Net Input tax credit | E6: Maximum refund amount to be claimed
B7: 1 | C7: 2 | D7: 3 | E7: 4 = (1*3)/2
A8: IGST | B8: ='Export Turnover'!B17 -> 125640150 | C8: ='Adjusted Total Turnover'!B20 -> 134502707 | D8: ='ITC summery'!E31 -> 5953626.5 | E8: =B8*D8/C8 -> 5561334.3
A9: CGST
A10: SGST
A12: Total | B12: =B8 -> 125640150 | C12: =C8 -> 134502707 | D12: =D8 -> 5953626.5 | E12: =E8 -> 5561334.3
A15: Head | B15: Balance in Credit ledger at the end of tax period for which refund is claim i.e December 25 | C15: Balance in Electronic Credit ledger at the time of filing of refund application | D15: Maximum Refund allowed to be claimed | E15: Refund to be Claimed | F15: Balance available after applying for refund
A16: IGST | B16: 0 | D16: =IF(B16>C16,C16,B16) -> 0 | E16: 0 | F16: 0
A17: CGST | B17: 6446379 | C17: 4206109 | D17: =MIN(IF(B17>C17,C17,B17),E8/2) -> 2780667.2 | E17: =MIN(D17,C17)-305000 -> 2475667.2 | F17: =C17-E17 -> 1730441.8
A18: SGST | B18: 5543095 | C18: 2781300 | D18: =MIN(IF(B18>C18,C18,B18),E8/2) -> 2780667.2 | E18: =MIN(D18,C18)-305000 -> 2475667.2 | F18: =C18-E18 -> 305632.83
B19: =SUM(B16:B18) -> 11989474 | C19: =SUM(C16:C18) -> 6987409 | D19: =SUM(D16:D18) -> 5561334.3 | E19: =SUM(E16:E18) -> 4951334.3 | F19: =SUM(F16:F18) -> 2036074.7

Sheet SR Oct-25 to Dec-25
A1: Softdel System Limited Refund Working
A2: Sales Register
A3: Period: October-25 to December-25
L4: =SUBTOTAL(9,L6:L1048576) -> 148053420 | N4: =SUBTOTAL(9,N6:N1048576) -> 0 | O4: =SUBTOTAL(9,O6:O1048576) -> 0 | P4: =SUBTOTAL(9,P6:P1048576) -> 0 | Q4: =SUBTOTAL(9,Q6:Q1048576) -> 148053420
A5: Month | B5: Invoice No | C5: Invoice Date | D5: Customer Name | E5: Type of Supply | F5: Place of Supply | G5: GSTIN | H5: HSN/ SAC | I5: Currency | J5: Exchange Rate | K5: Amt in Foreign Currency | L5: Taxable Value | M5: Rate | N5: IGST | O5: CGST | P5: SGST | Q5: Invoice Value | R5: Remark-1 | S5: Type of Supply | T5: Adjusted Turnover (AT) | U5: Zero Rated Turnover (ZRT) | V5: Client Remarks
A6: 45931 | B6: SSPL/10-25Dom/01 | C6: 45937 | D6: KONE Elevator India Private Limited | E6: B2B | F6: India | G6: 27AAACK2567P1Z1 | H6: 998313 | L6: 366850 | M6: 0.18 | N6: 0 | O6: 33016.5 | P6: 33016.5 | Q6: 432883 | R6: Domestic Sales | S6: 1. Domestic Sales | T6: Considered in AT | U6: Not Considered in ZRT
A7: 45931 | B7: SSPL/10-25RoE/1 | C7: 45961 | D7: Asset Vantage Systems Private Limited for cost sharing (asset) | E7: B2B | F7: India | G7: 27AALCS2597J1ZO | H7: 998599 | L7: 631659 | M7: 0.18 | N7: 0 | O7: 56849.31 | P7: 56849.31 | Q7: 745357.62 | R7: Domestic Sales | S7: 1. Domestic Sales | T7: Considered in AT | U7: Not Considered in ZRT
A8: 45931 | B8: SSPL/10-25RoE/2 | C8: 45961 | D8: Asset Vantage Systems Private Limited for cost sharing (asset) | E8: B2B | F8: India | G8: 27AALCS2597J1ZO | H8: 998599 | L8: 753661 | M8: 0.18 | N8: 0 | O8: 67829.49 | P8: 67829.49 | Q8: 889319.98 | R8: Domestic Sales | S8: 1. Domestic Sales | T8: Considered in AT | U8: Not Considered in ZRT
A9: 45931 | B9: SSPL/10-25RoE/3 | C9: 45961 | D9: Unidel Technologies LLP for cost sharing (Liab) | E9: B2B | F9: India | G9: 27AAEFU8529J1ZN | H9: 998599 | L9: 21000 | M9: 0.18 | N9: 0 | O9: 1890 | P9: 1890 | Q9: 24780 | R9: Domestic Sales | S9: 1. Domestic Sales | T9: Considered in AT | U9: Not Considered in ZRT
A10: 45931 | B10: SSPL/10-25RoE/4 | C10: 45961 | D10: Asset Vantage Systems Private Limited for cost sharing (asset) | E10: B2B | F10: India | G10: 27AALCS2597J1ZO | H10: 998519 | L10: 1221286 | M10: 0.18 | N10: 0 | O10: 109915.74 | P10: 109915.74 | Q10: 1441117.5 | R10: Domestic Sales | S10: 1. Domestic Sales | T10: Considered in AT | U10: Not Considered in ZRT
A11: 45931 | B11: SSPL/10-25RoE/5 | C11: 45961 | D11: Unidel Technologies LLP for cost sharing (Liab) | E11: B2B | F11: India | G11: 27AAEFU8529J1ZN | H11: 998519 | L11: 3771 | M11: 0.18 | N11: 0 | O11: 339.39 | P11: 339.39 | Q11: 4449.78 | R11: Domestic Sales | S11: 1. Domestic Sales | T11: Considered in AT | U11: Not Considered in ZRT
A12: 45931 | B12: SSPL/10-25EX/1 | C12: 45961 | D12: SS USA Inc | E12: Export - Without payment of tax | F12: USA | H12: 998313 | I12: USD | J12: 88.5696 | K12: 200000 | L12: 17713920 | M12: 0 | N12: 0 | O12: 0 | P12: 0 | Q12: 17713920 | R12: Export - Without payment of tax | S12: 3. Export - Without payment of tax | T12: Considered in AT | U12: Considered in ZRT
A13: 45931 | B13: SSPL/10-25EX/2 | C13: 45961 | D13: SS USA Inc | E13: Export - Without payment of tax | F13: USA | H13: 998313 | I13: USD | J13: 88.5696 | K13: 150000 | L13: 13285440 | M13: 0 | N13: 0 | O13: 0 | P13: 0 | Q13: 13285440 | R13: Export - Without payment of tax | S13: 3. Export - Without payment of tax | T13: Considered in AT | U13: Considered in ZRT
A14: 45931 | B14: SSPL/10-25EX/3 | C14: 45961 | D14: SS USA Inc | E14: Export - Without payment of tax | F14: USA | H14: 998313 | I14: USD | J14: 88.5696 | K14: 130000 | L14: 11514048 | M14: 0 | N14: 0 | O14: 0 | P14: 0 | Q14: 11514048 | R14: Export - Without payment of tax | S14: 3. Export - Without payment of tax | T14: Considered in AT | U14: Considered in ZRT
A15: 45931 | B15: SSPL/10-25EX/4 | C15: 45961 | D15: SS USA Inc | E15: Export - Without payment of tax | F15: USA | H15: 998313 | I15: USD | J15: 88.5696 | K15: 100000 | L15: 8856960 | M15: 0 | N15: 0 | O15: 0 | P15: 0 | Q15: 8856960 | R15: Export - Without payment of tax | S15: 3. Export - Without payment of tax | T15: Considered in AT | U15: Considered in ZRT
A16: 45931 | B16: SSPL/10-25EX/5 | C16: 45961 | D16: Softdel Systems Private Limited JBO | E16: Exempted | F16: Japan | H16: 998313 | L16: 5800000 | M16: 0 | N16: 0 | O16: 0 | P16: 0 | Q16: 5800000 | R16: Exempt Sales | S16: 2. Exempt Sales | T16: Not Considered in AT | U16: Not Considered in ZRT
A17: 45931 | B17: SSPL/10-25EX/6 | C17: 45961 | D17: Softdel Systems Private Limited JBO | E17: Exempted | F17: Japan | H17: 998313 | L17: 4060000 | M17: 0 | N17: 0 | O17: 0 | P17: 0 | Q17: 4060000 | R17: Exempt Sales | S17: 2. Exempt Sales | T17: Not Considered in AT | U17: Not Considered in ZRT
A18: 45962 | B18: SSPL/11-25Dom/1 | C18: 45966 | D18: KONE Elevator India Private Limited | E18: B2B | F18: India | G18: 27AAACK2567P1Z1 | H18: 998313 | L18: 333500 | M18: 0.18 | N18: 0 | O18: 30015 | P18: 30015 | Q18: 393530 | R18: Domestic Sales | S18: 1. Domestic Sales | T18: Considered in AT | U18: Not Considered in ZRT
A19: 45962 | B19: SSPL/11-25Dom/2 | C19: 45985 | D19: Danfoss Industries Private Limited | E19: B2B | F19: India | G19: 33AABCD0321M1Z4 | H19: 998313 | L19: 250000 | M19: 0.18 | N19: 45000 | O19: 0 | P19: 0 | Q19: 295000 | R19: Domestic Sales | S19: 1. Domestic Sales | T19: Considered in AT | U19: Not Considered in ZRT
A20: 45962 | B20: SSPL/11-25RoE/1 | C20: 45991 | D20: Unidel Technologies LLP for cost sharing (Liab) | E20: B2B | F20: India | G20: 27AAEFU8529J1ZN | H20: 998599 | L20: 13000 | M20: 0.18 | N20: 0 | O20: 1170 | P20: 1170 | Q20: 15340 | R20: Domestic Sales | S20: 1. Domestic Sales | T20: Considered in AT | U20: Not Considered in ZRT
A21: 45962 | B21: SSPL/11-25RoE/2 | C21: 45991 | D21: Asset Vantage Systems Private Limited for cost sharing (asset) | E21: B2B | F21: India | G21: 27AALCS2597J1ZO | H21: 998599 | L21: 753661 | M21: 0.18 | N21: 0 | O21: 67829.49 | P21: 67829.49 | Q21: 889319.98 | R21: Domestic Sales | S21: 1. Domestic Sales | T21: Considered in AT | U21: Not Considered in ZRT
A22: 45962 | B22: SSPL/11-25RoE/3 | C22: 45991 | D22: Asset Vantage Systems Private Limited for cost sharing (asset) | E22: B2B | F22: India | G22: 27AALCS2597J1ZO | H22: 998599 | L22: 1198548 | M22: 0.18 | N22: 0 | O22: 107869.32 | P22: 107869.32 | Q22: 1414286.6 | R22: Domestic Sales | S22: 1. Domestic Sales | T22: Considered in AT | U22: Not Considered in ZRT
A23: 45962 | B23: SSPL/11-25RoE/4 | C23: 45991 | D23: Unidel Technologies LLP for cost sharing (Liab) | E23: B2B | F23: India | G23: 27AAEFU8529J1ZN | H23: 998519 | L23: 3771 | M23: 0.18 | N23: 0 | O23: 339.39 | P23: 339.39 | Q23: 4449.78 | R23: Domestic Sales | S23: 1. Domestic Sales | T23: Considered in AT | U23: Not Considered in ZRT
A24: 45962 | B24: SSPL/11-25RoE/5 | C24: 45991 | D24: Asset Vantage Systems Private Limited for cost sharing (asset) | E24: B2B | F24: India | G24: 27AALCS2597J1ZO | H24: 998599 | L24: 433754 | M24: 0.18 | N24: 0 | O24: 39037.86 | P24: 39037.86 | Q24: 511829.72 | R24: Domestic Sales | S24: 1. Domestic Sales | T24: Considered in AT | U24: Not Considered in ZRT
A25: 45962 | B25: SSPL/11-25EX/1 | C25: 45978 | D25: SS USA Inc | E25: Export - Without payment of tax | F25: USA | H25: 998313 | I25: USD | J25: 88.6525 | K25: 80000 | L25: 7092200 | M25: 0 | N25: 0 | O25: 0 | P25: 0 | Q25: 7092200 | R25: Export - Without payment of tax | S25: 3. Export - Without payment of tax | T25: Considered in AT | U25: Considered in ZRT
A26: 45962 | B26: SSPL/11-25EX/2 | C26: 45991 | D26: SS USA Inc | E26: Export - Without payment of tax | F26: USA | H26: 998313 | I26: USD | J26: 89.3476 | K26: 200000 | L26: 17869520 | M26: 0 | N26: 0 | O26: 0 | P26: 0 | Q26: 17869520 | R26: Export - Without payment of tax | S26: 3. Export - Without payment of tax | T26: Considered in AT | U26: Considered in ZRT
A27: 45962 | B27: SSPL/11-25EX/3 | C27: 45991 | D27: SS USA Inc | E27: Export - Without payment of tax | F27: USA | H27: 998313 | I27: USD | J27: 89.3476 | K27: 150000 | L27: 13402140 | M27: 0 | N27: 0 | O27: 0 | P27: 0 | Q27: 13402140 | R27: Export - Without payment of tax | S27: 3. Export - Without payment of tax | T27: Considered in AT | U27: Considered in ZRT
A28: 45962 | B28: SSPL/11-25EX/4 | C28: 45991 | D28: SS USA Inc | E28: Export - Without payment of tax | F28: USA | H28: 998313 | I28: USD | J28: 89.3476 | K28: 150000 | L28: 13402140 | M28: 0 | N28: 0 | O28: 0 | P28: 0 | Q28: 13402140 | R28: Export - Without payment of tax | S28: 3. Export - Without payment of tax | T28: Considered in AT | U28: Considered in ZRT
A29: 45962 | B29: SSPL/11-25EX/5 | C29: 45991 | D29: Softdel Systems Private Limited JBO | E29: Exempted | F29: Japan | H29: 998313 | L29: 5700000 | M29: 0 | N29: 0 | O29: 0 | P29: 0 | Q29: 5700000 | R29: Exempt Sales | S29: 2. Exempt Sales | T29: Not Considered in AT | U29: Not Considered in ZRT
A30: 45992 | B30: SSPL/12-25Dom/1 | C30: 45994 | D30: KONE Elevator India Private Limited | E30: B2B | F30: India | G30: 27AAACK2567P1Z1 | H30: 998313 | L30: 333500 | M30: 0.18 | N30: 0 | O30: 30015 | P30: 30015 | Q30: 393530 | R30: Domestic Sales | S30: 1. Domestic Sales | T30: Considered in AT | U30: Not Considered in ZRT
A31: 45992 | B31: SSPL/12-25Dom/2 | C31: 46013 | D31: San Telequip Pvt Ltd | E31: B2B | F31: India | G31: 27AACCS9541B1ZG | H31: 997731 | L31: 195000 | M31: 0.18 | N31: 0 | O31: 17550 | P31: 17550 | Q31: 230100 | R31: Domestic Sales | S31: 1. Domestic Sales | T31: Considered in AT | U31: Not Considered in ZRT
A32: 45992 | B32: SSPL/12-25Dom/3 | C32: 46020 | D32: KONE Elevator India Private Limited | E32: B2B | F32: India | G32: 27AAACK2567P1Z1 | H32: 998313 | L32: 816640 | M32: 0.18 | N32: 0 | O32: 73497.6 | P32: 73497.6 | Q32: 963635.2 | R32: Domestic Sales | S32: 1. Domestic Sales | T32: Considered in AT | U32: Not Considered in ZRT
A33: 45992 | B33: SSPL/12-25RoE/1 | C33: 46022 | D33: Asset Vantage Systems Private Limited for cost sharing (asset) | E33: B2B | F33: India | G33: 27AALCS2597J1ZO | H33: 998599 | L33: 394433 | M33: 0.18 | N33: 0 | O33: 35498.97 | P33: 35498.97 | Q33: 465430.94 | R33: Domestic Sales | S33: 1. Domestic Sales | T33: Considered in AT | U33: Not Considered in ZRT
A34: 45992 | B34: SSPL/12-25RoE/2 | C34: 46022 | D34: Asset Vantage Systems Private Limited for cost sharing (asset) | E34: B2B | F34: India | G34: 27AALCS2597J1ZO | H34: 998599 | L34: 1197727 | M34: 0.18 | N34: 0 | O34: 107795.43 | P34: 107795.43 | Q34: 1413317.9 | R34: Domestic Sales | S34: 1. Domestic Sales | T34: Considered in AT | U34: Not Considered in ZRT
A35: 45992 | B35: SSPL/12-25RoE/3 | C35: 46022 | D35: Unidel Technologies LLP for cost sharing (Liab) | E35: B2B | F35: India | G35: 27AAEFU8529J1ZN | H35: 998519 | L35: 3775 | M35: 0.18 | N35: 0 | O35: 339.75 | P35: 339.75 | Q35: 4454.5 | R35: Domestic Sales | S35: 1. Domestic Sales | T35: Considered in AT | U35: Not Considered in ZRT
A36: 45992 | B36: SSPL/12-25RoE/4 | C36: 46022 | D36: Asset Vantage Systems Private Limited for cost sharing (asset) | E36: B2B | F36: India | G36: 27AALCS2597J1ZO | H36: 998599 | L36: 753661 | M36: 0.18 | N36: 0 | O36: 67829.49 | P36: 67829.49 | Q36: 889319.98 | R36: Domestic Sales | S36: 1. Domestic Sales | T36: Considered in AT | U36: Not Considered in ZRT
A37: 45992 | B37: SSPL/12-25EX/1 | C37: 46022 | D37: SS USA Inc | E37: Export - Without payment of tax | F37: USA | H37: 998313 | I37: USD | J37: 89.83 | K37: 120000 | L37: 10779600 | M37: 0 | N37: 0 | O37: 0 | P37: 0 | Q37: 10779600 | R37: Export - Without payment of tax | S37: 3. Export - Without payment of tax | T37: Considered in AT | U37: Considered in ZRT
A38: 45992 | B38: SSPL/12-25EX/2 | C38: 46022 | D38: SS USA Inc | E38: Export - Without payment of tax | F38: USA | H38: 998313 | I38: USD | J38: 89.8354 | K38: 120000 | L38: 10780248 | M38: 0 | N38: 0 | O38: 0 | P38: 0 | Q38: 10780248 | R38: Export - Without payment of tax | S38: 3. Export - Without payment of tax | T38: Considered in AT | U38: Considered in ZRT
A39: 45992 | B39: SSPL/12-25EX/3 | C39: 46022 | D39: SS USA Inc | E39: Export - Without payment of tax | F39: USA | H39: 998313 | I39: USD | J39: 89.8354 | K39: 130000 | L39: 11678602 | M39: 0 | N39: 0 | O39: 0 | P39: 0 | Q39: 11678602 | R39: Export - Without payment of tax | S39: 3. Export - Without payment of tax | T39: Considered in AT | U39: Considered in ZRT
A40: 45992 | B40: SSPL/12-25EX/4 | C40: 46022 | D40: SS USA Inc | E40: Export - Without payment of tax | F40: USA | H40: 998313 | I40: USD | J40: 89.8354 | K40: 130000 | L40: 11678602 | M40: 0 | N40: 0 | O40: 0 | P40: 0 | Q40: 11678602 | R40: Export - Without payment of tax | S40: 3. Export - Without payment of tax | T40: Considered in AT | U40: Considered in ZRT
A41: 45992 | B41: SSPL/12-25EX/7 | C41: 46022 | D41: Softdel Systems Private Limited JBO | E41: Exempted | F41: Japan | H41: 998313 | L41: 5800000 | M41: 0 | N41: 0 | O41: 0 | P41: 0 | Q41: 5800000 | R41: Exempt Sales | S41: 2. Exempt Sales | T41: Not Considered in AT | U41: Not Considered in ZRT
A42: 45992 | B42: SSPL/12-25EX/8 | C42: 46022 | D42: Softdel Systems Private Limited JBO | E42: Exempted | F42: Japan | H42: 998313 | L42: 4640000 | M42: 0 | N42: 0 | O42: 0 | P42: 0 | Q42: 4640000 | R42: Exempt Sales | S42: 2. Exempt Sales | T42: Not Considered in AT | U42: Not Considered in ZRT
A43: 45992 | B43: 2 | C43: 29-Dec-2025 | D43: KONE ELEVATOR INDIA PRIVATE LIMITED | E43: Credit Note | F43: India | G43: 27AAACK2567P1Z1 | H43: 998313 | L43: -816640 | M43: 0.18 | N43: 0 | O43: -73497.6 | P43: -73497.6 | Q43: -963635 | R43: B2B Credit Note | S43: 4. B2B Credit Note | T43: Considered in AT | U43: Not Considered in ZRT

Sheet Sales Summary
A1: Softdel System Private Limited
A2: Sales Summary
A3: Period: Oct-25 to Dec-25
A4: Sales as per Sales registered
A5: Row Labels | B5: Sum of Taxable Value | C5: Sum of IGST | D5: Sum of CGST | E5: Sum of SGST
A6: 1. Domestic Sales | B6: 9679197 | C6: 45000 | D6: 848627.73 | E6: 848627.73
A7: 2. Exempt Sales | B7: 26000000 | C7: 0 | D7: 0 | E7: 0
A8: 3. Export - Without payment of tax | B8: 148053420 | C8: 0 | D8: 0 | E8: 0
A9: 4. B2B Credit Note | B9: -816640 | C9: 0 | D9: -73497.6 | E9: -73497.6
A10: Grand Total | B10: 182915977 | C10: 45000 | D10: 775130.13 | E10: 775130.13
A12: Sales as per GSTR-1
A13: Type of Sales | B13: Sum of Taxable Value | C13: Sum of IGST | D13: Sum of CGST | E13: Sum of SGST
A14: 1. Domestic Sales | B14: ='Monthly Return Summary'!R5 -> 9679197 | C14: ='Monthly Return Summary'!S5 -> 45000 | D14: ='Monthly Return Summary'!T5 -> 848627.73 | E14: ='Monthly Return Summary'!U5 -> 848627.73
A15: 2. Exempt Sales (Net of Credit Notes) | B15: ='Monthly Return Summary'!R6 -> 26000000 | C15: ='Monthly Return Summary'!S6 -> 0 | D15: ='Monthly Return Summary'!T6 -> 0 | E15: ='Monthly Return Summary'!U6 -> 0
A16: 3. Export Sales (WOP) - (Net of Credit Notes) | B16: ='Monthly Return Summary'!R7 -> 148053420 | C16: ='Monthly Return Summary'!S7 -> 0 | D16: ='Monthly Return Summary'!T7 -> 0 | E16: ='Monthly Return Summary'!U7 -> 0
A17: 4. Credit note - B2B | B17: ='Monthly Return Summary'!R8 -> -816640 | C17: ='Monthly Return Summary'!S8 -> 0 | D17: ='Monthly Return Summary'!T8 -> -73497.6 | E17: ='Monthly Return Summary'!U8 -> -73497.6
A18: 5. SEZ - Without payment of tax | B18: ='Monthly Return Summary'!R9 -> 0 | C18: ='Monthly Return Summary'!S9 -> 0 | D18: ='Monthly Return Summary'!T9 -> 0 | E18: ='Monthly Return Summary'!U9 -> 0
A19: Grand Total | B19: =SUM(B14:B17) -> 182915977 | C19: =SUM(C14:C17) -> 45000 | D19: =SUM(D14:D17) -> 775130.13 | E19: =SUM(E14:E17) -> 775130.13
A21: Sales as per GSTR-3B
A22: Type of Sales | B22: Sum of Taxable Value | C22: Sum of IGST | D22: Sum of CGST | E22: Sum of SGST
A23: 1. Outward supplies (other than zero rated, nil rated and exempted) | B23: ='Monthly Return Summary'!R14 -> 8862557 | C23: ='Monthly Return Summary'!S14 -> 45000 | D23: ='Monthly Return Summary'!T14 -> 775130.49 | E23: ='Monthly Return Summary'!U14 -> 775130.49
A24: 2. Outward taxable supplies (zero rated) | B24: ='Monthly Return Summary'!R15 -> 148053420 | C24: ='Monthly Return Summary'!S15 -> 0 | D24: ='Monthly Return Summary'!T15 -> 0 | E24: ='Monthly Return Summary'!U15 -> 0
A25: 3. Other outward supplies (nil rated, exempted) | B25: ='Monthly Return Summary'!R16 -> 26000000 | C25: ='Monthly Return Summary'!S16 -> 0 | D25: ='Monthly Return Summary'!T16 -> 0 | E25: ='Monthly Return Summary'!U16 -> 0
A26: Grand Total | B26: =SUM(B23:B25) -> 182915977 | C26: =SUM(C23:C25) -> 45000 | D26: =SUM(D23:D25) -> 775130.49 | E26: =SUM(E23:E25) -> 775130.49
A28: Difference (GSTR-3B-GSTR-1)
A29: Type of Sales | B29: Sum of Taxable Value | C29: Sum of IGST | D29: Sum of CGST | E29: Sum of SGST
A30: Difference (GSTR-3B-GSTR-1) | B30: =B26-B19 -> 0 | C30: =C26-C19 -> 0 | D30: =D26-D19 -> 0.36 | E30: =E26-E19 -> 0.36
A31: Grand Total | B31: =B30 -> 0 | C31: =C30 -> 0 | D31: =D30 -> 0.36 | E31: =E30 -> 0.36

Sheet Adjusted Total Turnover
A1: Softdel System Limited Refund Working
A2: Sales Register
A3: Period: October-25 to December-25
A5: Sales as per GSTR-1
A6: Type of Sales | B6: Sum of Taxable Value | C6: Sum of IGST | D6: Sum of CGST | E6: Sum of SGST
A7: 1. Domestic Sales (Net of Credit Notes) | B7: ='Sales Summary'!B6+'Sales Summary'!B9 -> 8862557 | C7: ='Sales Summary'!C6+'Sales Summary'!C9 -> 45000 | D7: ='Sales Summary'!D6+'Sales Summary'!D9 -> 775130.13 | E7: ='Sales Summary'!E6+'Sales Summary'!E9 -> 775130.13
A8: 2. Exempt Sales (Net of Credit Notes) | B8: ='Sales Summary'!B7 -> 26000000 | C8: ='Sales Summary'!C7 -> 0 | D8: ='Sales Summary'!D7 -> 0 | E8: ='Sales Summary'!E7 -> 0
A9: 3. Export- Without payment of tax | B9: ='Sales Summary'!B8 -> 148053420 | C9: ='Sales Summary'!C8 -> 0 | D9: ='Sales Summary'!D8 -> 0 | E9: ='Sales Summary'!E8 -> 0
A10: Grand Total | B10: =SUM(B7:B9) -> 182915977 | C10: =SUM(C7:C9) -> 45000 | D10: =SUM(D7:D9) -> 775130.13 | E10: =SUM(E7:E9) -> 775130.13
A14: Supplies excluded for the calculation of "Adjusted Total Turnover"
A15: - Exempt Supplies | B15: =B8 -> 26000000 | C15: =C8 -> 0 | D15: =D8 -> 0 | E15: =E8 -> 0
A16: - Total export supplies to SS USA Inc whose amount received onwards September 2025 | B16: ='Export sales'!Z2 -> 148053420 | C16: ='Export sales'!AA2 -> 0 | D16: ='Export sales'!AB2 -> 0 | E16: ='Export sales'!AC2 -> 0
A18: Supplies Added for the calculation of "Adjusted Total Turnover"
A19: + Export - (WOP) - Pertains to October 24 to March 25- Amount received during current period | B19: ='Export Turnover'!B16 -> 125640150 | C19: 0 | D19: 0 | E19: 0
A20: Adjusted Total Turnover | B20: =B10-B15-B16+B19 -> 134502707 | C20: =C10-C15 -> 45000 | D20: =D10-D15 -> 775130.13 | E20: =E10-E15 -> 775130.13

Sheet Export Turnover
A1: Softdel System Limited Refund Working
A2: Sales Register
A3: Period: April-25 to September-25
A5: Sales Register
A6: Row Labels | B6: Sum of Taxable Value | C6: Sum of IGST
A7: SS USA Inc | B7: 148053420 | C7: 0
A8: Export - Without payment of tax | B8: 148053420 | C8: 0
A9: Grand Total | B9: 148053420 | C9: 0
A11: Supplies excluded for the calculation of "Export Turnover"
A13: - Total export supplies to SS USA Inc whose amount received onwards September 2025 | B13: =B8 -> 148053420 | C13: 0
A15: Supplies Added for the calculation of "Export Turnover"
A16: + Export - (WOP) - Pertains to October 24 to June 25- Amount received during current period | B16: ='Exp invoics Apr to Sep 25'!X3 -> 125640150 | C16: ='Export sales'!AA2 -> 0
A17: Export Turnover considered for Refund | B17: =B9-B12-B13+B16 -> 125640150 | C17: =C9-C12-C13+C16 -> 0

Sheet Export sales
A1: Softdel System Limited Refund Working | J1: Yellow invoice to singapore | Y1: Row Labels | Z1: Sum of Taxable Value | AA1: Sum of IGST | AB1: Sum of CGST | AC1: Sum of SGST
A2: Sales Register | J2: Invoices are not avalible with us | Y2: Not Considered in ZRT | Z2: 148053420 | AA2: 0 | AB2: 0 | AC2: 0
A3: Period: Oct-25 to Dec-25 | Y3: Grand Total | Z3: 148053420 | AA3: 0 | AB3: 0 | AC3: 0
L4: =SUBTOTAL(9,L6:L17) -> 148053420 | M4: =SUBTOTAL(9,M6:M17) -> 0 | N4: =SUBTOTAL(9,N6:N17) -> 0 | O4: =SUBTOTAL(9,O6:O17) -> 0 | P4: =SUBTOTAL(9,P6:P17) -> 0 | Q4: =SUBTOTAL(9,Q6:Q17) -> 148053420
A5: Month | B5: Invoice No | C5: Invoice Date | D5: Customer Name | E5: Type of Supply | F5: Place of Supply | G5: Customer GSTIN | H5: HSN/ SAC | I5: Currency | J5: Exchange Rate | K5: Amt in Foreign Currency | L5: Taxable Value | M5: Rate | N5: IGST | O5: CGST | P5: SGST | Q5: Invoice Value | R5: Remark-1 | S5: Type of Supply | T5: Adjusted Turnover (AT) | U5: Zero Rated Turnover (ZRT) | V5: Client Remarks | W5: Client Remarks
A6: 45931 | B6: SSPL/10-25EX/1 | C6: 45961 | D6: SS USA Inc | E6: Export - Without payment of tax | F6: USA | H6: 998313 | I6: USD | J6: 88.5696 | K6: 200000 | L6: 17713920 | M6: 0 | N6: 0 | O6: 0 | P6: 0 | Q6: 17713920 | R6: Export - WOP - Amount received after December | S6: 3. Export - Without payment of tax | T6: Not Considered in AT | U6: Not Considered in ZRT
A7: 45931 | B7: SSPL/10-25EX/2 | C7: 45961 | D7: SS USA Inc | E7: Export - Without payment of tax | F7: USA | H7: 998313 | I7: USD | J7: 88.5696 | K7: 150000 | L7: 13285440 | M7: 0 | N7: 0 | O7: 0 | P7: 0 | Q7: 13285440 | R7: Export - WOP - Amount received after December | S7: 3. Export - Without payment of tax | T7: Not Considered in AT | U7: Not Considered in ZRT
A8: 45931 | B8: SSPL/10-25EX/3 | C8: 45961 | D8: SS USA Inc | E8: Export - Without payment of tax | F8: USA | H8: 998313 | I8: USD | J8: 88.5696 | K8: 130000 | L8: 11514048 | M8: 0 | N8: 0 | O8: 0 | P8: 0 | Q8: 11514048 | R8: Export - WOP - Amount received after December | S8: 3. Export - Without payment of tax | T8: Not Considered in AT | U8: Not Considered in ZRT
A9: 45931 | B9: SSPL/10-25EX/4 | C9: 45961 | D9: SS USA Inc | E9: Export - Without payment of tax | F9: USA | H9: 998313 | I9: USD | J9: 88.5696 | K9: 100000 | L9: 8856960 | M9: 0 | N9: 0 | O9: 0 | P9: 0 | Q9: 8856960 | R9: Export - WOP - Amount received after December | S9: 3. Export - Without payment of tax | T9: Not Considered in AT | U9: Not Considered in ZRT
A10: 45962 | B10: SSPL/11-25EX/1 | C10: 45978 | D10: SS USA Inc | E10: Export - Without payment of tax | F10: USA | H10: 998313 | I10: USD | J10: 88.6525 | K10: 80000 | L10: 7092200 | M10: 0 | N10: 0 | O10: 0 | P10: 0 | Q10: 7092200 | R10: Export - WOP - Amount received after December | S10: 3. Export - Without payment of tax | T10: Not Considered in AT | U10: Not Considered in ZRT
A11: 45962 | B11: SSPL/11-25EX/2 | C11: 45991 | D11: SS USA Inc | E11: Export - Without payment of tax | F11: USA | H11: 998313 | I11: USD | J11: 89.3476 | K11: 200000 | L11: 17869520 | M11: 0 | N11: 0 | O11: 0 | P11: 0 | Q11: 17869520 | R11: Export - WOP - Amount received after December | S11: 3. Export - Without payment of tax | T11: Not Considered in AT | U11: Not Considered in ZRT
A12: 45962 | B12: SSPL/11-25EX/3 | C12: 45991 | D12: SS USA Inc | E12: Export - Without payment of tax | F12: USA | H12: 998313 | I12: USD | J12: 89.3476 | K12: 150000 | L12: 13402140 | M12: 0 | N12: 0 | O12: 0 | P12: 0 | Q12: 13402140 | R12: Export - WOP - Amount received after December | S12: 3. Export - Without payment of tax | T12: Not Considered in AT | U12: Not Considered in ZRT
A13: 45962 | B13: SSPL/11-25EX/4 | C13: 45991 | D13: SS USA Inc | E13: Export - Without payment of tax | F13: USA | H13: 998313 | I13: USD | J13: 89.3476 | K13: 150000 | L13: 13402140 | M13: 0 | N13: 0 | O13: 0 | P13: 0 | Q13: 13402140 | R13: Export - WOP - Amount received after December | S13: 3. Export - Without payment of tax | T13: Not Considered in AT | U13: Not Considered in ZRT
A14: 45992 | B14: SSPL/12-25EX/1 | C14: 46022 | D14: SS USA Inc | E14: Export - Without payment of tax | F14: USA | H14: 998313 | I14: USD | J14: 89.83 | K14: 120000 | L14: 10779600 | M14: 0 | N14: 0 | O14: 0 | P14: 0 | Q14: 10779600 | R14: Export - WOP - Amount received after December | S14: 3. Export - Without payment of tax | T14: Not Considered in AT | U14: Not Considered in ZRT
A15: 45992 | B15: SSPL/12-25EX/2 | C15: 46022 | D15: SS USA Inc | E15: Export - Without payment of tax | F15: USA | H15: 998313 | I15: USD | J15: 89.8354 | K15: 120000 | L15: 10780248 | M15: 0 | N15: 0 | O15: 0 | P15: 0 | Q15: 10780248 | R15: Export - WOP - Amount received after December | S15: 3. Export - Without payment of tax | T15: Not Considered in AT | U15: Not Considered in ZRT
A16: 45992 | B16: SSPL/12-25EX/3 | C16: 46022 | D16: SS USA Inc | E16: Export - Without payment of tax | F16: USA | H16: 998313 | I16: USD | J16: 89.8354 | K16: 130000 | L16: 11678602 | M16: 0 | N16: 0 | O16: 0 | P16: 0 | Q16: 11678602 | R16: Export - WOP - Amount received after December | S16: 3. Export - Without payment of tax | T16: Not Considered in AT | U16: Not Considered in ZRT
A17: 45992 | B17: SSPL/12-25EX/4 | C17: 46022 | D17: SS USA Inc | E17: Export - Without payment of tax | F17: USA | H17: 998313 | I17: USD | J17: 89.8354 | K17: 130000 | L17: 11678602 | M17: 0 | N17: 0 | O17: 0 | P17: 0 | Q17: 11678602 | R17: Export - WOP - Amount received after December | S17: 3. Export - Without payment of tax | T17: Not Considered in AT | U17: Not Considered in ZRT

Sheet Exp invoics Apr to Sep 25
W2: Row Labels | X2: Sum of Taxable Value | Y2: Sum of IGST | Z2: Sum of CGST | AA2: Sum of SGST
W3: Considered in ZRT | X3: 125640150 | Y3: 0 | Z3: 0 | AA3: 0
W4: Not Considered in ZRT | X4: 1.3139902e+08 | Y4: 0 | Z4: 0 | AA4: 0
A5: Month | B5: Invoice No | C5: Invoice Date | D5: Customer Name | E5: Type of Supply | F5: Place of Supply | G5: Customer GSTIN | H5: HSN/ SAC | I5: Currency | J5: Exchange Rate | K5: Amt in Foreign Currency | L5: Taxable Value | M5: Rate | N5: IGST | O5: CGST | P5: SGST | Q5: Invoice Value | R5: Type of Supply | S5: Zero Rated Turnover (ZRT) | T5: Client Remarks | W5: Grand Total | X5: 2.5703917e+08 | Y5: 0 | Z5: 0 | AA5: 0
A6: 45748 | B6: SSPL/04-25Ex/04 | C6: 45777 | D6: SS USA Inc | E6: Export - Without payment of tax | F6: USA | G6: Unregistered | H6: 998313 | I6: USD | J6: 85.16 | K6: 120000 | L6: 10219200 | M6: 0 | N6: 0 | O6: 0 | P6: 0 | Q6: 10219200 | R6: Export - WOP - Amount received after September | S6: Considered in ZRT
A7: 45748 | B7: SSPL/04-25Ex/05 | C7: 45777 | D7: SS USA Inc | E7: Export - Without payment of tax | F7: USA | G7: Unregistered | H7: 998313 | I7: USD | J7: 85.16 | K7: 130000 | L7: 11070800 | M7: 0 | N7: 0 | O7: 0 | P7: 0 | Q7: 11070800 | R7: Export - WOP - Amount received after September | S7: Considered in ZRT
A8: 45802 | B8: SSPL/05-25EX/1 | C8: 45806 | D8: SS USA Inc | E8: Export - Without payment of tax | F8: USA | G8: Unregistered | H8: 998313 | I8: USD | J8: 85.42 | K8: 60000 | L8: 5125200 | M8: 0 | N8: 0 | O8: 0 | P8: 0 | Q8: 5125200 | R8: Export - WOP - Amount received after September | S8: Considered in ZRT
A9: 45802 | B9: SSPL/05-25EX/2 | C9: 45808 | D9: SS USA Inc | E9: Export - Without payment of tax | F9: USA | G9: Unregistered | H9: 998313 | I9: USD | J9: 85.4719 | K9: 120000 | L9: 10256628 | M9: 0 | N9: 0 | O9: 0 | P9: 0 | Q9: 10256628 | R9: Export - WOP - Amount received after September | S9: Considered in ZRT
A10: 45802 | B10: SSPL/05-25EX/3 | C10: 45808 | D10: SS USA Inc | E10: Export - Without payment of tax | F10: USA | G10: Unregistered | H10: 998313 | I10: USD | J10: 85.4719 | K10: 120000 | L10: 10256628 | M10: 0 | N10: 0 | O10: 0 | P10: 0 | Q10: 10256628 | R10: Export - WOP - Amount received after September | S10: Considered in ZRT
A11: 45802 | B11: SSPL/05-25EX/4 | C11: 45808 | D11: SS USA Inc | E11: Export - Without payment of tax | F11: USA | G11: Unregistered | H11: 998313 | I11: USD | J11: 85.4719 | K11: 130000 | L11: 11111347 | M11: 0 | N11: 0 | O11: 0 | P11: 0 | Q11: 11111347 | R11: Export - WOP - Amount received after September | S11: Considered in ZRT
A12: 45802 | B12: SSPL/05-25EX/5 | C12: 45808 | D12: SS USA Inc | E12: Export - Without payment of tax | F12: USA | G12: Unregistered | H12: 998313 | I12: USD | J12: 85.4719 | K12: 130000 | L12: 11111347 | M12: 0 | N12: 0 | O12: 0 | P12: 0 | Q12: 11111347 | R12: Export - WOP - Amount received after September | S12: Considered in ZRT
A13: 45809 | B13: SSPL/06-25Ex/1 | C13: 45811 | D13: SS USA Inc | E13: Export - Without payment of tax | F13: USA | G13: Unregistered | H13: 998313 | I13: USD | J13: 85.4 | K13: 175000 | L13: 14945000 | M13: 0 | N13: 0 | O13: 0 | P13: 0 | Q13: 14945000 | R13: Export - WOP - Amount received after September | S13: Considered in ZRT
A14: 45809 | B14: SSPL/06-25EX/2 | C14: 45827 | D14: SS USA Inc | E14: Export - Without payment of tax | F14: USA | G14: Unregistered | H14: 998313 | I14: USD | J14: 86.44 | K14: 110000 | L14: 9508400 | M14: 0 | N14: 0 | O14: 0 | P14: 0 | Q14: 9508400 | R14: Export - WOP - Amount received after September | S14: Considered in ZRT
A15: 45809 | B15: SSPL/06-25EX/3 | C15: 45834 | D15: SS USA Inc | E15: Export - Without payment of tax | F15: USA | G15: Unregistered | H15: 998313 | I15: USD | J15: 85.99 | K15: 200000 | L15: 17198000 | M15: 0 | N15: 0 | O15: 0 | P15: 0 | Q15: 17198000 | R15: Export - WOP - Amount received after September | S15: Considered in ZRT
A16: 45839 | B16: SSPL/07-25EX/1 | C16: 45868 | D16: SS USA Inc | E16: Export - Without payment of tax | F16: USA | G16: Unregistered | H16: 998313 | I16: USD | J16: 86.92 | K16: 50000 | L16: 4346000 | M16: 0 | N16: 0 | O16: 0 | P16: 0 | Q16: 4346000 | R16: Export - WOP - Amount received after September | S16: Considered in ZRT
A17: 45839 | B17: SSPL/07-25EX/3 | C17: 45869 | D17: SS USA Inc | E17: Export - Without payment of tax | F17: USA | G17: Unregistered | H17: 998313 | I17: USD | J17: 87.43 | K17: 120000 | L17: 10491600 | M17: 0 | N17: 0 | O17: 0 | P17: 0 | Q17: 10491600 | R17: Export - WOP - Amount received after September | S17: Considered in ZRT
... A32: 45901 | B32: SSPL/09-25EX/6 | C32: 45930 | D32: SS USA Inc | E32: Export - Without payment of tax | F32: USA | G32: Unregistered | H32: 998313 | I32: USD | J32: 88.7083 | K32: 120000 | L32: 10644996 | M32: 0 | N32: 0 | O32: 0 | P32: 0 | Q32: 10644996 | R32: Export - WOP - Amount received after September | S32: Not Considered in ZRT

Sheet Sales Vs FIRC 
A1: Softdel System Limited Refund Working
A2: FIRC Summary
A3: Period: October-25 to December-25
I4: =SUBTOTAL(9,I6:I1048576) -> 125640150 | N4: =SUBTOTAL(9,N6:N1048576) -> 125640150 | P4: =SUBTOTAL(9,P6:P1048576) -> 125640150 | Q4: =SUBTOTAL(9,Q6:Q1048576) -> 0 | S4: =N4-P4 -> 0
A5: - | B5: SR No. | C5: Client Name | D5: Invoice Number | E5: Invoice Date | F5: Nature of Service (Description) | G5: Currency of Invoice | H5: Invoice Amount in Foreign Currency | I5: Export Value in INR | J5: FIRC No. | K5: Date of Receipt | L5: FIRC Amount in Foreign Currency | M5: Exchange Rate | N5: Collection Amount in INR | P5: Check | Q5: -
B6: 1 | C6: SS USA Inc | D6: SSPL/04-25Ex/04 | E6: 45777 | G6: USD | H6: 120000 | I6: 10219200 | J6: 0209GRSJ25075560 | K6: 45947 | L6: 109965 | M6: 87.8 | N6: 9654927
J7: 0209GRSJ25084454 | K7: 45954 | L7: =N7/M7 -> 6431.9275 | M7: 87.73 | N7: =I6-N6 -> 564273 | P7: =N7+N6 -> 10219200 | Q7: =P7-I6 -> 0
B8: 2 | C8: SS USA Inc | D8: SSPL/04-25Ex/05 | E8: 45777 | G8: USD | H8: 130000 | I8: 11070800 | J8: 0209GRSJ25084454 | K8: 45954 | L8: =N8/M8 -> 113533.07 | M8: 87.73 | N8: ='FIRC Register'!F5-'Sales Vs FIRC '!N7 -> 9960256.4
J9: 0209GRSJ25083190 | K9: 45954 | L9: =N9/M9 -> 12658.652 | M9: 87.73 | N9: =I8-N8 -> 1110543.6 | P9: =N9+N8 -> 11070800 | Q9: =P9-I8 -> 0
B10: 3 | C10: SS USA Inc | D10: SSPL/05-25EX/1 | E10: 45806 | G10: USD | H10: 60000 | I10: 5125200 | J10: 0209GRSJ25083190 | K10: 45954 | L10: =N10/M10 -> 58420.153 | M10: 87.73 | N10: 5125200 | P10: =N10 -> 5125200 | Q10: =P10-I10 -> 0
B11: 4 | C11: SS USA Inc | D11: SSPL/05-25EX/2 | E11: 45808 | G11: USD | H11: 120000 | I11: 10256628 | J11: 0209GRSJ25083190 | K11: 45954 | L11: =N11/M11 -> 48886.195 | M11: 87.73 | N11: ='FIRC Register'!F6-'Sales Vs FIRC '!N10-'Sales Vs FIRC '!N9 -> 4288785.9
J12: 0209GRSJ25137046 | K12: 45961 | L12: =N12/M12 -> 67311.551 | M12: 88.66 | N12: =I11-N11 -> 5967842.1 | P12: =N12+N11 -> 10256628 | Q12: =P12-I11 -> 0
B13: 5 | C13: SS USA Inc | D13: SSPL/05-25EX/3 | E13: 45808 | G13: USD | H13: 120000 | I13: 10256628 | J13: 0209GRSJ25137046 | K13: 45961 | L13: =N13/M13 -> 42653.449 | M13: 88.66 | N13: ='FIRC Register'!F7-'Sales Vs FIRC '!N12 -> 3781654.8
J14: 0209GRSK25026388 | K14: 45968 | L14: =N14/M14 -> 73080.962 | M14: 88.6 | N14: =I13-N13 -> 6474973.2 | P14: =N14+N13 -> 10256628 | Q14: =P14-I13 -> 0
B15: 6 | C15: SS USA Inc | D15: SSPL/05-25EX/4 | E15: 45808 | G15: USD | H15: 130000 | I15: 11111347 | J15: 0209GRSK25026388 | K15: 45968 | L15: =N15/M15 -> 46884.038 | M15: 88.6 | N15: ='FIRC Register'!F9-'Sales Vs FIRC '!N14 -> 4153925.8
J16: 0209GRSK25026433 | K16: 45968 | L16: =N16/M16 -> 78526.199 | M16: 88.6 | N16: =I15-N15 -> 6957421.2 | P16: =N16+N15 -> 11111347 | Q16: =P16-I15 -> 0
B17: 7 | C17: SS USA Inc | D17: SSPL/05-25EX/5 | E17: 45808 | G17: USD | H17: 130000 | I17: 11111347 | J17: 0209GRSK25026433 | K17: 45968 | L17: =N17/M17 -> 31438.801 | M17: 88.6 | N17: ='FIRC Register'!F10-'Sales Vs FIRC '!N16 -> 2785477.8
J18: 0209GRSK25064826 | K18: 45978 | L18: =N18/M18 -> 94066.989 | M18: 88.51 | N18: =I17-N17 -> 8325869.2 | P18: =N18+N17 -> 11111347 | Q18: =P18-I17 -> 0
B19: 8 | C19: SS USA Inc | D19: SSPL/06-25Ex/1 | E19: 45811 | G19: USD | H19: 175000 | I19: 14945000 | J19: 0209GRSK25064826 | K19: 45978 | L19: =N19/M19 -> 25898.011 | M19: 88.51 | N19: ='FIRC Register'!F12-'Sales Vs FIRC '!N18 -> 2292232.9
J20: 0209GRSK25064780 | K20: 45978 | L20: =N20/M20 -> 99965 | M20: 88.51 | N20: ='FIRC Register'!F13 -> 8847902.2
J21: 0209GRSK25083734 | K21: 45981 | L21: =N21/M21 -> 42915.237 | M21: 88.66 | N21: =I19-N20-N19 -> 3804864.9 | P21: =N21+N20+N19 -> 14945000 | Q21: =P21-I19 -> 0
B22: 9 | C22: SS USA Inc | D22: SSPL/06-25EX/2 | E22: 45827 | G22: USD | H22: 110000 | I22: 9508400 | J22: 0209GRSK25083734 | K22: 45981 | L22: =N22/M22 -> 37049.763 | M22: 88.66 | N22: ='FIRC Register'!F14-'Sales Vs FIRC '!N21 -> 3284832
J23: 0209GRSL25010603 | K23: 45994 | L23: =N23/M23 -> 69089.343 | M23: 90.08 | N23: =I22-N22 -> 6223568 | P23: =N23+N22 -> 9508400 | Q23: =P23-I22 -> 0
B24: 10 | C24: SS USA Inc | D24: SSPL/06-25EX/3 | E24: 45834 | G24: USD | H24: 200000 | I24: 17198000 | J24: 0209GRSL25010603 | K24: 45994 | L24: =N24/M24 -> 80875.657 | M24: 90.08 | N24: ='FIRC Register'!F15-'Sales Vs FIRC '!N23 -> 7285279.2
J25: 0209GRSL25060277 | K25: 46003 | L25: =N25/M25 -> 109799.74 | M25: 90.28 | N25: =I24-N24 -> 9912720.8 | P25: =N25+N24 -> 17198000 | Q25: =P25-I24 -> 0
B26: 11 | C26: SS USA Inc | D26: SSPL/07-25EX/1 | E26: 45868 | G26: USD | H26: 50000 | I26: 4346000 | J26: 0209GRSL25060277 | K26: 46003 | L26: =N26/M26 -> 40165.257 | M26: 90.28 | N26: ='FIRC Register'!F16-'Sales Vs FIRC '!N25 -> 3626119.4
J27: 0209GRSL25080255 | K27: 46008 | L27: =N27/M27 -> 7998.6733 | M27: 90 | N27: =I26-N26 -> 719880.6 | P27: =N27+N26 -> 4346000 | Q27: =P27-I26 -> 0
B28: 12 | C28: SS USA Inc | D28: SSPL/07-25EX/3 | E28: 45869 | G28: USD | H28: 120000 | I28: 10491600 | J28: 0209GRSL25080255 | K28: 46008 | L28: =N28/M28 -> 116573.33 | M28: 90 | N28: =I28 -> 10491600 | P28: =N28 -> 10491600 | Q28: =P28-I28 -> 0

Sheet FIRC Register
A1: Softdel System Limited Refund Working
F2: =SUBTOTAL(9,F4:F1048576) -> 2.5812112e+08
A3: Sr No | B3: No. | C3: Date (dd-mm-yyyy) | D3: Currency | E3: Amount in Foreign Currency | F3: Value (In INR) | G3: Bank Name | H3: - | I3: Rate | J3: Remarks
A4: 1 | B4: 0209GRSJ25075560 | C4: 45947 | D4: USD | E4: 109965 | F4: 9654927 | I4: 87.8 | J4: Utilised
A5: =A4+1 -> 2 | B5: 0209GRSJ25084454 | C5: 45954 | D5: USD | E5: 119965 | F5: 10524529 | I5: 87.73 | J5: Utilised
A6: =A5+1 -> 3 | B6: 0209GRSJ25083190 | C6: 45954 | D6: USD | E6: 119965 | F6: 10524529 | I6: 87.73 | J6: Utilised
A7: =A6+1 -> 4 | B7: 0209GRSJ25137046 | C7: 45961 | D7: USD | E7: 109965 | F7: 9749496.9 | I7: 88.66 | J7: Utilised
A8: =A7+1 -> 5 | B8: 0209GRSK25013366 | C8: 45967 | D8: JPY | E8: 12000000 | F8: 6780000 | I8: 0.565 | J8: Not utilized as payment received from Japan.
A9: =A8+1 -> 6 | B9: 0209GRSK25026388 | C9: 45968 | D9: USD | E9: 119965 | F9: 10628899 | I9: 88.6 | J9: Utilised
A10: =A9+1 -> 7 | B10: 0209GRSK25026433 | C10: 45968 | D10: USD | E10: 109965 | F10: 9742899 | I10: 88.6 | J10: Utilised
A11: =A10+1 -> 8 | B11: 0209GRSK25049558 | C11: 45974 | D11: JPY | E11: 10000000 | F11: 5590000 | I11: 0.559 | J11: Not utilized as payment received from Japan.
A12: =A11+1 -> 9 | B12: 0209GRSK25064826 | C12: 45978 | D12: USD | E12: 119965 | F12: 10618102 | I12: 88.51 | J12: Utilised
A13: =A12+1 -> 10 | B13: 0209GRSK25064780 | C13: 45978 | D13: USD | E13: 99965 | F13: 8847902.2 | I13: 88.51 | J13: Utilised
A14: =A13+1 -> 11 | B14: 0209GRSK25083734 | C14: 45981 | D14: USD | E14: 79965 | F14: 7089696.9 | I14: 88.66 | J14: Utilised
A15: =A14+1 -> 12 | B15: 0209GRSL25010603 | C15: 45994 | D15: USD | E15: 149965 | F15: 13508847 | I15: 90.08 | J15: Utilised
A16: =A15+1 -> 13 | B16: 0209GRSL25060277 | C16: 46003 | D16: USD | E16: 149965 | F16: 13538840 | I16: 90.28 | J16: Utilised
... A28: =A27+1 -> 25 | B28: 0209GRSC26018580 | C28: 46086 | D28: USD | E28: 129965 | F28: 11895696 | I28: 91.53 | J28: Not utilized

Sheet statement 3
A1: Goods and Services Tax
A4: Statement-3 [rule 89(2) (b) & 89(2)(c)]
A6: * Indicates Mandatory Fields | C6: GSTIN* | D6: 27AAECS0576Q1ZQ | M6: * Indicates Mandatory Fields
A7: From Return Period* (mmyyyy) | D7: 102025 | G7: Refund Type: Export without payment of tax (accumulated ITC) | M7: * Please use clear from drop down to delete. Do not hard delete the contents
A8: To Return Period* (mmyyyy) | D8: 122025
A9: ***Note:- These sheet at a time can take upto 10,000 rows / entries Kindly download the latest version of offline utility for preparing and uploading the statement on GST portal. Else you may face issues while uploading the statement prepared using the old version
A10: Sr. No. | B10: Document Details | F10: Goods/ Services (G/S) | G10: Shipping bill/ Bill of export/ Endorsed invoice no. | K10: EGM Details | M10: BRC/ FIRC | P10: Error
B11: Type of Document | C11: No. | D11: Date (dd-mm-yyyy) | E11: Value | G11: Port Code | H11: No. | I11: Date (dd-mm-yyyy) | J11: FOB Value | K11: Ref No. | L11: Date (dd-mm-yyyy) | M11: No. | N11: Date (dd-mm-yyyy) | O11: Value
A12: 1 | B12: 2 | C12: 3 | D12: 4 | E12: 5 | F12: 6 | G12: 7 | H12: 8 | I12: 9 | J12: 10 | K12: 11 | L12: 12 | M12: 13 | N12: 14 | O12: 15 | P12: 16
A13: 1 | B13: Invoice | C13: SSPL/04-25Ex/04 | D13: 45777 | E13: 10219200 | F13: S | M13: 0209GRSJ25075560 | N13: 45947 | O13: 9654927
A14: =A13+1 -> 2 | B14: Invoice | C14: SSPL/04-25Ex/05 | D14: 45777 | E14: 11070800 | F14: S | M14: 0209GRSJ25084454 | N14: 45954 | O14: 10524529
A15: =A14+1 -> 3 | B15: Invoice | C15: SSPL/05-25EX/1 | D15: 45806 | E15: 5125200 | F15: S | M15: 0209GRSJ25083190 | N15: 45954 | O15: 10524529
A16: =A15+1 -> 4 | B16: Invoice | C16: SSPL/05-25EX/2 | D16: 45808 | E16: 10256628 | F16: S | M16: 0209GRSJ25137046 | N16: 45961 | O16: 9749496.9
A17: =A16+1 -> 5 | B17: Invoice | C17: SSPL/05-25EX/3 | D17: 45808 | E17: 10256628 | F17: S | M17: 0209GRSK25026388 | N17: 45968 | O17: 10628899
A18: =A17+1 -> 6 | B18: Invoice | C18: SSPL/05-25EX/4 | D18: 45808 | E18: 11111347 | F18: S | M18: 0209GRSK25026433 | N18: 45968 | O18: 9742899
A19: =A18+1 -> 7 | B19: Invoice | C19: SSPL/05-25EX/5 | D19: 45808 | E19: 11111347 | F19: S | M19: 0209GRSK25064826 | N19: 45978 | O19: 10618102
A20: =A19+1 -> 8 | B20: Invoice | C20: SSPL/06-25Ex/1 | D20: 45811 | E20: 14945000 | F20: S | M20: 0209GRSK25064780 | N20: 45978 | O20: 8847902.2
A21: =A20+1 -> 9 | B21: Invoice | C21: SSPL/06-25EX/2 | D21: 45827 | E21: 9508400 | F21: S | M21: 0209GRSK25083734 | N21: 45981 | O21: 7089696.9
A22: =A21+1 -> 10 | B22: Invoice | C22: SSPL/06-25EX/3 | D22: 45834 | E22: 17198000 | F22: S | M22: 0209GRSL25010603 | N22: 45994 | O22: 13508847
A23: =A22+1 -> 11 | B23: Invoice | C23: SSPL/07-25EX/1 | D23: 45868 | E23: 4346000 | F23: S | M23: 0209GRSL25060277 | N23: 46003 | O23: 13538840
A24: =A23+1 -> 12 | B24: Invoice | C24: SSPL/07-25EX/3 | D24: 45869 | E24: 10491600 | F24: S | M24: 0209GRSL25080255 | N24: 46008 | O24: 13496850

Sheet Monthly Return Summary
B3: Sales as per GSTR-1 - Oct-25 | G3: Sales as per GSTR-1 - Nov-25 | L3: Sales as per GSTR-1 - Dec-25 | R3: Total
A4: Type of Sales | B4: Taxable Value | C4: IGST | D4: CGST | E4: SGST | G4: Taxable Value | H4: IGST | I4: CGST | J4: SGST | L4: Taxable Value | M4: IGST | N4: CGST | O4: SGST | R4: Taxable Value | S4: IGST | T4: CGST | U4: SGST
A5: 1. Domestic Sales (Net of Credit Notes) | B5: 2998227 | C5: 0 | D5: 269840.43 | E5: 269840.43 | G5: 2986234 | H5: 45000 | I5: 246261.06 | J5: 246261.06 | L5: 3694736 | M5: 0 | N5: 332526.24 | O5: 332526.24 | R5: =B5+G5+L5 -> 9679197 | S5: =C5+H5+M5 -> 45000 | T5: =D5+I5+N5 -> 848627.73 | U5: =E5+J5+O5 -> 848627.73
A6: 2. Exempt Sales (Net of Credit Notes) | B6: 9860000 | C6: 0 | D6: 0 | E6: 0 | G6: 5700000 | H6: 0 | I6: 0 | J6: 0 | L6: 10440000 | M6: 0 | N6: 0 | O6: 0 | R6: =B6+G6+L6 -> 26000000 | S6: =C6+H6+M6 -> 0 | T6: =D6+I6+N6 -> 0 | U6: =E6+J6+O6 -> 0
A7: 3. Export Sales (WOP) - (Net of Credit Notes) | B7: 51370368 | C7: 0 | D7: 0 | E7: 0 | G7: 51766000 | H7: 0 | I7: 0 | J7: 0 | L7: 44917052 | M7: 0 | N7: 0 | O7: 0 | R7: =B7+G7+L7 -> 148053420 | S7: =C7+H7+M7 -> 0 | T7: =D7+I7+N7 -> 0 | U7: =E7+J7+O7 -> 0
A8: 4. B2B Credit note | B8: 0 | C8: 0 | D8: 0 | E8: 0 | G8: 0 | H8: 0 | I8: 0 | J8: 0 | L8: -816640 | M8: 0 | N8: -73497.6 | O8: -73497.6 | R8: =B8+G8+L8 -> -816640 | S8: =C8+H8+M8 -> 0 | T8: =D8+I8+N8 -> -73497.6 | U8: =E8+J8+O8 -> -73497.6
A9: 5. SEZ - Without payment of tax | B9: 0 | C9: 0 | D9: 0 | E9: 0 | G9: 0 | H9: 0 | I9: 0 | J9: 0 | L9: 0 | M9: 0 | N9: 0 | O9: 0 | R9: =B9+G9+L9 -> 0 | S9: =C9+H9+M9 -> 0 | T9: =D9+I9+N9 -> 0 | U9: =E9+J9+O9 -> 0
A10: Grand Total | B10: =SUM(B5:B9) -> 64228595 | C10: =SUM(C5:C9) -> 0 | D10: =SUM(D5:D9) -> 269840.43 | E10: =SUM(E5:E9) -> 269840.43 | G10: =SUM(G5:G9) -> 60452234 | H10: =SUM(H5:H9) -> 45000 | I10: =SUM(I5:I9) -> 246261.06 | J10: =SUM(J5:J9) -> 246261.06 | L10: =SUM(L5:L9) -> 58235148 | M10: =SUM(M5:M9) -> 0 | N10: =SUM(N5:N9) -> 259028.64 | O10: =SUM(O5:O9) -> 259028.64 | R10: =SUM(R5:R9) -> 182915977 | S10: =SUM(S5:S9) -> 45000 | T10: =SUM(T5:T9) -> 775130.13 | U10: =SUM(U5:U9) -> 775130.13
R11: =R10-R6 -> 156915977 | S11: =S10-S6 -> 45000 | T11: =T10-T6 -> 775130.13 | U11: =U10-U6 -> 775130.13
B12: Sales as per GSTR-3B - Oct-25 | G12: Sales as per GSTR-3B - Nov-25 | L12: Sales as per GSTR-3B - Dec-25 | R12: Total
A13: Type of Sales | B13: Taxable Value | C13: IGST | D13: CGST | E13: SGST | G13: Taxable Value | H13: IGST | I13: CGST | J13: SGST | L13: Taxable Value | M13: IGST | N13: CGST | O13: SGST | R13: Taxable Value | S13: IGST | T13: CGST | U13: SGST
A14: 1. Outward supplies (other than zero rated, nil rated and exempted) | B14: 2998227 | C14: 0 | D14: 269840.43 | E14: 269840.43 | G14: 2986234 | H14: 45000 | I14: 246261.06 | J14: 246261.06 | L14: 2878096 | M14: 0 | N14: 259029 | O14: 259029 | R14: =B14+G14+L14 -> 8862557 | S14: =C14+H14+M14 -> 45000 | T14: =D14+I14+N14 -> 775130.49 | U14: =E14+J14+O14 -> 775130.49
A15: 2. Outward taxable supplies (zero rated) | B15: 51370368 | C15: 0 | D15: 0 | E15: 0 | G15: 51766000 | H15: 0 | I15: 0 | J15: 0 | L15: 44917052 | M15: 0 | N15: 0 | O15: 0 | R15: =B15+G15+L15 -> 148053420 | S15: =C15+H15+M15 -> 0 | T15: =D15+I15+N15 -> 0 | U15: =E15+J15+O15 -> 0
A16: 3. Other outward supplies (nil rated, exempted) | B16: 9860000 | C16: 0 | D16: 0 | E16: 0 | G16: 5700000 | H16: 0 | I16: 0 | J16: 0 | L16: 10440000 | M16: 0 | N16: 0 | O16: 0 | R16: =B16+G16+L16 -> 26000000 | S16: =C16+H16+M16 -> 0 | T16: =D16+I16+N16 -> 0 | U16: =E16+J16+O16 -> 0
A17: Grand Total | B17: =SUM(B14:B16) -> 64228595 | C17: =SUM(C14:C16) -> 0 | D17: =SUM(D14:D16) -> 269840.43 | E17: =SUM(E14:E16) -> 269840.43 | G17: =SUM(G14:G16) -> 60452234 | H17: =SUM(H14:H16) -> 45000 | I17: =SUM(I14:I16) -> 246261.06 | J17: =SUM(J14:J16) -> 246261.06 | L17: =SUM(L14:L16) -> 58235148 | M17: =SUM(M14:M16) -> 0 | N17: =SUM(N14:N16) -> 259029 | O17: =SUM(O14:O16) -> 259029 | R17: =SUM(R14:R16) -> 182915977 | S17: =SUM(S14:S16) -> 45000 | T17: =SUM(T14:T16) -> 775130.49 | U17: =SUM(U14:U16) -> 775130.49
B19: Purchase as per GSTR-3B - Oct-25 | G19: Purchase as per GSTR-3B - Nov-25 | L19: Purchase as per GSTR-3B - Dec-25 | R19: Total
A20: Type of Purchase | B20: Taxable Value | C20: IGST | D20: CGST | E20: SGST | G20: Taxable Value | H20: IGST | I20: CGST | J20: SGST | L20: Taxable Value | M20: IGST | N20: CGST | O20: SGST | R20: Taxable Value | S20: IGST | T20: CGST | U20: SGST
A21: 1. + IMPG | R21: =B21+G21+L21 -> 0 | S21: =C21+H21+M21 -> 0 | T21: =D21+I21+N21 -> 0 | U21: =E21+J21+O21 -> 0
A22: 2. + IMPS | C22: 20740 | H22: 83937 | M22: 29481 | R22: =B22+G22+L22 -> 0 | S22: =C22+H22+M22 -> 134158 | T22: =D22+I22+N22 -> 0 | U22: =E22+J22+O22 -> 0
A23: 3. + RCM - Domestic | I23: 1305 | J23: 1305 | R23: =B23+G23+L23 -> 0 | S23: =C23+H23+M23 -> 0 | T23: =D23+I23+N23 -> 1305 | U23: =E23+J23+O23 -> 1305
A24: 4. + All Other ITC | C24: 832681 | D24: 1263634 | E24: 1263634 | H24: 218989 | I24: 1194899 | J24: 1194899 | M24: 381595 | N24: 2315218 | O24: 2315218 | R24: =B24+G24+L24 -> 0 | S24: =C24+H24+M24 -> 1433265 | T24: =D24+I24+N24 -> 4773751 | U24: =E24+J24+O24 -> 4773751
A25: 5. - Reversal u/s 17(5) | C25: -114863 | D25: -149966 | E25: -149966 | H25: -22721 | I25: -84940 | J25: -84940 | M25: -48492 | N25: -220162 | O25: -220162 | R25: =B25+G25+L25 -> 0 | S25: =C25+H25+M25 -> -186076 | T25: =D25+I25+N25 -> -455068 | U25: =E25+J25+O25 -> -455068
A26: 6. - Other Reversals | C26: -105195 | D26: -293749 | E26: -293749 | H26: -61960 | I26: -488735 | J26: -488735 | M26: -140582 | N26: -1096190 | O26: -1096190 | R26: =B26+G26+L26 -> 0 | S26: =C26+H26+M26 -> -307737 | T26: =D26+I26+N26 -> -1878674 | U26: =E26+J26+O26 -> -1878674
A27: Net ITC Availed | B27: =SUM(B21:B26) -> 0 | C27: =SUM(C21:C26) -> 633363 | D27: =SUM(D21:D26) -> 819919 | E27: =SUM(E21:E26) -> 819919 | G27: =SUM(G21:G26) -> 0 | H27: =SUM(H21:H26) -> 218245 | I27: =SUM(I21:I26) -> 622529 | J27: =SUM(J21:J26) -> 622529 | L27: =SUM(L21:L26) -> 0 | M27: =SUM(M21:M26) -> 222002 | N27: =SUM(N21:N26) -> 998866 | O27: =SUM(O21:O26) -> 998866 | R27: =SUM(R21:R26) -> 0 | S27: =SUM(S21:S26) -> 1073610 | T27: =SUM(T21:T26) -> 2441314 | U27: =SUM(U21:U26) -> 2441314 | V27: =SUM(R27:U27) -> 5956238
C29: -1
C30: -1

Sheet Annexure-B
A1: Softdel Systems Private Limited
A2: Annexure-B | D2: ACN2526000058808
I3: =SUBTOTAL(9,I7:I901) -> 2441313.7 | J3: =SUBTOTAL(9,J7:J901) -> 2441313.7 | K3: =SUBTOTAL(9,K7:K901) -> 1073609.1 | N3: =SUBTOTAL(9,N7:N901) -> 5956236.5
A4: Sr No. | B4: GSTIN of the supplier | C4: Name of the Supplier | D4: Invoice details | G4: Category of inputs supplies | I4: Central Tax | J4: State tax/Union Territory tax | K4: Integrated tax | L4: Cess | M4: Eligible for ITC | N4: Amount of Eligible ITC | O4: Months in GSTR-3B | P4: Serial Number in GSTR-2B | Q4: Months in GSTR-2B | R4: Remarks
D5: Invoice No. | E5: Date | F5: Invoice Value | G5: Inputs/Inputs Services/capital goods | H5: HSN/SAC | M5: Yes/No/Partially
A6: 1 | B6: 2 | C6: 3 | D6: 4 | E6: 5 | F6: 6 | G6: 7 | H6: 8 | I6: 9 | J6: 10 | K6: 11 | L6: 12 | M6: 13 | N6: 14 | O6: 15 | P6: 16 | Q6: 17 | R6: 18
A7: 1 | B7: IMPS | C7: Zoom Video Communications Inc. | D7: INV325785229 | E7: 45944 | F7: 984 | G7: Input Service | H7: 0 | I7: 0 | J7: 0 | K7: 150 | L7: 0 | M7: Yes | N7: 150 | O7: 45931 | P7: IMPS | Q7: 45931 | R7: IMPS
A8: 2 | B8: IMPS | C8: GitHub, Inc. | D8: INV102317885 | E8: 45931 | F8: 88626 | G8: Input Service | H8: 0 | I8: 0 | J8: 0 | K8: 13519 | L8: 0 | M8: Yes | N8: 13519 | O8: 45931 | P8: IMPS | Q8: 45931 | R8: IMPS
A9: 3 | B9: IMPS | C9: GitHub, Inc. | D9: INV101861196 | E9: 45928 | F9: 4774 | G9: Input Service | H9: 0 | I9: 0 | J9: 0 | K9: 728 | L9: 0 | M9: Yes | N9: 728 | O9: 45931 | P9: IMPS | Q9: 45931 | R9: IMPS
A10: 4 | B10: IMPS | C10: GitHub, Inc. | D10: INV101864279 | E10: 45928 | F10: 11719 | G10: Input Service | H10: 0 | I10: 0 | J10: 0 | K10: 1788 | L10: 0 | M10: Yes | N10: 1788 | O10: 45931 | P10: IMPS | Q10: 45931 | R10: IMPS
A11: 5 | B11: IMPS | C11: GitHub, Inc. | D11: INV103201239 | E11: 45938 | F11: 11340 | G11: Input Service | H11: 0 | I11: 0 | J11: 0 | K11: 1730 | L11: 0 | M11: Yes | N11: 1730 | O11: 45931 | P11: IMPS | Q11: 45931 | R11: IMPS
A12: 6 | B12: IMPS | C12: GitHub, Inc. | D12: INV103796429 | E12: 45943 | F12: 216 | G12: Input Service | H12: 0 | I12: 0 | J12: 0 | K12: 33 | L12: 0 | M12: Yes | N12: 33 | O12: 45931 | P12: IMPS | Q12: 45931 | R12: IMPS
A13: 7 | B13: IMPS | C13: Zoom Video Communications Inc. | D13: INV325267738 | E13: 45940 | F13: 18301 | G13: Input Service | H13: 0 | I13: 0 | J13: 0 | K13: 2792 | L13: 0 | M13: Yes | N13: 2792 | O13: 45931 | P13: IMPS | Q13: 45931 | R13: IMPS
A14: 8 | B14: 27AASCS3903K1ZV | C14: SEMSYS PRIVATE LIMITED | D14: 2526350 | E14: 01/10/2025 | F14: 11564 | G14: Input Service | H14: 998332 | I14: 882 | J14: 882 | K14: 0 | L14: 0 | M14: No | N14: 1764 | O14: 45931 | P14: 2596 | Q14: 45931 | R14: All other ITC
A15: 9 | B15: 27AASCS3903K1ZV | C15: SEMSYS PRIVATE LIMITED | D15: 2526351 | E15: 01/10/2025 | F15: 9440 | G15: Input Service | H15: 998332 | I15: 720 | J15: 720 | K15: 0 | L15: 0 | M15: No | N15: 1440 | O15: 45931 | P15: 2597 | Q15: 45931 | R15: All other ITC
A16: 10 | B16: 27AASCS3903K1ZV | C16: SEMSYS PRIVATE LIMITED | D16: 2526352 | E16: 01/10/2025 | F16: 9440 | G16: Input Service | H16: 998332 | I16: 720 | J16: 720 | K16: 0 | L16: 0 | M16: No | N16: 1440 | O16: 45931 | P16: 2598 | Q16: 45931 | R16: All other ITC
A17: 11 | B17: 27AASCS3903K1ZV | C17: SEMSYS PRIVATE LIMITED | D17: 2526353 | E17: 01/10/2025 | F17: 4720 | G17: Input Service | H17: 998332 | I17: 360 | J17: 360 | K17: 0 | L17: 0 | M17: No | N17: 720 | O17: 45931 | P17: 2599 | Q17: 45931 | R17: All other ITC
A18: 12 | B18: 27AASCS3903K1ZV | C18: SEMSYS PRIVATE LIMITED | D18: 2526354 | E18: 01/10/2025 | F18: 4720 | G18: Input Service | H18: 998332 | I18: 360 | J18: 360 | K18: 0 | L18: 0 | M18: No | N18: 720 | O18: 45931 | P18: 2600 | Q18: 45931 | R18: All other ITC
A19: 13 | B19: 27AASCS3903K1ZV | C19: SEMSYS PRIVATE LIMITED | D19: 2526355 | E19: 01/10/2025 | F19: 23600 | G19: Input Service | H19: 998332 | I19: 1800 | J19: 1800 | K19: 0 | L19: 0 | M19: No | N19: 3600 | O19: 45931 | P19: 2601 | Q19: 45931 | R19: All other ITC
A20: 14 | B20: 27AAGCR8772D1Z2 | C20: Porter | D20: CRN1267653331 | E20: 30/09/2025 | F20: 118 | G20: Input Service | H20: 996511 | I20: 9 | J20: 9 | K20: 0 | L20: 0 | M20: No | N20: 18 | O20: 45931 | P20: 877 | Q20: 45931 | R20: All other ITC
A21: 15 | B21: 27AIFPK3096H1Z3 | C21: RAJ ELECTRICALS | D21: 63210 | E21: 10/10/2025 | F21: 413 | G21: Inputs | H21: 0 | I21: 31.5 | J21: 31.5 | K21: 0 | L21: 0 | M21: No | N21: 63 | O21: 45931 | P21: 2728 | Q21: 45931 | R21: All other ITC
A22: 16 | B22: 27AAMFD2812K1ZC | C22: DESIGNSTYLE STUDIOS | D22: 69 | E22: 11/08/2025 | F22: 1770 | H22: 0 | I22: 135 | J22: 135 | K22: 0 | L22: 0 | M22: No | N22: 270 | O22: 45931 | P22: 2724 | Q22: 45931 | R22: All other ITC
A23: 17 | B23: 03ACCPS7232A1Z5 | C23: ELECTRO SALES | D23: ES-ECOM-179 | E23: 06/10/2025 | F23: 1330 | H23: 0 | I23: 0 | J23: 0 | K23: 202.88 | L23: 0 | M23: No | N23: 202.88 | O23: 45931 | P23: 2605 | Q23: 45931 | R23: All other ITC
A24: 18 | B24: 27AAACU4322N1Z6 | C24: UPS EXPRESS PRIVATE LIMITED | D24: 427100363393 | E24: 29/10/2025 | F24: 5272.24 | G24: Input Service | H24: 996813 | I24: 402.12 | J24: 402.12 | K24: 0 | L24: 0 | M24: No | N24: 804.24 | O24: 45931 | P24: 2723 | Q24: 45931 | R24: All other ITC
A25: 19 | B25: 27AAACU4322N1Z6 | C25: UPS EXPRESS PRIVATE LIMITED | D25: 427100360338 | E25: 05/10/2025 | F25: 929.84 | G25: Input Service | H25: 996813 | I25: 70.92 | J25: 70.92 | K25: 0 | L25: 0 | M25: No | N25: 141.84 | O25: 45931 | P25: 2722 | Q25: 45931 | R25: All other ITC
A26: 20 | B26: 07AAACJ0054A1ZD | C26: JETWAYS TRAVELS PVT.LTD. | D26: HP501130 | E26: 31/10/2025 | F26: 16402 | G26: Input Service | H26: 998551 | I26: 0 | J26: 0 | K26: 2502 | L26: 0 | M26: No | N26: 2502 | O26: 45931 | P26: 2719 | Q26: 45931 | R26: All other ITC
A27: 21 | B27: 07AAACJ0054A1ZD | C27: JETWAYS TRAVELS PVT.LTD. | D27: HP501109 | E27: 27/10/2025 | F27: 8260 | G27: Input Service | H27: 998551 | I27: 0 | J27: 0 | K27: 1260 | L27: 0 | M27: No | N27: 1260 | O27: 45931 | P27: 2718 | Q27: 45931 | R27: All other ITC
A28: 22 | B28: 07AAACJ0054A1ZD | C28: JETWAYS TRAVELS PVT.LTD. | D28: HP501108 | E28: 27/10/2025 | F28: 8968 | G28: Input Service | H28: 998551 | I28: 0 | J28: 0 | K28: 1368 | L28: 0 | M28: No | N28: 1368 | O28: 45931 | P28: 2717 | Q28: 45931 | R28: All other ITC
A29: 23 | B29: 07AAACJ0054A1ZD | C29: JETWAYS TRAVELS PVT.LTD. | D29: DP525244 | E29: 25/10/2025 | F29: 118 | G29: Input Service | H29: 998551 | I29: 0 | J29: 0 | K29: 18 | L29: 0 | M29: No | N29: 18 | O29: 45931 | P29: 2712 | Q29: 45931 | R29: All other ITC
A30: 24 | B30: 07AAACJ0054A1ZD | C30: JETWAYS TRAVELS PVT.LTD. | D30: DP525243 | E30: 25/10/2025 | F30: 118 | G30: Input Service | H30: 998551 | I30: 0 | J30: 0 | K30: 18 | L30: 0 | M30: No | N30: 18 | O30: 45931 | P30: 2711 | Q30: 45931 | R30: All other ITC
A31: 25 | B31: 27AAWCS5258F1ZQ | C31: SMARTWORKS COWORKING SPACES LIMITED | D31: PUN06/SC25/00761 | E31: 22/10/2025 | F31: 3404409.7 | G31: Input Service | H31: 997212 | I31: 259658.37 | J31: 259658.37 | K31: 0 | L31: 0 | M31: No | N31: 519316.74 | O31: 45931 | P31: 2703 | Q31: 45931 | R31: All other ITC
A32: 26 | B32: 06AADCH6128C1ZZ | C32: Handy Online Solutions Private Limited | D32: ONGRID061722397 | E32: 29/10/2025 | F32: 7278.24 | G32: Inputs | H32: 853669 | I32: 0 | J32: 0 | K32: 1110.24 | L32: 0 | M32: No | N32: 1110.24 | O32: 45931 | P32: 2695 | Q32: 45931 | R32: All other ITC
A33: 27 | B33: 27ARCPK9149B1ZU | C33: UNIVERSAL ELECTRICALS | D33: 8919 | E33: 15/10/2025 | F33: 2076.8 | G33: Inputs | H33: 0 | I33: 158.4 | J33: 158.4 | K33: 0 | L33: 0 | M33: No | N33: 316.8 | O33: 45931 | P33: 2692 | Q33: 45931 | R33: All other ITC
A34: 28 | B34: 27AAACB2100P1ZX | C34: Vodafone Idea Limited | D34: MHI1410526435759 | E34: 09/10/2025 | F34: 411.82 | G34: Input Service | H34: 998413 | I34: 31.41 | J34: 31.41 | K34: 0 | L34: 0 | M34: No | N34: 62.82 | O34: 45931 | P34: 2691 | Q34: 45931 | R34: All other ITC
A35: 29 | B35: 36AEUPV4314A1ZE | C35: Vegesna Akshaya Avyanga Industries | D35: 014/2025-2026 | E35: 30/10/2025 | F35: 295000 | G35: Input Service | H35: 998313 | I35: 0 | J35: 0 | K35: 45000 | L35: 0 | M35: No | N35: 45000 | O35: 45931 | P35: 2686 | Q35: 45931 | R35: All other ITC
A36: 30 | B36: 27AABCC7181N2Z7 | C36: SWISS INTERNATIONAL AIR LINES LTD. | D36: LXBOM251000654 | E36: 08/10/2025 | F36: 105483 | G36: Inputs | H36: 440362 | I36: 2511.5 | J36: 2511.5 | K36: 0 | L36: 0 | M36: No | N36: 5023 | O36: 45931 | P36: 2680 | Q36: 45931 | R36: All other ITC
A37: 31 | B37: 27AABCF6516A1Z3 | C37: FEDEX EXPRESS TRANSPORTATION AND SUPPLY CHAIN SERVICES (I) PRIVATE LIMITED | D37: BOM-C-279329 | E37: 25/10/2025 | F37: 944 | G37: Input Service | H37: 996812 | I37: 72 | J37: 72 | K37: 0 | L37: 0 | M37: No | N37: 144 | O37: 45931 | P37: 2679 | Q37: 45931 | R37: All other ITC
A38: 32 | B38: 06AAACM5586C1ZL | C38: Microsoft Corporation (India) Pvt Ltd | D38: TIO26HR101264303 | E38: 27/10/2025 | F38: 1253.16 | G38: Input Service | H38: 998313 | I38: 0 | J38: 0 | K38: 191.16 | L38: 0 | M38: No | N38: 191.16 | O38: 45931 | P38: 2678 | Q38: 45931 | R38: All other ITC
A39: 33 | B39: 27AABCD3611Q1ZI | C39: DHL EXPRESS (INDIA) PRIVATE LIMITED | D39: BOM160246 | E39: 07/10/2025 | F39: 1298 | G39: Input Service | H39: 996812 | I39: 99 | J39: 99 | K39: 0 | L39: 0 | M39: No | N39: 198 | O39: 45931 | P39: 2677 | Q39: 45931 | R39: All other ITC
A40: 34 | B40: 27AAECI7859N1ZQ | C40: Maars Creative Concepts Private Limited | D40: SOFT/594/25-26 | E40: 30/10/2025 | F40: 743.4 | G40: Inputs | H40: 482090 | I40: 56.7 | J40: 56.7 | K40: 0 | L40: 0 | M40: No | N40: 113.4 | O40: 45931 | P40: 2672 | Q40: 45931 | R40: All other ITC
A41: 35 | B41: 27AAECI7859N1ZQ | C41: Maars Creative Concepts Private Limited | D41: SOFT/581/25-26 | E41: 18/10/2025 | F41: 247.8 | G41: Inputs | H41: 482090 | I41: 18.9 | J41: 18.9 | K41: 0 | L41: 0 | M41: No | N41: 37.8 | O41: 45931 | P41: 2671 | Q41: 45931 | R41: All other ITC
A42: 36 | B42: 27AAECI7859N1ZQ | C42: Maars Creative Concepts Private Limited | D42: SOFT/560/25-26 | E42: 13/10/2025 | F42: 826 | G42: Inputs | H42: 482090 | I42: 63 | J42: 63 | K42: 0 | L42: 0 | M42: No | N42: 126 | O42: 45931 | P42: 2670 | Q42: 45931 | R42: All other ITC
A43: 37 | B43: 27AAECI7859N1ZQ | C43: Maars Creative Concepts Private Limited | D43: SOFT/540/25-26 | E43: 06/10/2025 | F43: 123.9 | G43: Inputs | H43: 482090 | I43: 9.45 | J43: 9.45 | K43: 0 | L43: 0 | M43: No | N43: 18.9 | O43: 45931 | P43: 2669 | Q43: 45931 | R43: All other ITC
A44: 38 | B44: 27DBRPP0459R1ZK | C44: Shree Caterers | D44: 2025-26/476 | E44: 31/10/2025 | F44: 2520 | G44: Input Service | H44: 99633 | I44: 60 | J44: 60 | K44: 0 | L44: 0 | M44: No | N44: 120 | O44: 45931 | P44: 2626 | Q44: 45931 | R44: All other ITC
A45: 39 | B45: 27AAACC2498P1Z3 | C45: CENTRAL BANK OF INDIA | D45: 26271C0003803394 | E45: 31/10/2025 | F45: 0.56 | G45: Inputs | H45: 440173 | I45: 0.04 | J45: 0.04 | K45: 0 | L45: 0 | M45: No | N45: 0.08 | O45: 45931 | P45: 2627 | Q45: 45931 | R45: All other ITC
... A51: 45 | B51: 27AISPB8261G1Z0 | C51: BHUTADA ENTERPRISES | D51: SH0038-0019417 | E51: 29/10/2025 | F51: 1820 | G51: Inputs | H51: 29152100 | I51: 47.01 | J51: 47.01 | K51: 0 | L51: 0 | M51: No | N51: 94.02 | O51: 45931 | P51: 2633 | Q51: 45931 | R51: All other ITC
A52: 46 | B52: 27AZJPG1481H1ZC | C52: OM SAI SECURITY AND MANPOWER SERVICES / OM SAI TOURS AND TRAVELS | D52: 5904 | E52: 31/10/2025 | F52: 10269 | G52: Input Service | H52: 996813 | I52: 244.5 | J52: 244.5 | K52: 0 | L52: 0 | M52: No | N52: 489 | O52: 45931 | P52: 2660 | Q52: 45931 | R52: All other ITC
A53: 47 | B53: 27AZJPG1481H1ZC | C53: OM SAI SECURITY AND MANPOWER SERVICES / OM SAI TOURS AND TRAVELS | D53: 5824 | E53: 31/10/2025 | F53: 4925.56 | G53: Input Service | H53: 996813 | I53: 117.28 | J53: 117.28 | K53: 0 | L53: 0 | M53: No | N53: 234.56 | O53: 45931 | P53: 2659 | Q53: 45931 | R53: All other ITC
A54: 48 | B54: 27AABCR0111M1ZN | C54: ROYAL ORCHID HOTELS LIMITED | D54: ROCP-2526-12575 | E54: 16/10/2025 | F54: 791.73 | G54: Input Service | H54: 996311 | I54: 60.39 | J54: 60.39 | K54: 0 | L54: 0 | M54: No | N54: 120.78 | O54: 45931 | P54: 2636 | Q54: 45931 | R54: All other ITC
A55: 49 | B55: 27AZJPG1481H1ZC | C55: OM SAI SECURITY AND MANPOWER SERVICES / OM SAI TOURS AND TRAVELS | D55: 5796 | E55: 31/10/2025 | F55: 5187 | G55: Input Service | H55: 996813 | I55: 123.5 | J55: 123.5 | K55: 0 | L55: 0 | M55: No | N55: 247 | O55: 45931 | P55: 2658 | Q55: 45931 | R55: All other ITC
A56: 50 | B56: 27AZJPG1481H1ZC | C56: OM SAI SECURITY AND MANPOWER SERVICES / OM SAI TOURS AND TRAVELS | D56: 5795 | E56: 31/10/2025 | F56: 5234.26 | G56: Input Service | H56: 996813 | I56: 124.63 | J56: 124.63 | K56: 0 | L56: 0 | M56: No | N56: 249.26 | O56: 45931 | P56: 2657 | Q56: 45931 | R56: All other ITC
A57: 51 | B57: 27AZJPG1481H1ZC | C57: OM SAI SECURITY AND MANPOWER SERVICES / OM SAI TOURS AND TRAVELS | D57: 5763 | E57: 31/10/2025 | F57: 10958.86 | G57: Input Service | H57: 996813 | I57: 260.93 | J57: 260.93 | K57: 0 | L57: 0 | M57: No | N57: 521.86 | O57: 45931 | P57: 2656 | Q57: 45931 | R57: All other ITC
A58: 52 | B58: 27ABBPM0253H1ZZ | C58: J RAY HARDWARE / J RAY ENGINEERING CO. | D58: JRH-15960 | E58: 10/10/2025 | F58: 426.22 | H58: 0 | I58: 32.51 | J58: 32.51 | K58: 0 | L58: 0 | M58: No | N58: 65.02 | O58: 45931 | P58: 2640 | Q58: 45931 | R58: All other ITC
A59: 53 | B59: 27AAACI1195H1ZM | C59: ICICI BANK LIMITED | D59: 135251007031815 | E59: 07/10/2025 | F59: 13463.32 | G59: Input Service | H59: 997157 | I59: 1026.86 | J59: 1026.86 | K59: 0 | L59: 0 | M59: No | N59: 2053.72 | O59: 45931 | P59: 2641 | Q59: 45931 | R59: All other ITC
A60: 54 | B60: 27AAACI1195H1ZM | C60: ICICI BANK LIMITED | D60: 135251013059916 | E60: 13/10/2025 | F60: 17866.26 | G60: Input Service | H60: 997157 | I60: 1362.68 | J60: 1362.68 | K60: 0 | L60: 0 | M60: No | N60: 2725.36 | O60: 45931 | P60: 2642 | Q60: 45931 | R60: All other ITC
A61: 55 | B61: 27AAACI1195H1ZM | C61: ICICI BANK LIMITED | D61: 135251017090732 | E61: 17/10/2025 | F61: 16702.81 | G61: Input Service | H61: 997157 | I61: 1273.94 | J61: 1273.94 | K61: 0 | L61: 0 | M61: No | N61: 2547.88 | O61: 45931 | P61: 2643 | Q61: 45931 | R61: All other ITC
A62: 56 | B62: 27AAACI1195H1ZM | C62: ICICI BANK LIMITED | D62: 135251024114788 | E62: 24/10/2025 | F62: 17728.95 | G62: Input Service | H62: 997157 | I62: 1352.21 | J62: 1352.21 | K62: 0 | L62: 0 | M62: No | N62: 2704.42 | O62: 45931 | P62: 2644 | Q62: 45931 | R62: All other ITC
A63: 57 | B63: 27AAACI1195H1ZM | C63: ICICI BANK LIMITED | D63: 135251024114824 | E63: 24/10/2025 | F63: 17728.95 | G63: Input Service | H63: 997157 | I63: 1352.21 | J63: 1352.21 | K63: 0 | L63: 0 | M63: No | N63: 2704.42 | O63: 45931 | P63: 2645 | Q63: 45931 | R63: All other ITC
A64: 58 | B64: 27AAACI1195H1ZM | C64: ICICI BANK LIMITED | D64: 135251031156281 | E64: 31/10/2025 | F64: 16814.42 | G64: Input Service | H64: 997157 | I64: 1282.46 | J64: 1282.46 | K64: 0 | L64: 0 | M64: No | N64: 2564.92 | O64: 45931 | P64: 2646 | Q64: 45931 | R64: All other ITC
A65: 59 | B65: 27AAACI1195H1ZM | C65: ICICI BANK LIMITED | D65: TS61315298202510 | E65: 31/10/2025 | F65: 590 | G65: Input Service | H65: 997157 | I65: 45 | J65: 45 | K65: 0 | L65: 0 | M65: No | N65: 90 | O65: 45931 | P65: 2647 | Q65: 45931 | R65: All other ITC
A66: 60 | B66: 27AAACI1195H1ZM | C66: ICICI BANK LIMITED | D66: TS61898693202510 | E66: 31/10/2025 | F66: 2360 | G66: Input Service | H66: 997157 | I66: 180 | J66: 180 | K66: 0 | L66: 0 | M66: No | N66: 360 | O66: 45931 | P66: 2648 | Q66: 45931 | R66: All other ITC
A67: 61 | B67: 27AAACI1195H1ZM | C67: ICICI BANK LIMITED | D67: TS63153615202510 | E67: 31/10/2025 | F67: 4720 | G67: Input Service | H67: 997157 | I67: 360 | J67: 360 | K67: 0 | L67: 0 | M67: No | N67: 720 | O67: 45931 | P67: 2649 | Q67: 45931 | R67: All other ITC
A68: 62 | B68: 27AAIFR9573K1ZE | C68: RAJIV ELECTRONICS | D68: HCA6254 | E68: 13/10/2025 | F68: 575.26 | G68: Inputs | H68: 773833 | I68: 43.88 | J68: 43.88 | K68: 0 | L68: 0 | M68: No | N68: 87.76 | O68: 45931 | P68: 2650 | Q68: 45931 | R68: All other ITC
A69: 63 | B69: 36AAJCA3639B1ZX | C69: M/S ARGUS EMBEDDED SYSTEMS PRIVATE LIMITED | D69: AE-INV-2526-0899 | E69: 31/10/2025 | F69: 275553.6 | G69: Input Service | H69: 998112 | I69: 0 | J69: 0 | K69: 42033.6 | L69: 0 | M69: No | N69: 42033.6 | O69: 45931 | P69: 2651 | Q69: 45931 | R69: All other ITC
A70: 64 | B70: 36AAJCA3639B1ZX | C70: M/S ARGUS EMBEDDED SYSTEMS PRIVATE LIMITED | D70: AE-INV-2526-0900 | E70: 31/10/2025 | F70: 75331.2 | G70: Input Service | H70: 998112 | I70: 0 | J70: 0 | K70: 11491.2 | L70: 0 | M70: No | N70: 11491.2 | O70: 45931 | P70: 2652 | Q70: 45931 | R70: All other ITC
A71: 65 | B71: 27AZJPG1481H1ZC | C71: OM SAI SECURITY AND MANPOWER SERVICES / OM SAI TOURS AND TRAVELS | D71: 5760 | E71: 31/10/2025 | F71: 7555.8 | G71: Input Service | H71: 996813 | I71: 179.9 | J71: 179.9 | K71: 0 | L71: 0 | M71: No | N71: 359.8 | O71: 45931 | P71: 2653 | Q71: 45931 | R71: All other ITC
A72: 66 | B72: 27AZJPG1481H1ZC | C72: OM SAI SECURITY AND MANPOWER SERVICES / OM SAI TOURS AND TRAVELS | D72: 5761 | E72: 31/10/2025 | F72: 5218.5 | G72: Input Service | H72: 996813 | I72: 124.25 | J72: 124.25 | K72: 0 | L72: 0 | M72: No | N72: 248.5 | O72: 45931 | P72: 2654 | Q72: 45931 | R72: All other ITC
A73: 67 | B73: 27AZJPG1481H1ZC | C73: OM SAI SECURITY AND MANPOWER SERVICES / OM SAI TOURS AND TRAVELS | D73: 5762 | E73: 31/10/2025 | F73: 5101.96 | G73: Input Service | H73: 996813 | I73: 121.48 | J73: 121.48 | K73: 0 | L73: 0 | M73: No | N73: 242.96 | O73: 45931 | P73: 2655 | Q73: 45931 | R73: All other ITC
A74: 68 | B74: 07AAACJ0054A1ZD | C74: JETWAYS TRAVELS PVT.LTD. | D74: DP523155 | E74: 07/10/2025 | F74: 118 | G74: Input Service | H74: 998551 | I74: 0 | J74: 0 | K74: 18 | L74: 0 | M74: Yes | N74: 18 | O74: 45931 | P74: 2710 | Q74: 45931 | R74: All other ITC
A75: 69 | B75: 27AABCM2461K1ZF | C75: MAGARPATTA TOWNSHIP DEVP & CONST COMPANY LTD | D75: PM012610/019447 | E75: 03/10/2025 | F75: 127.2 | G75: Input Service | H75: 997221 | I75: 10 | J75: 10 | K75: 0 | L75: 0 | M75: Yes | N75: 20 | O75: 45931 | P75: 2709 | Q75: 45931 | R75: All other ITC
A76: 70 | B76: 27AABCK3418J1ZK | C76: KANJI FOREX PRIVATE LIMITED | D76: SP/2526/1/4179 | E76: 08/10/2025 | F76: 295 | G76: Input Service | H76: 997157 | I76: 22.5 | J76: 22.5 | K76: 0 | L76: 0 | M76: Yes | N76: 45 | O76: 45931 | P76: 2732 | Q76: 45931 | R76: All other ITC
A77: 71 | B77: 27AABCK3418J1ZK | C77: KANJI FOREX PRIVATE LIMITED | D77: PP/2526/2/633 | E77: 29/10/2025 | F77: 295 | G77: Input Service | H77: 997157 | I77: 22.5 | J77: 22.5 | K77: 0 | L77: 0 | M77: Yes | N77: 45 | O77: 45931 | P77: 2731 | Q77: 45931 | R77: All other ITC
A78: 72 | B78: 27AABCK3418J1ZK | C78: KANJI FOREX PRIVATE LIMITED | D78: PP/2526/2/628 | E78: 27/10/2025 | F78: 295 | G78: Input Service | H78: 997157 | I78: 22.5 | J78: 22.5 | K78: 0 | L78: 0 | M78: Yes | N78: 45 | O78: 45931 | P78: 2730 | Q78: 45931 | R78: All other ITC
A79: 73 | B79: 27AABCK3418J1ZK | C79: KANJI FOREX PRIVATE LIMITED | D79: PP/2526/2/573 | E79: 03/10/2025 | F79: 353.06 | G79: Input Service | H79: 997157 | I79: 26.93 | J79: 26.93 | K79: 0 | L79: 0 | M79: Yes | N79: 53.86 | O79: 45931 | P79: 2729 | Q79: 45931 | R79: All other ITC
A80: 74 | B80: 27AAEFP1428R1ZS | C80: PRICE WATERHOUSE & CO LLP | D80: 19226077636 | E80: 29/10/2025 | F80: 1930059 | G80: Input Service | H80: 998231 | I80: 147208 | J80: 147208 | K80: 0 | L80: 0 | M80: Yes | N80: 294416 | O80: 45931 | P80: 2725 | Q80: 45931 | R80: All other ITC
A81: 75 | B81: 27AAACT2209D2ZT | C81: TUV INDIA PVT LTD. | D81: MH2526015870 | E81: 27/10/2025 | F81: 1045480 | G81: Input Service | H81: 998346 | I81: 79740 | J81: 79740 | K81: 0 | L81: 0 | M81: Yes | N81: 159480 | O81: 45931 | P81: 2727 | Q81: 45931 | R81: All other ITC
A82: 76 | B82: 27AAACA4269Q1Z6 | C82: MIZUHO CAPSAVE FINANCE PRIVATE LIMITED | D82: B1MH2526/005845 | E82: 01/10/2025 | F82: 834440.41 | G82: Input Service | H82: 997315 | I82: 63643.76 | J82: 63643.76 | K82: 0 | L82: 0 | M82: Yes | N82: 127287.52 | O82: 45931 | P82: 2682 | Q82: 45931 | R82: All other ITC
A83: 77 | B83: 27AABCM2461K1ZF | C83: MAGARPATTA TOWNSHIP DEVP & CONST COMPANY LTD | D83: PM012610/019446 | E83: 03/10/2025 | F83: 506.8 | G83: Input Service | H83: 997221 | I83: 39 | J83: 39 | K83: 0 | L83: 0 | M83: Yes | N83: 78 | O83: 45931 | P83: 2708 | Q83: 45931 | R83: All other ITC
A84: 78 | B84: 27AABCK3418J1ZK | C84: KANJI FOREX PRIVATE LIMITED | D84: SP/2526/2/2449 | E84: 09/10/2025 | F84: 531 | G84: Input Service | H84: 997157 | I84: 40.5 | J84: 40.5 | K84: 0 | L84: 0 | M84: Yes | N84: 81 | O84: 45931 | P84: 2734 | Q84: 45931 | R84: All other ITC
A85: 79 | B85: 07AAACJ0054A1ZD | C85: JETWAYS TRAVELS PVT.LTD. | D85: IP502500 | E85: 08/10/2025 | F85: 826 | G85: Input Service | H85: 998551 | I85: 0 | J85: 0 | K85: 126 | L85: 0 | M85: Yes | N85: 126 | O85: 45931 | P85: 2721 | Q85: 45931 | R85: All other ITC
A86: 80 | B86: 07AAACJ0054A1ZD | C86: JETWAYS TRAVELS PVT.LTD. | D86: IP502470 | E86: 07/10/2025 | F86: 826 | G86: Input Service | H86: 998551 | I86: 0 | J86: 0 | K86: 126 | L86: 0 | M86: Yes | N86: 126 | O86: 45931 | P86: 2720 | Q86: 45931 | R86: All other ITC
A87: 81 | B87: 27AABCK3418J1ZK | C87: KANJI FOREX PRIVATE LIMITED | D87: SP/2526/2/2311 | E87: 03/10/2025 | F87: 860.62 | G87: Input Service | H87: 997157 | I87: 65.64 | J87: 65.64 | K87: 0 | L87: 0 | M87: Yes | N87: 131.28 | O87: 45931 | P87: 2733 | Q87: 45931 | R87: All other ITC
A88: 82 | B88: 27AABCK3418J1ZK | C88: KANJI FOREX PRIVATE LIMITED | D88: SP/2526/2/2557 | E88: 15/10/2025 | F88: 1052.56 | G88: Input Service | H88: 997157 | I88: 80.28 | J88: 80.28 | K88: 0 | L88: 0 | M88: Yes | N88: 160.56 | O88: 45931 | P88: 2735 | Q88: 45931 | R88: All other ITC
A89: 83 | B89: 36AABCI2726B1Z3 | C89: INTER GLOBE AVIATION LIMITED INDIGO | D89: TS1252610BE70683 | E89: 08/10/2025 | F89: 3470 | G89: Input Service | H89: 996425 | I89: 0 | J89: 0 | K89: 199 | L89: 0 | M89: Yes | N89: 199 | O89: 45931 | P89: 2668 | Q89: 45931 | R89: All other ITC
A90: 84 | B90: 27AAECG2483J1ZE | C90: GNR SOLUTION PRIVATE LIMITED | D90: GNR/R/25-26/2657 | E90: 10/10/2025 | F90: 1770 | G90: Input Service | H90: 997315 | I90: 135 | J90: 135 | K90: 0 | L90: 0 | M90: Yes | N90: 270 | O90: 45931 | P90: 2697 | Q90: 45931 | R90: All other ITC
A91: 85 | B91: 27AABCR0111M1ZN | C91: ROYAL ORCHID HOTELS LIMITED | D91: ROCP-2526-12574 | E91: 16/10/2025 | F91: 6037.52 | G91: Input Service | H91: 996311 | I91: 143.76 | J91: 143.76 | K91: 0 | L91: 0 | M91: Yes | N91: 287.52 | O91: 45931 | P91: 2635 | Q91: 45931 | R91: All other ITC
A92: 86 | B92: 07AALCC6699P1ZJ | C92: COMMBITZ ESIM PRIVATE LIMITED | D92: CM202526000413 | E92: 07/10/2025 | F92: 1904.52 | G92: Input Service | H92: 9984 | I92: 0 | J92: 0 | K92: 290.52 | L92: 0 | M92: Yes | N92: 290.52 | O92: 45931 | P92: 2739 | Q92: 45931 | R92: All other ITC
... A95: 89 | B95: 07AACCN6194P2ZQ | C95: AIR INDIA LIMITED | D95: 072612BP10AFD825 | E95: 25/10/2025 | F95: 7353 | G95: Input Service | H95: 996425 | I95: 0 | J95: 0 | K95: 351 | L95: 0 | M95: Yes | N95: 351 | O95: 45931 | P95: 2681 | Q95: 45931 | R95: All other ITC
A96: 90 | B96: 27AAGCJ1813R1Z5 | C96: JYT LOGISTICS PRIVATE LIMITED | D96: 9520 | E96: 11/10/2025 | F96: 3540 | G96: Input Service | H96: 996712 | I96: 270 | J96: 270 | K96: 0 | L96: 0 | M96: Yes | N96: 540 | O96: 45931 | P96: 2726 | Q96: 45931 | R96: All other ITC
A97: 91 | B97: 27BMWPD2551E2ZZ | C97: ROOTS OFFICE SOLUTIONS | D97: S0006119 | E97: 21/09/2025 | F97: 4620.12 | G97: Inputs | H97: 3926 | I97: 333.06 | J97: 333.06 | K97: 0 | L97: 0 | M97: Yes | N97: 666.12 | O97: 45931 | P97: 2689 | Q97: 45931 | R97: All other ITC
A98: 92 | B98: 27AADCP7742E1ZD | C98: PRODUCT DOSSIER SOLUTIONS INDIA PRIVATE LIMITED | D98: PDS-25186 | E98: 03/10/2025 | F98: 610896.38 | G98: Input Service | H98: 998313 | I98: 46593.79 | J98: 46593.79 | K98: 0 | L98: 0 | M98: Yes | N98: 93187.58 | O98: 45931 | P98: 2693 | Q98: 45931 | R98: All other ITC
A99: 93 | B99: 27AAECG2483J1ZE | C99: GNR SOLUTION PRIVATE LIMITED | D99: GNR/R/25-26/2660 | E99: 10/10/2025 | F99: 473126.9 | G99: Input Service | H99: 997315 | I99: 36085.95 | J99: 36085.95 | K99: 0 | L99: 0 | M99: Yes | N99: 72171.9 | O99: 45931 | P99: 2700 | Q99: 45931 | R99: All other ITC
A100: 94 | B100: 27AATPE1292M1Z7 | C100: ERAGAM SIDHANTH REDDY | D100: OCT-2025-302 | E100: 01/10/2025 | F100: 413877.92 | G100: Input Service | H100: 997212 | I100: 31566.96 | J100: 31566.96 | K100: 0 | L100: 0 | M100: Yes | N100: 63133.92 | O100: 45931 | P100: 2665 | Q100: 45931 | R100: All other ITC
A101: 95 | B101: 27AATPE1295N1Z2 | C101: ERAGAM SANJEETH REDDY | D101: OCT-2025-303 | E101: 01/10/2025 | F101: 413877.92 | G101: Input Service | H101: 997212 | I101: 31566.96 | J101: 31566.96 | K101: 0 | L101: 0 | M101: Yes | N101: 63133.92 | O101: 45931 | P101: 2701 | Q101: 45931 | R101: All other ITC
A102: 96 | B102: 27AATPE1292M1Z7 | C102: ERAGAM SIDHANTH REDDY | D102: OCT-2025-301 | E102: 01/10/2025 | F102: 393496.96 | G102: Input Service | H102: 997212 | I102: 30012.48 | J102: 30012.48 | K102: 0 | L102: 0 | M102: Yes | N102: 60024.96 | O102: 45931 | P102: 2664 | Q102: 45931 | R102: All other ITC
A103: 97 | B103: 27AATPE1295N1Z2 | C103: ERAGAM SANJEETH REDDY | D103: OCT-2025-304 | E103: 01/10/2025 | F103: 393496.96 | G103: Input Service | H103: 997212 | I103: 30012.48 | J103: 30012.48 | K103: 0 | L103: 0 | M103: Yes | N103: 60024.96 | O103: 45931 | P103: 2702 | Q103: 45931 | R103: All other ITC
A104: 98 | B104: 27ABJCS6128G1Z4 | C104: SSBC GLOBAL LOGISTICS PRIVATE LIMITED | D104: 955/2025-26 | E104: 24/10/2025 | F104: 5254.54 | G104: Input Service | H104: 996812 | I104: 400.77 | J104: 400.77 | K104: 0 | L104: 0 | M104: Yes | N104: 801.54 | O104: 45931 | P104: 2637 | Q104: 45931 | R104: All other ITC
A105: 99 | B105: 27AAACH1458C1ZZ | C105: TATA TELESERVICES MAHARASHTRA LIMITED | D105: 2171776949 | E105: 15/10/2025 | F105: 6478.2 | G105: Input Service | H105: 998412 | I105: 494.1 | J105: 494.1 | K105: 0 | L105: 0 | M105: Yes | N105: 988.2 | O105: 45931 | P105: 2630 | Q105: 45931 | R105: All other ITC
A106: 100 | B106: 27AAACE6958L1Z4 | C106: EMBEE SOFTWARE P LTD | D106: MEGSI26/20548 | E106: 30/10/2025 | F106: 287580.94 | G106: Input Service | H106: 997331 | I106: 21934.14 | J106: 21934.14 | K106: 0 | L106: 0 | M106: Yes | N106: 43868.28 | O106: 45931 | P106: 2673 | Q106: 45931 | R106: All other ITC
A107: 101 | B107: 36AAFCK5835K1Z6 | C107: KEKA TECHNOLOGIES | D107: K06613-0009 | E107: 14/10/2025 | F107: 271178.51 | G107: Input Service | H107: 997331 | I107: 0 | J107: 0 | K107: 41366.21 | L107: 0 | M107: Yes | N107: 41366.21 | O107: 45931 | P107: 2602 | Q107: 45931 | R107: All other ITC
...

Sheet PR Conso (Oct 25-dec 2025)
A1: Softdel Systems Private Limited | N1: -1 | P1: Inputs | W1: 60 | X1: 64 | Y1: 1 | Z1: 2 | AA1: 34 | AB1: =SUBTOTAL(9,W1:AA1) -> 161
A2: Purchase Register | I2: =I4-I3 -> -0.89669506 | J2: =J4-J3 -> -0.31744398 | K2: =K4-K3 -> -0.31744398 | M2: -1 | P2: Input Service
A3: Period: October-25 to December-25 | I3: ='Monthly Return Summary'!S27 -> 1073610 | J3: ='Monthly Return Summary'!T27 -> 2441314 | K3: ='Monthly Return Summary'!U27 -> 2441314
G4: =SUBTOTAL(9,G6:G1048576) -> 54232601 | H4: =SUBTOTAL(9,H6:H1048576) -> 39993858 | I4: =SUBTOTAL(9,I6:I1048576) -> 1073609.1 | J4: =SUBTOTAL(9,J6:J1048576) -> 2441313.7 | K4: =SUBTOTAL(9,K6:K1048576) -> 2441313.7 | L4: =SUBTOTAL(9,L6:L1048576) -> 5956236.5
A5: Month | B5: GSTIN of supplier | C5: Trade/Legal name | D5: Invoice number | E5: Invoice Date | F5: Rate(%) | G5: Invoice Value(₹) | H5: Taxable Value (₹) | I5: Integrated Tax(₹) | J5: Central Tax(₹) | K5: State/UT Tax(₹) | L5: Total Tax | M5: GSTN and invoice number | N5: HSN Code | O5: Description of service | P5: Nature of Purchase | Q5: Serial No. in GSTR-2B | R5: ITC Taken in the month of / GSTR-2B month | S5: GSTR-3B month | T5: Eligibility | U5: Major Remarks | V5: Major Remarks-2 | W5: GSTR 3B remarks | Y5: t | AA5: c | AD5: TOTAL TAX | AE5: GSTIN AND INVOICE NUMBER
A6: 45931 | B6: IMPS | C6: Zoom Video Communications Inc. | D6: INV325785229 | E6: 45944 | F6: 0.17985612 | G6: 984 | H6: 834 | I6: 150 | J6: 0 | K6: 0 | L6: 150 | M6: INV325785229 | N6: 0 | O6: Membership & Subscription | P6: Input Service | Q6: IMPS | R6: 45931 | S6: 45931 | T6: Yes | U6: IMPS | W6: IMPS | Z6: =_xlfn.XLOOKUP(AC6,'[9]PR Conso (Apr 25-Sep 25)'!$P:$P,'[9]PR Conso (Apr 25-Sep 25)'!$Z:$Z) -> #N/A | AB6: 1 | AC6: =CONCATENATE(M6,AB6) -> INV3257852291
A7: 45931 | B7: IMPS | C7: GitHub, Inc. | D7: INV102317885 | E7: 45931 | F7: 0.17985612 | G7: 88626 | H7: 75107 | I7: 13519 | J7: 0 | K7: 0 | L7: 13519 | M7: INV102317885 | N7: 0 | O7: Membership & Subscription | P7: Input Service | Q7: IMPS | R7: 45931 | S7: 45931 | T7: Yes | U7: IMPS | W7: IMPS | Z7: =_xlfn.XLOOKUP(AC7,'[9]PR Conso (Apr 25-Sep 25)'!$P:$P,'[9]PR Conso (Apr 25-Sep 25)'!$Z:$Z) -> #N/A | AB7: =AB6+1 -> 2 | AC7: =CONCATENATE(M7,AB7) -> INV1023178852
A8: 45931 | B8: IMPS | C8: GitHub, Inc. | D8: INV101861196 | E8: 45928 | F8: 0.17985612 | G8: 4774 | H8: 4046 | I8: 728 | J8: 0 | K8: 0 | L8: 728 | M8: INV101861196 | N8: 0 | O8: Membership & Subscription | P8: Input Service | Q8: IMPS | R8: 45931 | S8: 45931 | T8: Yes | U8: IMPS | W8: IMPS | Z8: =_xlfn.XLOOKUP(AC8,'[9]PR Conso (Apr 25-Sep 25)'!$P:$P,'[9]PR Conso (Apr 25-Sep 25)'!$Z:$Z) -> #N/A | AB8: =AB7+1 -> 3 | AC8: =CONCATENATE(M8,AB8) -> INV1018611963
A9: 45931 | B9: IMPS | C9: GitHub, Inc. | D9: INV101864279 | E9: 45928 | F9: 0.17985612 | G9: 11719 | H9: 9931 | I9: 1788 | J9: 0 | K9: 0 | L9: 1788 | M9: INV101864279 | N9: 0 | O9: Membership & Subscription | P9: Input Service | Q9: IMPS | R9: 45931 | S9: 45931 | T9: Yes | U9: IMPS | W9: IMPS | Z9: =_xlfn.XLOOKUP(AC9,'[9]PR Conso (Apr 25-Sep 25)'!$P:$P,'[9]PR Conso (Apr 25-Sep 25)'!$Z:$Z) -> #N/A | AB9: =AB8+1 -> 4 | AC9: =CONCATENATE(M9,AB9) -> INV1018642794
A10: 45931 | B10: IMPS | C10: GitHub, Inc. | D10: INV103201239 | E10: 45938 | F10: 0.17985612 | G10: 11340 | H10: 9610 | I10: 1730 | J10: 0 | K10: 0 | L10: 1730 | M10: INV103201239 | N10: 0 | O10: Membership & Subscription | P10: Input Service | Q10: IMPS | R10: 45931 | S10: 45931 | T10: Yes | U10: IMPS | W10: IMPS | Z10: =_xlfn.XLOOKUP(AC10,'[9]PR Conso (Apr 25-Sep 25)'!$P:$P,'[9]PR Conso (Apr 25-Sep 25)'!$Z:$Z) -> #N/A | AB10: =AB9+1 -> 5 | AC10: =CONCATENATE(M10,AB10) -> INV1032012395
A11: 45931 | B11: IMPS | C11: GitHub, Inc. | D11: INV103796429 | E11: 45943 | F11: 0.17985612 | G11: 216 | H11: 183 | I11: 33 | J11: 0 | K11: 0 | L11: 33 | M11: INV103796429 | N11: 0 | O11: Membership & Subscription | P11: Input Service | Q11: IMPS | R11: 45931 | S11: 45931 | T11: Yes | U11: IMPS | W11: IMPS | Z11: =_xlfn.XLOOKUP(AC11,'[9]PR Conso (Apr 25-Sep 25)'!$P:$P,'[9]PR Conso (Apr 25-Sep 25)'!$Z:$Z) -> #N/A | AB11: =AB10+1 -> 6 | AC11: =CONCATENATE(M11,AB11) -> INV1037964296
A12: 45931 | B12: IMPS | C12: Zoom Video Communications Inc. | D12: INV325267738 | E12: 45940 | F12: 0.17985612 | G12: 18301 | H12: 15509 | I12: 2792 | J12: 0 | K12: 0 | L12: 2792 | M12: INV325267738 | N12: 0 | O12: Membership & Subscription | P12: Input Service | Q12: IMPS | R12: 45931 | S12: 45931 | T12: Yes | U12: IMPS | W12: IMPS | Z12: =_xlfn.XLOOKUP(AC12,'[9]PR Conso (Apr 25-Sep 25)'!$P:$P,'[9]PR Conso (Apr 25-Sep 25)'!$Z:$Z) -> #N/A | AB12: =AB11+1 -> 7 | AC12: =CONCATENATE(M12,AB12) -> INV3252677387
A13: 45931 | B13: 27AASCS3903K1ZV | C13: SEMSYS PRIVATE LIMITED | D13: 2526350 | E13: 01/10/2025 | F13: 0.17985612 | G13: 11564 | H13: 9800 | I13: 0 | J13: 882 | K13: 882 | L13: 1764 | M13: 27AASCS3903K1ZV2526350 | N13: 998332 | O13: Professional Fees | P13: Input Service | Q13: 2596 | R13: 45931 | S13: 45931 | T13: Yes | U13: Matched with 2B | W13: All other ITC | Z13: =_xlfn.XLOOKUP(AC13,'[9]PR Conso (Apr 25-Sep 25)'!$P:$P,'[9]PR Conso (Apr 25-Sep 25)'!$Z:$Z) -> #N/A | AB13: =AB12+1 -> 8 | AC13: =CONCATENATE(M13,AB13) -> 27AASCS3903K1ZV25263508
A14: 45931 | B14: 27AASCS3903K1ZV | C14: SEMSYS PRIVATE LIMITED | D14: 2526351 | E14: 01/10/2025 | F14: 0.17985612 | G14: 9440 | H14: 8000 | I14: 0 | J14: 720 | K14: 720 | L14: 1440 | M14: 27AASCS3903K1ZV2526351 | N14: 998332 | O14: Professional Fees | P14: Input Service | Q14: 2597 | R14: 45931 | S14: 45931 | T14: Yes | U14: Matched with 2B | W14: All other ITC | Z14: =_xlfn.XLOOKUP(AC14,'[9]PR Conso (Apr 25-Sep 25)'!$P:$P,'[9]PR Conso (Apr 25-Sep 25)'!$Z:$Z) -> #N/A | AB14: =AB13+1 -> 9 | AC14: =CONCATENATE(M14,AB14) -> 27AASCS3903K1ZV25263519
A15: 45931 | B15: 27AASCS3903K1ZV | C15: SEMSYS PRIVATE LIMITED | D15: 2526352 | E15: 01/10/2025 | F15: 0.17985612 | G15: 9440 | H15: 8000 | I15: 0 | J15: 720 | K15: 720 | L15: 1440 | M15: 27AASCS3903K1ZV2526352 | N15: 998332 | O15: Professional Fees | P15: Input Service | Q15: 2598 | R15: 45931 | S15: 45931 | T15: Yes | U15: Matched with 2B | W15: All other ITC | Z15: =_xlfn.XLOOKUP(AC15,'[9]PR Conso (Apr 25-Sep 25)'!$P:$P,'[9]PR Conso (Apr 25-Sep 25)'!$Z:$Z) -> #N/A | AB15: =AB14+1 -> 10 | AC15: =CONCATENATE(M15,AB15) -> 27AASCS3903K1ZV252635210
A16: 45931 | B16: 27AASCS3903K1ZV | C16: SEMSYS PRIVATE LIMITED | D16: 2526353 | E16: 01/10/2025 | F16: 0.17985612 | G16: 4720 | H16: 4000 | I16: 0 | J16: 360 | K16: 360 | L16: 720 | M16: 27AASCS3903K1ZV2526353 | N16: 998332 | O16: Professional Fees | P16: Input Service | Q16: 2599 | R16: 45931 | S16: 45931 | T16: Yes | U16: Matched with 2B | W16: All other ITC | Z16: =_xlfn.XLOOKUP(AC16,'[9]PR Conso (Apr 25-Sep 25)'!$P:$P,'[9]PR Conso (Apr 25-Sep 25)'!$Z:$Z) -> #N/A | AB16: =AB15+1 -> 11 | AC16: =CONCATENATE(M16,AB16) -> 27AASCS3903K1ZV252635311
A17: 45931 | B17: 27AASCS3903K1ZV | C17: SEMSYS PRIVATE LIMITED | D17: 2526354 | E17: 01/10/2025 | F17: 0.17985612 | G17: 4720 | H17: 4000 | I17: 0 | J17: 360 | K17: 360 | L17: 720 | M17: 27AASCS3903K1ZV2526354 | N17: 998332 | O17: Professional Fees | P17: Input Service | Q17: 2600 | R17: 45931 | S17: 45931 | T17: Yes | U17: Matched with 2B | W17: All other ITC | Z17: =_xlfn.XLOOKUP(AC17,'[9]PR Conso (Apr 25-Sep 25)'!$P:$P,'[9]PR Conso (Apr 25-Sep 25)'!$Z:$Z) -> #N/A | AB17: =AB16+1 -> 12 | AC17: =CONCATENATE(M17,AB17) -> 27AASCS3903K1ZV252635412
A18: 45931 | B18: 27AASCS3903K1ZV | C18: SEMSYS PRIVATE LIMITED | D18: 2526355 | E18: 01/10/2025 | F18: 0.17985612 | G18: 23600 | H18: 20000 | I18: 0 | J18: 1800 | K18: 1800 | L18: 3600 | M18: 27AASCS3903K1ZV2526355 | N18: 998332 | O18: Professional Fees | P18: Input Service | Q18: 2601 | R18: 45931 | S18: 45931 | T18: Yes | U18: Matched with 2B | W18: All other ITC | Z18: =_xlfn.XLOOKUP(AC18,'[9]PR Conso (Apr 25-Sep 25)'!$P:$P,'[9]PR Conso (Apr 25-Sep 25)'!$Z:$Z) -> #N/A | AB18: =AB17+1 -> 13 | AC18: =CONCATENATE(M18,AB18) -> 27AASCS3903K1ZV252635513
A19: 45931 | B19: 27AAGCR8772D1Z2 | C19: Porter | D19: CRN1267653331 | E19: 30/09/2025 | F19: 0.17985612 | G19: 118 | H19: 100 | I19: 0 | J19: 9 | K19: 9 | L19: 18 | M19: 27AAGCR8772D1Z2CRN1267653331 | N19: 996511 | O19: Courior Services | P19: Input Service | Q19: 877 | R19: 45931 | S19: 45931 | T19: Yes | U19: Matched with 2B | W19: All other ITC | Z19: =_xlfn.XLOOKUP(AC19,'[9]PR Conso (Apr 25-Sep 25)'!$P:$P,'[9]PR Conso (Apr 25-Sep 25)'!$Z:$Z) -> #N/A | AB19: =AB18+1 -> 14 | AC19: =CONCATENATE(M19,AB19) -> 27AAGCR8772D1Z2CRN126765333114
A20: 45931 | B20: 27AIFPK3096H1Z3 | C20: RAJ ELECTRICALS | D20: 63210 | E20: 10/10/2025 | F20: 0.17985612 | G20: 413 | H20: 350 | I20: 0 | J20: 31.5 | K20: 31.5 | L20: 63 | M20: 27AIFPK3096H1Z363210 | N20: 0 | O20: Hardware/Software Expenses | P20: Inputs | Q20: 2728 | R20: 45931 | S20: 45931 | T20: Yes | U20: Matched with 2B | W20: All other ITC | Z20: =_xlfn.XLOOKUP(AC20,'[9]PR Conso (Apr 25-Sep 25)'!$P:$P,'[9]PR Conso (Apr 25-Sep 25)'!$Z:$Z) -> #N/A | AB20: =AB19+1 -> 15 | AC20: =CONCATENATE(M20,AB20) -> 27AIFPK3096H1Z36321015
A21: 45931 | B21: 27AAMFD2812K1ZC | C21: DESIGNSTYLE STUDIOS | D21: 69 | E21: 11/08/2025 | F21: 0.17985612 | G21: 1770 | H21: 1500 | I21: 0 | J21: 135 | K21: 135 | L21: 270 | M21: 27AAMFD2812K1ZC69 | N21: 0 | O21: 0 | Q21: 2724 | R21: 45931 | S21: 45931 | T21: Yes | U21: Matched with 2B | W21: All other ITC | X21: Description taken from last refund working | Z21: =_xlfn.XLOOKUP(AC21,'[9]PR Conso (Apr 25-Sep 25)'!$P:$P,'[9]PR Conso (Apr 25-Sep 25)'!$Z:$Z) -> #N/A | AB21: =AB20+1 -> 16 | AC21: =CONCATENATE(M21,AB21) -> 27AAMFD2812K1ZC6916
A22: 45931 | B22: 03ACCPS7232A1Z5 | C22: ELECTRO SALES | D22: ES-ECOM-179 | E22: 06/10/2025 | F22: 0.17985612 | G22: 1330 | H22: 1127.12 | I22: 202.88 | J22: 0 | K22: 0 | L22: 202.88 | M22: 03ACCPS7232A1Z5ES-ECOM-179 | N22: 0 | O22: 0 | Q22: 2605 | R22: 45931 | S22: 45931 | T22: Yes | U22: Matched with 2B | W22: All other ITC | X22: Description taken from last refund working | Z22: =_xlfn.XLOOKUP(AC22,'[9]PR Conso (Apr 25-Sep 25)'!$P:$P,'[9]PR Conso (Apr 25-Sep 25)'!$Z:$Z) -> #N/A | AB22: =AB21+1 -> 17 | AC22: =CONCATENATE(M22,AB22) -> 03ACCPS7232A1Z5ES-ECOM-17917
A23: 45931 | B23: 27AAACU4322N1Z6 | C23: UPS EXPRESS PRIVATE LIMITED | D23: 427100363393 | E23: 29/10/2025 | F23: 0.17985612 | G23: 5272.24 | H23: 4468 | I23: 0 | J23: 402.12 | K23: 402.12 | L23: 804.24 | M23: 27AAACU4322N1Z6427100363393 | N23: 996813 | O23: Courior Services | P23: Input Service | Q23: 2723 | R23: 45931 | S23: 45931 | T23: Yes | U23: Matched with 2B | W23: All other ITC | Z23: =_xlfn.XLOOKUP(AC23,'[9]PR Conso (Apr 25-Sep 25)'!$P:$P,'[9]PR Conso (Apr 25-Sep 25)'!$Z:$Z) -> #N/A | AB23: =AB22+1 -> 18 | AC23: =CONCATENATE(M23,AB23) -> 27AAACU4322N1Z642710036339318
A24: 45931 | B24: 27AAACU4322N1Z6 | C24: UPS EXPRESS PRIVATE LIMITED | D24: 427100360338 | E24: 05/10/2025 | F24: 0.17985612 | G24: 929.84 | H24: 788 | I24: 0 | J24: 70.92 | K24: 70.92 | L24: 141.84 | M24: 27AAACU4322N1Z6427100360338 | N24: 996813 | O24: Courior Services | P24: Input Service | Q24: 2722 | R24: 45931 | S24: 45931 | T24: Yes | U24: Matched with 2B | W24: All other ITC | Z24: =_xlfn.XLOOKUP(AC24,'[9]PR Conso (Apr 25-Sep 25)'!$P:$P,'[9]PR Conso (Apr 25-Sep 25)'!$Z:$Z) -> #N/A | AB24: =AB23+1 -> 19 | AC24: =CONCATENATE(M24,AB24) -> 27AAACU4322N1Z642710036033819
A25: 45931 | B25: 07AAACJ0054A1ZD | C25: JETWAYS TRAVELS PVT.LTD. | D25: HP501130 | E25: 31/10/2025 | F25: 0.17985612 | G25: 16402 | H25: 13900 | I25: 2502 | J25: 0 | K25: 0 | L25: 2502 | M25: 07AAACJ0054A1ZDHP501130 | N25: 998551 | O25: Travel Expenses | P25: Input Service | Q25: 2719 | R25: 45931 | S25: 45931 | T25: Yes | U25: Matched with 2B | W25: All other ITC | Z25: =_xlfn.XLOOKUP(AC25,'[9]PR Conso (Apr 25-Sep 25)'!$P:$P,'[9]PR Conso (Apr 25-Sep 25)'!$Z:$Z) -> #N/A | AB25: =AB24+1 -> 20 | AC25: =CONCATENATE(M25,AB25) -> 07AAACJ0054A1ZDHP50113020
A26: 45931 | B26: 07AAACJ0054A1ZD | C26: JETWAYS TRAVELS PVT.LTD. | D26: HP501109 | E26: 27/10/2025 | F26: 0.17985612 | G26: 8260 | H26: 7000 | I26: 1260 | J26: 0 | K26: 0 | L26: 1260 | M26: 07AAACJ0054A1ZDHP501109 | N26: 998551 | O26: Travel Expenses | P26: Input Service | Q26: 2718 | R26: 45931 | S26: 45931 | T26: Yes | U26: Matched with 2B | W26: All other ITC | Z26: =_xlfn.XLOOKUP(AC26,'[9]PR Conso (Apr 25-Sep 25)'!$P:$P,'[9]PR Conso (Apr 25-Sep 25)'!$Z:$Z) -> #N/A | AB26: =AB25+1 -> 21 | AC26: =CONCATENATE(M26,AB26) -> 07AAACJ0054A1ZDHP50110921
A27: 45931 | B27: 07AAACJ0054A1ZD | C27: JETWAYS TRAVELS PVT.LTD. | D27: HP501108 | E27: 27/10/2025 | F27: 0.17985612 | G27: 8968 | H27: 7600 | I27: 1368 | J27: 0 | K27: 0 | L27: 1368 | M27: 07AAACJ0054A1ZDHP501108 | N27: 998551 | O27: Travel Expenses | P27: Input Service | Q27: 2717 | R27: 45931 | S27: 45931 | T27: Yes | U27: Matched with 2B | W27: All other ITC | Z27: =_xlfn.XLOOKUP(AC27,'[9]PR Conso (Apr 25-Sep 25)'!$P:$P,'[9]PR Conso (Apr 25-Sep 25)'!$Z:$Z) -> #N/A | AB27: =AB26+1 -> 22 | AC27: =CONCATENATE(M27,AB27) -> 07AAACJ0054A1ZDHP50110822
A28: 45931 | B28: 07AAACJ0054A1ZD | C28: JETWAYS TRAVELS PVT.LTD. | D28: DP525244 | E28: 25/10/2025 | F28: 0.17985612 | G28: 118 | H28: 100 | I28: 18 | J28: 0 | K28: 0 | L28: 18 | M28: 07AAACJ0054A1ZDDP525244 | N28: 998551 | O28: Travel Expenses | P28: Input Service | Q28: 2712 | R28: 45931 | S28: 45931 | T28: Yes | U28: Matched with 2B | W28: All other ITC | Z28: =_xlfn.XLOOKUP(AC28,'[9]PR Conso (Apr 25-Sep 25)'!$P:$P,'[9]PR Conso (Apr 25-Sep 25)'!$Z:$Z) -> #N/A | AB28: =AB27+1 -> 23 | AC28: =CONCATENATE(M28,AB28) -> 07AAACJ0054A1ZDDP52524423
A29: 45931 | B29: 07AAACJ0054A1ZD | C29: JETWAYS TRAVELS PVT.LTD. | D29: DP525243 | E29: 25/10/2025 | F29: 0.17985612 | G29: 118 | H29: 100 | I29: 18 | J29: 0 | K29: 0 | L29: 18 | M29: 07AAACJ0054A1ZDDP525243 | N29: 998551 | O29: Travel Expenses | P29: Input Service | Q29: 2711 | R29: 45931 | S29: 45931 | T29: Yes | U29: Matched with 2B | W29: All other ITC | Z29: =_xlfn.XLOOKUP(AC29,'[9]PR Conso (Apr 25-Sep 25)'!$P:$P,'[9]PR Conso (Apr 25-Sep 25)'!$Z:$Z) -> #N/A | AB29: =AB28+1 -> 24 | AC29: =CONCATENATE(M29,AB29) -> 07AAACJ0054A1ZDDP52524324
A30: 45931 | B30: 27AAWCS5258F1ZQ | C30: SMARTWORKS COWORKING SPACES LIMITED | D30: PUN06/SC25/00761 | E30: 22/10/2025 | F30: 0.17985612 | G30: 3404409.7 | H30: 2885093 | I30: 0 | J30: 259658.37 | K30: 259658.37 | L30: 519316.74 | M30: 27AAWCS5258F1ZQPUN06/SC25/00761 | N30: 997212 | O30: Rent-Office | P30: Input Service | Q30: 2703 | R30: 45931 | S30: 45931 | T30: Yes | U30: Matched with 2B | W30: All other ITC | Z30: =_xlfn.XLOOKUP(AC30,'[9]PR Conso (Apr 25-Sep 25)'!$P:$P,'[9]PR Conso (Apr 25-Sep 25)'!$Z:$Z) -> #N/A | AB30: =AB29+1 -> 25 | AC30: =CONCATENATE(M30,AB30) -> 27AAWCS5258F1ZQPUN06/SC25/0076125
A31: 45931 | B31: 06AADCH6128C1ZZ | C31: Handy Online Solutions Private Limited | D31: ONGRID061722397 | E31: 29/10/2025 | F31: 0.17985612 | G31: 7278.24 | H31: 6168 | I31: 1110.24 | J31: 0 | K31: 0 | L31: 1110.24 | M31: 06AADCH6128C1ZZONGRID061722397 | N31: 853669 | O31: Professional Fees | P31: Inputs | Q31: 2695 | R31: 45931 | S31: 45931 | T31: Yes | U31: Matched with 2B | W31: All other ITC | Z31: =_xlfn.XLOOKUP(AC31,'[9]PR Conso (Apr 25-Sep 25)'!$P:$P,'[9]PR Conso (Apr 25-Sep 25)'!$Z:$Z) -> #N/A | AB31: =AB30+1 -> 26 | AC31: =CONCATENATE(M31,AB31) -> 06AADCH6128C1ZZONGRID06172239726
A32: 45931 | B32: 27ARCPK9149B1ZU | C32: UNIVERSAL ELECTRICALS | D32: 8919 | E32: 15/10/2025 | F32: 0.17985612 | G32: 2076.8 | H32: 1760 | I32: 0 | J32: 158.4 | K32: 158.4 | L32: 316.8 | M32: 27ARCPK9149B1ZU8919 | N32: 0 | O32: Hardware/Software Expenses | P32: Inputs | Q32: 2692 | R32: 45931 | S32: 45931 | T32: Yes | U32: Matched with 2B | W32: All other ITC | Z32: =_xlfn.XLOOKUP(AC32,'[9]PR Conso (Apr 25-Sep 25)'!$P:$P,'[9]PR Conso (Apr 25-Sep 25)'!$Z:$Z) -> #N/A | AB32: =AB31+1 -> 27 | AC32: =CONCATENATE(M32,AB32) -> 27ARCPK9149B1ZU891927
A33: 45931 | B33: 27AAACB2100P1ZX | C33: Vodafone Idea Limited | D33: MHI1410526435759 | E33: 09/10/2025 | F33: 0.17985612 | G33: 411.82 | H33: 349 | I33: 0 | J33: 31.41 | K33: 31.41 | L33: 62.82 | M33: 27AAACB2100P1ZXMHI1410526435759 | N33: 998413 | O33: Internet Connectivity charges | P33: Input Service | Q33: 2691 | R33: 45931 | S33: 45931 | T33: Yes | U33: Matched with 2B | W33: All other ITC | Z33: =_xlfn.XLOOKUP(AC33,'[9]PR Conso (Apr 25-Sep 25)'!$P:$P,'[9]PR Conso (Apr 25-Sep 25)'!$Z:$Z) -> #N/A | AB33: =AB32+1 -> 28 | AC33: =CONCATENATE(M33,AB33) -> 27AAACB2100P1ZXMHI141052643575928
A34: 45931 | B34: 36AEUPV4314A1ZE | C34: Vegesna Akshaya Avyanga Industries | D34: 014/2025-2026 | E34: 30/10/2025 | F34: 0.17985612 | G34: 295000 | H34: 250000 | I34: 45000 | J34: 0 | K34: 0 | L34: 45000 | M34: 36AEUPV4314A1ZE014/2025-2026 | N34: 998313 | O34: Professional Fees | P34: Input Service | Q34: 2686 | R34: 45931 | S34: 45931 | T34: Yes | U34: Matched with 2B | W34: All other ITC | Z34: =_xlfn.XLOOKUP(AC34,'[9]PR Conso (Apr 25-Sep 25)'!$P:$P,'[9]PR Conso (Apr 25-Sep 25)'!$Z:$Z) -> #N/A | AB34: =AB33+1 -> 29 | AC34: =CONCATENATE(M34,AB34) -> 36AEUPV4314A1ZE014/2025-202629
A35: 45931 | B35: 27AABCC7181N2Z7 | C35: SWISS INTERNATIONAL AIR LINES LTD. | D35: LXBOM251000654 | E35: 08/10/2025 | F35: 0.05 | G35: 105483 | H35: 100460 | I35: 0 | J35: 2511.5 | K35: 2511.5 | L35: 5023 | M35: 27AABCC7181N2Z7LXBOM251000654 | N35: 440362 | O35: Travel Expenses | P35: Inputs | Q35: 2680 | R35: 45931 | S35: 45931 | T35: Yes | U35: Matched with 2B | W35: All other ITC | Z35: =_xlfn.XLOOKUP(AC35,'[9]PR Conso (Apr 25-Sep 25)'!$P:$P,'[9]PR Conso (Apr 25-Sep 25)'!$Z:$Z) -> #N/A | AB35: =AB34+1 -> 30 | AC35: =CONCATENATE(M35,AB35) -> 27AABCC7181N2Z7LXBOM25100065430
A36: 45931 | B36: 27AABCF6516A1Z3 | C36: FEDEX EXPRESS TRANSPORTATION AND SUPPLY CHAIN SERVICES (I) PRIVATE LIMITED | D36: BOM-C-279329 | E36: 25/10/2025 | F36: 0.17985612 | G36: 944 | H36: 800 | I36: 0 | J36: 72 | K36: 72 | L36: 144 | M36: 27AABCF6516A1Z3BOM-C-279329 | N36: 996812 | O36: Courior Services | P36: Input Service | Q36: 2679 | R36: 45931 | S36: 45931 | T36: Yes | U36: Matched with 2B | W36: All other ITC | Z36: =_xlfn.XLOOKUP(AC36,'[9]PR Conso (Apr 25-Sep 25)'!$P:$P,'[9]PR Conso (Apr 25-Sep 25)'!$Z:$Z) -> #N/A | AB36: =AB35+1 -> 31 | AC36: =CONCATENATE(M36,AB36) -> 27AABCF6516A1Z3BOM-C-27932931
A37: 45931 | B37: 06AAACM5586C1ZL | C37: Microsoft Corporation (India) Pvt Ltd | D37: TIO26HR101264303 | E37: 27/10/2025 | F37: 0.17985612 | G37: 1253.16 | H37: 1062 | I37: 191.16 | J37: 0 | K37: 0 | L37: 191.16 | M37: 06AAACM5586C1ZLTIO26HR101264303 | N37: 998313 | O37: Software Services | P37: Input Service | Q37: 2678 | R37: 45931 | S37: 45931 | T37: Yes | U37: Matched with 2B | W37: All other ITC | Z37: =_xlfn.XLOOKUP(AC37,'[9]PR Conso (Apr 25-Sep 25)'!$P:$P,'[9]PR Conso (Apr 25-Sep 25)'!$Z:$Z) -> #N/A | AB37: =AB36+1 -> 32 | AC37: =CONCATENATE(M37,AB37) -> 06AAACM5586C1ZLTIO26HR10126430332
A38: 45931 | B38: 27AABCD3611Q1ZI | C38: DHL EXPRESS (INDIA) PRIVATE LIMITED | D38: BOM160246 | E38: 07/10/2025 | F38: 0.17985612 | G38: 1298 | H38: 1100 | I38: 0 | J38: 99 | K38: 99 | L38: 198 | M38: 27AABCD3611Q1ZIBOM160246 | N38: 996812 | O38: Courior Services | P38: Input Service | Q38: 2677 | R38: 45931 | S38: 45931 | T38: Yes | U38: Matched with 2B | W38: All other ITC | Z38: =_xlfn.XLOOKUP(AC38,'[9]PR Conso (Apr 25-Sep 25)'!$P:$P,'[9]PR Conso (Apr 25-Sep 25)'!$Z:$Z) -> #N/A | AB38: =AB37+1 -> 33 | AC38: =CONCATENATE(M38,AB38) -> 27AABCD3611Q1ZIBOM16024633
A39: 45931 | B39: 27AAECI7859N1ZQ | C39: Maars Creative Concepts Private Limited | D39: SOFT/594/25-26 | E39: 30/10/2025 | F39: 0.17985612 | G39: 743.4 | H39: 630 | I39: 0 | J39: 56.7 | K39: 56.7 | L39: 113.4 | M39: 27AAECI7859N1ZQSOFT/594/25-26 | N39: 482090 | O39: Printing & Stationery | P39: Inputs | Q39: 2672 | R39: 45931 | S39: 45931 | T39: Yes | U39: Matched with 2B | W39: All other ITC | Z39: =_xlfn.XLOOKUP(AC39,'[9]PR Conso (Apr 25-Sep 25)'!$P:$P,'[9]PR Conso (Apr 25-Sep 25)'!$Z:$Z) -> #N/A | AB39: =AB38+1 -> 34 | AC39: =CONCATENATE(M39,AB39) -> 27AAECI7859N1ZQSOFT/594/25-2634
A40: 45931 | B40: 27AAECI7859N1ZQ | C40: Maars Creative Concepts Private Limited | D40: SOFT/581/25-26 | E40: 18/10/2025 | F40: 0.17985612 | G40: 247.8 | H40: 210 | I40: 0 | J40: 18.9 | K40: 18.9 | L40: 37.8 | M40: 27AAECI7859N1ZQSOFT/581/25-26 | N40: 482090 | O40: Printing & Stationery | P40: Inputs | Q40: 2671 | R40: 45931 | S40: 45931 | T40: Yes | U40: Matched with 2B | W40: All other ITC | Z40: =_xlfn.XLOOKUP(AC40,'[9]PR Conso (Apr 25-Sep 25)'!$P:$P,'[9]PR Conso (Apr 25-Sep 25)'!$Z:$Z) -> #N/A | AB40: =AB39+1 -> 35 | AC40: =CONCATENATE(M40,AB40) -> 27AAECI7859N1ZQSOFT/581/25-2635
A41: 45931 | B41: 27AAECI7859N1ZQ | C41: Maars Creative Concepts Private Limited | D41: SOFT/560/25-26 | E41: 13/10/2025 | F41: 0.17985612 | G41: 826 | H41: 700 | I41: 0 | J41: 63 | K41: 63 | L41: 126 | M41: 27AAECI7859N1ZQSOFT/560/25-26 | N41: 482090 | O41: Printing & Stationery | P41: Inputs | Q41: 2670 | R41: 45931 | S41: 45931 | T41: Yes | U41: Matched with 2B | W41: All other ITC | Z41: =_xlfn.XLOOKUP(AC41,'[9]PR Conso (Apr 25-Sep 25)'!$P:$P,'[9]PR Conso (Apr 25-Sep 25)'!$Z:$Z) -> #N/A | AB41: =AB40+1 -> 36 | AC41: =CONCATENATE(M41,AB41) -> 27AAECI7859N1ZQSOFT/560/25-2636
A42: 45931 | B42: 27AAECI7859N1ZQ | C42: Maars Creative Concepts Private Limited | D42: SOFT/540/25-26 | E42: 06/10/2025 | F42: 0.17985612 | G42: 123.9 | H42: 105 | I42: 0 | J42: 9.45 | K42: 9.45 | L42: 18.9 | M42: 27AAECI7859N1ZQSOFT/540/25-26 | N42: 482090 | O42: Printing & Stationery | P42: Inputs | Q42: 2669 | R42: 45931 | S42: 45931 | T42: Yes | U42: Matched with 2B | W42: All other ITC | Z42: =_xlfn.XLOOKUP(AC42,'[9]PR Conso (Apr 25-Sep 25)'!$P:$P,'[9]PR Conso (Apr 25-Sep 25)'!$Z:$Z) -> #N/A | AB42: =AB41+1 -> 37 | AC42: =CONCATENATE(M42,AB42) -> 27AAECI7859N1ZQSOFT/540/25-2637
A43: 45931 | B43: 27DBRPP0459R1ZK | C43: Shree Caterers | D43: 2025-26/476 | E43: 31/10/2025 | F43: 0.05 | G43: 2520 | H43: 2400 | I43: 0 | J43: 60 | K43: 60 | L43: 120 | M43: 27DBRPP0459R1ZK2025-26/476 | N43: 99633 | O43: Staff Welfare | P43: Input Service | Q43: 2626 | R43: 45931 | S43: 45931 | T43: Yes | U43: Matched with 2B | W43: All other ITC | Z43: =_xlfn.XLOOKUP(AC43,'[9]PR Conso (Apr 25-Sep 25)'!$P:$P,'[9]PR Conso (Apr 25-Sep 25)'!$Z:$Z) -> #N/A | AB43: =AB42+1 -> 38 | AC43: =CONCATENATE(M43,AB43) -> 27DBRPP0459R1ZK2025-26/47638
A44: 45931 | B44: 27AAACC2498P1Z3 | C44: CENTRAL BANK OF INDIA | D44: 26271C0003803394 | E44: 31/10/2025 | F44: 0.16666667 | G44: 0.56 | H44: 0.48 | I44: 0 | J44: 0.04 | K44: 0.04 | L44: 0.08 | M44: 27AAACC2498P1Z326271C0003803394 | N44: 440173 | O44: Bank Charges | P44: Inputs | Q44: 2627 | R44: 45931 | S44: 45931 | T44: Yes | U44: Matched with 2B | W44: All other ITC | Z44: =_xlfn.XLOOKUP(AC44,'[9]PR Conso (Apr 25-Sep 25)'!$P:$P,'[9]PR Conso (Apr 25-Sep 25)'!$Z:$Z) -> #N/A | AB44: =AB43+1 -> 39 | AC44: =CONCATENATE(M44,AB44) -> 27AAACC2498P1Z326271C000380339439
... A50: 45931 | B50: 27AISPB8261G1Z0 | C50: BHUTADA ENTERPRISES | D50: SH0038-0019417 | E50: 29/10/2025 | F50: 0.05 | G50: 1820 | H50: 1725.98 | I50: 0 | J50: 47.01 | K50: 47.01 | L50: 94.02 | M50: 27AISPB8261G1Z0SH0038-0019417 | N50: 29152100 | O50: ACETIC ACID | P50: Inputs | Q50: 2633 | R50: 45931 | S50: 45931 | T50: Yes | U50: Matched with 2B | W50: All other ITC | Z50: =_xlfn.XLOOKUP(AC50,'[9]PR Conso (Apr 25-Sep 25)'!$P:$P,'[9]PR Conso (Apr 25-Sep 25)'!$Z:$Z) -> #N/A | AB50: =AB49+1 -> 45 | AC50: =CONCATENATE(M50,AB50) -> 27AISPB8261G1Z0SH0038-001941745
A51: 45931 | B51: 27AZJPG1481H1ZC | C51: OM SAI SECURITY AND MANPOWER SERVICES / OM SAI TOURS AND TRAVELS | D51: 5904 | E51: 31/10/2025 | F51: 0.05 | G51: 10269 | H51: 9780 | I51: 0 | J51: 244.5 | K51: 244.5 | L51: 489 | M51: 27AZJPG1481H1ZC5904 | N51: 996813 | O51: Cab rent charges | P51: Input Service | Q51: 2660 | R51: 45931 | S51: 45931 | T51: Yes | U51: Matched with 2B | W51: All other ITC | Z51: =_xlfn.XLOOKUP(AC51,'[9]PR Conso (Apr 25-Sep 25)'!$P:$P,'[9]PR Conso (Apr 25-Sep 25)'!$Z:$Z) -> #N/A | AB51: =AB50+1 -> 46 | AC51: =CONCATENATE(M51,AB51) -> 27AZJPG1481H1ZC590446
A52: 45931 | B52: 27AZJPG1481H1ZC | C52: OM SAI SECURITY AND MANPOWER SERVICES / OM SAI TOURS AND TRAVELS | D52: 5824 | E52: 31/10/2025 | F52: 0.05 | G52: 4925.56 | H52: 4691 | I52: 0 | J52: 117.28 | K52: 117.28 | L52: 234.56 | M52: 27AZJPG1481H1ZC5824 | N52: 996813 | O52: Cab rent charges | P52: Input Service | Q52: 2659 | R52: 45931 | S52: 45931 | T52: Yes | U52: Matched with 2B | W52: All other ITC | Z52: =_xlfn.XLOOKUP(AC52,'[9]PR Conso (Apr 25-Sep 25)'!$P:$P,'[9]PR Conso (Apr 25-Sep 25)'!$Z:$Z) -> #N/A | AB52: =AB51+1 -> 47 | AC52: =CONCATENATE(M52,AB52) -> 27AZJPG1481H1ZC582447
A53: 45931 | B53: 27AABCR0111M1ZN | C53: ROYAL ORCHID HOTELS LIMITED | D53: ROCP-2526-12575 | E53: 16/10/2025 | F53: 0.17985612 | G53: 791.73 | H53: 670.95 | I53: 0 | J53: 60.39 | K53: 60.39 | L53: 120.78 | M53: 27AABCR0111M1ZNROCP-2526-12575 | N53: 996311 | O53: Hotel & Lodging Expenses | P53: Input Service | Q53: 2636 | R53: 45931 | S53: 45931 | T53: Yes | U53: Matched with 2B | W53: All other ITC | Z53: =_xlfn.XLOOKUP(AC53,'[9]PR Conso (Apr 25-Sep 25)'!$P:$P,'[9]PR Conso (Apr 25-Sep 25)'!$Z:$Z) -> #N/A | AB53: =AB52+1 -> 48 | AC53: =CONCATENATE(M53,AB53) -> 27AABCR0111M1ZNROCP-2526-1257548
A54: 45931 | B54: 27AZJPG1481H1ZC | C54: OM SAI SECURITY AND MANPOWER SERVICES / OM SAI TOURS AND TRAVELS | D54: 5796 | E54: 31/10/2025 | F54: 0.05 | G54: 5187 | H54: 4940 | I54: 0 | J54: 123.5 | K54: 123.5 | L54: 247 | M54: 27AZJPG1481H1ZC5796 | N54: 996813 | O54: Cab rent charges | P54: Input Service | Q54: 2658 | R54: 45931 | S54: 45931 | T54: Yes | U54: Matched with 2B | W54: All other ITC | Z54: =_xlfn.XLOOKUP(AC54,'[9]PR Conso (Apr 25-Sep 25)'!$P:$P,'[9]PR Conso (Apr 25-Sep 25)'!$Z:$Z) -> #N/A | AB54: =AB53+1 -> 49 | AC54: =CONCATENATE(M54,AB54) -> 27AZJPG1481H1ZC579649
A55: 45931 | B55: 27AZJPG1481H1ZC | C55: OM SAI SECURITY AND MANPOWER SERVICES / OM SAI TOURS AND TRAVELS | D55: 5795 | E55: 31/10/2025 | F55: 0.05 | G55: 5234.26 | H55: 4985 | I55: 0 | J55: 124.63 | K55: 124.63 | L55: 249.26 | M55: 27AZJPG1481H1ZC5795 | N55: 996813 | O55: Cab rent charges | P55: Input Service | Q55: 2657 | R55: 45931 | S55: 45931 | T55: Yes | U55: Matched with 2B | W55: All other ITC | Z55: =_xlfn.XLOOKUP(AC55,'[9]PR Conso (Apr 25-Sep 25)'!$P:$P,'[9]PR Conso (Apr 25-Sep 25)'!$Z:$Z) -> #N/A | AB55: =AB54+1 -> 50 | AC55: =CONCATENATE(M55,AB55) -> 27AZJPG1481H1ZC579550
A56: 45931 | B56: 27AZJPG1481H1ZC | C56: OM SAI SECURITY AND MANPOWER SERVICES / OM SAI TOURS AND TRAVELS | D56: 5763 | E56: 31/10/2025 | F56: 0.05 | G56: 10958.86 | H56: 10437 | I56: 0 | J56: 260.93 | K56: 260.93 | L56: 521.86 | M56: 27AZJPG1481H1ZC5763 | N56: 996813 | O56: Cab rent charges | P56: Input Service | Q56: 2656 | R56: 45931 | S56: 45931 | T56: Yes | U56: Matched with 2B | W56: All other ITC | Z56: =_xlfn.XLOOKUP(AC56,'[9]PR Conso (Apr 25-Sep 25)'!$P:$P,'[9]PR Conso (Apr 25-Sep 25)'!$Z:$Z) -> #N/A | AB56: =AB55+1 -> 51 | AC56: =CONCATENATE(M56,AB56) -> 27AZJPG1481H1ZC576351
A57: 45931 | B57: 27ABBPM0253H1ZZ | C57: J RAY HARDWARE / J RAY ENGINEERING CO. | D57: JRH-15960 | E57: 10/10/2025 | F57: 0.17985612 | G57: 426.22 | H57: 361.2 | I57: 0 | J57: 32.51 | K57: 32.51 | L57: 65.02 | M57: 27ABBPM0253H1ZZJRH-15960 | N57: 0 | O57: 0 | Q57: 2640 | R57: 45931 | S57: 45931 | T57: Yes | U57: Matched with 2B | W57: All other ITC | X57: Description taken from last refund working | Z57: =_xlfn.XLOOKUP(AC57,'[9]PR Conso (Apr 25-Sep 25)'!$P:$P,'[9]PR Conso (Apr 25-Sep 25)'!$Z:$Z) -> #N/A | AB57: =AB56+1 -> 52 | AC57: =CONCATENATE(M57,AB57) -> 27ABBPM0253H1ZZJRH-1596052
A58: 45931 | B58: 27AAACI1195H1ZM | C58: ICICI BANK LIMITED | D58: 135251007031815 | E58: 07/10/2025 | F58: 0.17985612 | G58: 13463.32 | H58: 11409.6 | I58: 0 | J58: 1026.86 | K58: 1026.86 | L58: 2053.72 | M58: 27AAACI1195H1ZM135251007031815 | N58: 997157 | O58: Bank charges | P58: Input Service | Q58: 2641 | R58: 45931 | S58: 45931 | T58: Yes | U58: Matched with 2B | W58: All other ITC | Z58: =_xlfn.XLOOKUP(AC58,'[9]PR Conso (Apr 25-Sep 25)'!$P:$P,'[9]PR Conso (Apr 25-Sep 25)'!$Z:$Z) -> #N/A | AB58: =AB57+1 -> 53 | AC58: =CONCATENATE(M58,AB58) -> 27AAACI1195H1ZM13525100703181553
A59: 45931 | B59: 27AAACI1195H1ZM | C59: ICICI BANK LIMITED | D59: 135251013059916 | E59: 13/10/2025 | F59: 0.17985612 | G59: 17866.26 | H59: 15140.9 | I59: 0 | J59: 1362.68 | K59: 1362.68 | L59: 2725.36 | M59: 27AAACI1195H1ZM135251013059916 | N59: 997157 | O59: Bank charges | P59: Input Service | Q59: 2642 | R59: 45931 | S59: 45931 | T59: Yes | U59: Matched with 2B | W59: All other ITC | Z59: =_xlfn.XLOOKUP(AC59,'[9]PR Conso (Apr 25-Sep 25)'!$P:$P,'[9]PR Conso (Apr 25-Sep 25)'!$Z:$Z) -> #N/A | AB59: =AB58+1 -> 54 | AC59: =CONCATENATE(M59,AB59) -> 27AAACI1195H1ZM13525101305991654
A60: 45931 | B60: 27AAACI1195H1ZM | C60: ICICI BANK LIMITED | D60: 135251017090732 | E60: 17/10/2025 | F60: 0.17985612 | G60: 16702.81 | H60: 14154.93 | I60: 0 | J60: 1273.94 | K60: 1273.94 | L60: 2547.88 | M60: 27AAACI1195H1ZM135251017090732 | N60: 997157 | O60: Bank charges | P60: Input Service | Q60: 2643 | R60: 45931 | S60: 45931 | T60: Yes | U60: Matched with 2B | W60: All other ITC | Z60: =_xlfn.XLOOKUP(AC60,'[9]PR Conso (Apr 25-Sep 25)'!$P:$P,'[9]PR Conso (Apr 25-Sep 25)'!$Z:$Z) -> #N/A | AB60: =AB59+1 -> 55 | AC60: =CONCATENATE(M60,AB60) -> 27AAACI1195H1ZM13525101709073255
A61: 45931 | B61: 27AAACI1195H1ZM | C61: ICICI BANK LIMITED | D61: 135251024114788 | E61: 24/10/2025 | F61: 0.17985612 | G61: 17728.95 | H61: 15024.53 | I61: 0 | J61: 1352.21 | K61: 1352.21 | L61: 2704.42 | M61: 27AAACI1195H1ZM135251024114788 | N61: 997157 | O61: Bank charges | P61: Input Service | Q61: 2644 | R61: 45931 | S61: 45931 | T61: Yes | U61: Matched with 2B | W61: All other ITC | Z61: =_xlfn.XLOOKUP(AC61,'[9]PR Conso (Apr 25-Sep 25)'!$P:$P,'[9]PR Conso (Apr 25-Sep 25)'!$Z:$Z) -> #N/A | AB61: =AB60+1 -> 56 | AC61: =CONCATENATE(M61,AB61) -> 27AAACI1195H1ZM13525102411478856
A62: 45931 | B62: 27AAACI1195H1ZM | C62: ICICI BANK LIMITED | D62: 135251024114824 | E62: 24/10/2025 | F62: 0.17985612 | G62: 17728.95 | H62: 15024.53 | I62: 0 | J62: 1352.21 | K62: 1352.21 | L62: 2704.42 | M62: 27AAACI1195H1ZM135251024114824 | N62: 997157 | O62: Bank charges | P62: Input Service | Q62: 2645 | R62: 45931 | S62: 45931 | T62: Yes | U62: Matched with 2B | W62: All other ITC | Z62: =_xlfn.XLOOKUP(AC62,'[9]PR Conso (Apr 25-Sep 25)'!$P:$P,'[9]PR Conso (Apr 25-Sep 25)'!$Z:$Z) -> #N/A | AB62: =AB61+1 -> 57 | AC62: =CONCATENATE(M62,AB62) -> 27AAACI1195H1ZM13525102411482457
A63: 45931 | B63: 27AAACI1195H1ZM | C63: ICICI BANK LIMITED | D63: 135251031156281 | E63: 31/10/2025 | F63: 0.17985612 | G63: 16814.42 | H63: 14249.5 | I63: 0 | J63: 1282.46 | K63: 1282.46 | L63: 2564.92 | M63: 27AAACI1195H1ZM135251031156281 | N63: 997157 | O63: Bank charges | P63: Input Service | Q63: 2646 | R63: 45931 | S63: 45931 | T63: Yes | U63: Matched with 2B | W63: All other ITC | Z63: =_xlfn.XLOOKUP(AC63,'[9]PR Conso (Apr 25-Sep 25)'!$P:$P,'[9]PR Conso (Apr 25-Sep 25)'!$Z:$Z) -> #N/A | AB63: =AB62+1 -> 58 | AC63: =CONCATENATE(M63,AB63) -> 27AAACI1195H1ZM13525103115628158
A64: 45931 | B64: 27AAACI1195H1ZM | C64: ICICI BANK LIMITED | D64: TS61315298202510 | E64: 31/10/2025 | F64: 0.17985612 | G64: 590 | H64: 500 | I64: 0 | J64: 45 | K64: 45 | L64: 90 | M64: 27AAACI1195H1ZMTS61315298202510 | N64: 997157 | O64: Bank charges | P64: Input Service | Q64: 2647 | R64: 45931 | S64: 45931 | T64: Yes | U64: Matched with 2B | W64: All other ITC | Z64: =_xlfn.XLOOKUP(AC64,'[9]PR Conso (Apr 25-Sep 25)'!$P:$P,'[9]PR Conso (Apr 25-Sep 25)'!$Z:$Z) -> #N/A | AB64: =AB63+1 -> 59 | AC64: =CONCATENATE(M64,AB64) -> 27AAACI1195H1ZMTS6131529820251059
A65: 45931 | B65: 27AAACI1195H1ZM | C65: ICICI BANK LIMITED | D65: TS61898693202510 | E65: 31/10/2025 | F65: 0.17985612 | G65: 2360 | H65: 2000 | I65: 0 | J65: 180 | K65: 180 | L65: 360 | M65: 27AAACI1195H1ZMTS61898693202510 | N65: 997157 | O65: Bank charges | P65: Input Service | Q65: 2648 | R65: 45931 | S65: 45931 | T65: Yes | U65: Matched with 2B | W65: All other ITC | Z65: =_xlfn.XLOOKUP(AC65,'[9]PR Conso (Apr 25-Sep 25)'!$P:$P,'[9]PR Conso (Apr 25-Sep 25)'!$Z:$Z) -> #N/A | AB65: =AB64+1 -> 60 | AC65: =CONCATENATE(M65,AB65) -> 27AAACI1195H1ZMTS6189869320251060
A66: 45931 | B66: 27AAACI1195H1ZM | C66: ICICI BANK LIMITED | D66: TS63153615202510 | E66: 31/10/2025 | F66: 0.17985612 | G66: 4720 | H66: 4000 | I66: 0 | J66: 360 | K66: 360 | L66: 720 | M66: 27AAACI1195H1ZMTS63153615202510 | N66: 997157 | O66: Bank charges | P66: Input Service | Q66: 2649 | R66: 45931 | S66: 45931 | T66: Yes | U66: Matched with 2B | W66: All other ITC | Z66: =_xlfn.XLOOKUP(AC66,'[9]PR Conso (Apr 25-Sep 25)'!$P:$P,'[9]PR Conso (Apr 25-Sep 25)'!$Z:$Z) -> #N/A | AB66: =AB65+1 -> 61 | AC66: =CONCATENATE(M66,AB66) -> 27AAACI1195H1ZMTS6315361520251061
A67: 45931 | B67: 27AAIFR9573K1ZE | C67: RAJIV ELECTRONICS | D67: HCA6254 | E67: 13/10/2025 | F67: 0.17985612 | G67: 575.26 | H67: 487.5 | I67: 0 | J67: 43.88 | K67: 43.88 | L67: 87.76 | M67: 27AAIFR9573K1ZEHCA6254 | N67: 773833 | O67: Hardware/Software Expenses | P67: Inputs | Q67: 2650 | R67: 45931 | S67: 45931 | T67: Yes | U67: Matched with 2B | W67: All other ITC | Z67: =_xlfn.XLOOKUP(AC67,'[9]PR Conso (Apr 25-Sep 25)'!$P:$P,'[9]PR Conso (Apr 25-Sep 25)'!$Z:$Z) -> #N/A | AB67: =AB66+1 -> 62 | AC67: =CONCATENATE(M67,AB67) -> 27AAIFR9573K1ZEHCA625462
A68: 45931 | B68: 36AAJCA3639B1ZX | C68: M/S ARGUS EMBEDDED SYSTEMS PRIVATE LIMITED | D68: AE-INV-2526-0899 | E68: 31/10/2025 | F68: 0.17985612 | G68: 275553.6 | H68: 233520 | I68: 42033.6 | J68: 0 | K68: 0 | L68: 42033.6 | M68: 36AAJCA3639B1ZXAE-INV-2526-0899 | N68: 998112 | O68: Professional Fees | P68: Input Service | Q68: 2651 | R68: 45931 | S68: 45931 | T68: Yes | U68: Matched with 2B | W68: All other ITC | Z68: =_xlfn.XLOOKUP(AC68,'[9]PR Conso (Apr 25-Sep 25)'!$P:$P,'[9]PR Conso (Apr 25-Sep 25)'!$Z:$Z) -> #N/A | AB68: =AB67+1 -> 63 | AC68: =CONCATENATE(M68,AB68) -> 36AAJCA3639B1ZXAE-INV-2526-089963
A69: 45931 | B69: 36AAJCA3639B1ZX | C69: M/S ARGUS EMBEDDED SYSTEMS PRIVATE LIMITED | D69: AE-INV-2526-0900 | E69: 31/10/2025 | F69: 0.17985612 | G69: 75331.2 | H69: 63840 | I69: 11491.2 | J69: 0 | K69: 0 | L69: 11491.2 | M69: 36AAJCA3639B1ZXAE-INV-2526-0900 | N69: 998112 | O69: Professional Fees | P69: Input Service | Q69: 2652 | R69: 45931 | S69: 45931 | T69: Yes | U69: Matched with 2B | W69: All other ITC | Z69: =_xlfn.XLOOKUP(AC69,'[9]PR Conso (Apr 25-Sep 25)'!$P:$P,'[9]PR Conso (Apr 25-Sep 25)'!$Z:$Z) -> #N/A | AB69: =AB68+1 -> 64 | AC69: =CONCATENATE(M69,AB69) -> 36AAJCA3639B1ZXAE-INV-2526-090064
A70: 45931 | B70: 27AZJPG1481H1ZC | C70: OM SAI SECURITY AND MANPOWER SERVICES / OM SAI TOURS AND TRAVELS | D70: 5760 | E70: 31/10/2025 | F70: 0.05 | G70: 7555.8 | H70: 7196 | I70: 0 | J70: 179.9 | K70: 179.9 | L70: 359.8 | M70: 27AZJPG1481H1ZC5760 | N70: 996813 | O70: Cab rent charges | P70: Input Service | Q70: 2653 | R70: 45931 | S70: 45931 | T70: Yes | U70: Matched with 2B | W70: All other ITC | Z70: =_xlfn.XLOOKUP(AC70,'[9]PR Conso (Apr 25-Sep 25)'!$P:$P,'[9]PR Conso (Apr 25-Sep 25)'!$Z:$Z) -> #N/A | AB70: =AB69+1 -> 65 | AC70: =CONCATENATE(M70,AB70) -> 27AZJPG1481H1ZC576065
A71: 45931 | B71: 27AZJPG1481H1ZC | C71: OM SAI SECURITY AND MANPOWER SERVICES / OM SAI TOURS AND TRAVELS | D71: 5761 | E71: 31/10/2025 | F71: 0.05 | G71: 5218.5 | H71: 4970 | I71: 0 | J71: 124.25 | K71: 124.25 | L71: 248.5 | M71: 27AZJPG1481H1ZC5761 | N71: 996813 | O71: Cab rent charges | P71: Input Service | Q71: 2654 | R71: 45931 | S71: 45931 | T71: Yes | U71: Matched with 2B | W71: All other ITC | Z71: =_xlfn.XLOOKUP(AC71,'[9]PR Conso (Apr 25-Sep 25)'!$P:$P,'[9]PR Conso (Apr 25-Sep 25)'!$Z:$Z) -> #N/A | AB71: =AB70+1 -> 66 | AC71: =CONCATENATE(M71,AB71) -> 27AZJPG1481H1ZC576166
A72: 45931 | B72: 27AZJPG1481H1ZC | C72: OM SAI SECURITY AND MANPOWER SERVICES / OM SAI TOURS AND TRAVELS | D72: 5762 | E72: 31/10/2025 | F72: 0.05 | G72: 5101.96 | H72: 4859 | I72: 0 | J72: 121.48 | K72: 121.48 | L72: 242.96 | M72: 27AZJPG1481H1ZC5762 | N72: 996813 | O72: Cab rent charges | P72: Input Service | Q72: 2655 | R72: 45931 | S72: 45931 | T72: Yes | U72: Matched with 2B | W72: All other ITC | Z72: =_xlfn.XLOOKUP(AC72,'[9]PR Conso (Apr 25-Sep 25)'!$P:$P,'[9]PR Conso (Apr 25-Sep 25)'!$Z:$Z) -> #N/A | AB72: =AB71+1 -> 67 | AC72: =CONCATENATE(M72,AB72) -> 27AZJPG1481H1ZC576267
A73: 45931 | B73: 07AAACJ0054A1ZD | C73: JETWAYS TRAVELS PVT.LTD. | D73: DP523155 | E73: 07/10/2025 | F73: 0.17985612 | G73: 118 | H73: 100 | I73: 18 | J73: 0 | K73: 0 | L73: 18 | M73: 07AAACJ0054A1ZDDP523155 | N73: 998551 | O73: Travel Expenses | P73: Input Service | Q73: 2710 | R73: 45931 | S73: 45931 | T73: Yes | U73: Matched with 2B | W73: All other ITC | Z73: =_xlfn.XLOOKUP(AC73,'[9]PR Conso (Apr 25-Sep 25)'!$P:$P,'[9]PR Conso (Apr 25-Sep 25)'!$Z:$Z) -> #N/A | AA73: =VLOOKUP(M73,[8]!Table2[Concatenate],1,0) -> #REF! | AB73: =AB72+1 -> 68 | AC73: =CONCATENATE(M73,AB73) -> 07AAACJ0054A1ZDDP52315568
A74: 45931 | B74: 27AABCM2461K1ZF | C74: MAGARPATTA TOWNSHIP DEVP & CONST COMPANY LTD | D74: PM012610/019447 | E74: 03/10/2025 | F74: 0.18656716 | G74: 127.2 | H74: 107.2 | I74: 0 | J74: 10 | K74: 10 | L74: 20 | M74: 27AABCM2461K1ZFPM012610/019447 | N74: 997221 | O74: Repairs & Maintenance-Leasehold premises | P74: Input Service | Q74: 2709 | R74: 45931 | S74: 45931 | T74: Yes | U74: Matched with 2B | W74: All other ITC | Z74: =_xlfn.XLOOKUP(AC74,'[9]PR Conso (Apr 25-Sep 25)'!$P:$P,'[9]PR Conso (Apr 25-Sep 25)'!$Z:$Z) -> #N/A | AA74: =VLOOKUP(M74,[8]!Table2[Concatenate],1,0) -> #REF! | AB74: =AB73+1 -> 69 | AC74: =CONCATENATE(M74,AB74) -> 27AABCM2461K1ZFPM012610/01944769
A75: 45931 | B75: 27AABCK3418J1ZK | C75: KANJI FOREX PRIVATE LIMITED | D75: SP/2526/1/4179 | E75: 08/10/2025 | F75: 0.17985612 | G75: 295 | H75: 250 | I75: 0 | J75: 22.5 | K75: 22.5 | L75: 45 | M75: 27AABCK3418J1ZKSP/2526/1/4179 | N75: 997157 | O75: Foreign exchange services | P75: Input Service | Q75: 2732 | R75: 45931 | S75: 45931 | T75: Yes | U75: Matched with 2B | W75: All other ITC | Z75: =_xlfn.XLOOKUP(AC75,'[9]PR Conso (Apr 25-Sep 25)'!$P:$P,'[9]PR Conso (Apr 25-Sep 25)'!$Z:$Z) -> #N/A | AA75: =VLOOKUP(M75,[8]!Table2[Concatenate],1,0) -> #REF! | AB75: =AB74+1 -> 70 | AC75: =CONCATENATE(M75,AB75) -> 27AABCK3418J1ZKSP/2526/1/417970
A76: 45931 | B76: 27AABCK3418J1ZK | C76: KANJI FOREX PRIVATE LIMITED | D76: PP/2526/2/633 | E76: 29/10/2025 | F76: 0.17985612 | G76: 295 | H76: 250 | I76: 0 | J76: 22.5 | K76: 22.5 | L76: 45 | M76: 27AABCK3418J1ZKPP/2526/2/633 | N76: 997157 | O76: Foreign exchange services | P76: Input Service | Q76: 2731 | R76: 45931 | S76: 45931 | T76: Yes | U76: Matched with 2B | W76: All other ITC | Z76: =_xlfn.XLOOKUP(AC76,'[9]PR Conso (Apr 25-Sep 25)'!$P:$P,'[9]PR Conso (Apr 25-Sep 25)'!$Z:$Z) -> #N/A | AA76: =VLOOKUP(M76,[8]!Table2[Concatenate],1,0) -> #REF! | AB76: =AB75+1 -> 71 | AC76: =CONCATENATE(M76,AB76) -> 27AABCK3418J1ZKPP/2526/2/63371
A77: 45931 | B77: 27AABCK3418J1ZK | C77: KANJI FOREX PRIVATE LIMITED | D77: PP/2526/2/628 | E77: 27/10/2025 | F77: 0.17985612 | G77: 295 | H77: 250 | I77: 0 | J77: 22.5 | K77: 22.5 | L77: 45 | M77: 27AABCK3418J1ZKPP/2526/2/628 | N77: 997157 | O77: Foreign exchange services | P77: Input Service | Q77: 2730 | R77: 45931 | S77: 45931 | T77: Yes | U77: Matched with 2B | W77: All other ITC | Z77: =_xlfn.XLOOKUP(AC77,'[9]PR Conso (Apr 25-Sep 25)'!$P:$P,'[9]PR Conso (Apr 25-Sep 25)'!$Z:$Z) -> #N/A | AA77: =VLOOKUP(M77,[8]!Table2[Concatenate],1,0) -> #REF! | AB77: =AB76+1 -> 72 | AC77: =CONCATENATE(M77,AB77) -> 27AABCK3418J1ZKPP/2526/2/62872
A78: 45931 | B78: 27AABCK3418J1ZK | C78: KANJI FOREX PRIVATE LIMITED | D78: PP/2526/2/573 | E78: 03/10/2025 | F78: 0.17985612 | G78: 353.06 | H78: 299.2 | I78: 0 | J78: 26.93 | K78: 26.93 | L78: 53.86 | M78: 27AABCK3418J1ZKPP/2526/2/573 | N78: 997157 | O78: Foreign exchange services | P78: Input Service | Q78: 2729 | R78: 45931 | S78: 45931 | T78: Yes | U78: Matched with 2B | W78: All other ITC | Z78: =_xlfn.XLOOKUP(AC78,'[9]PR Conso (Apr 25-Sep 25)'!$P:$P,'[9]PR Conso (Apr 25-Sep 25)'!$Z:$Z) -> #N/A | AA78: =VLOOKUP(M78,[8]!Table2[Concatenate],1,0) -> #REF! | AB78: =AB77+1 -> 73 | AC78: =CONCATENATE(M78,AB78) -> 27AABCK3418J1ZKPP/2526/2/57373
A79: 45931 | B79: 27AAEFP1428R1ZS | C79: PRICE WATERHOUSE & CO LLP | D79: 19226077636 | E79: 29/10/2025 | F79: 0.17985612 | G79: 1930059 | H79: 1635643 | I79: 0 | J79: 147208 | K79: 147208 | L79: 294416 | M79: 27AAEFP1428R1ZS19226077636 | N79: 998231 | O79: Professional Fees | P79: Input Service | Q79: 2725 | R79: 45931 | S79: 45931 | T79: Yes | U79: Matched with 2B | W79: All other ITC | Z79: =_xlfn.XLOOKUP(AC79,'[9]PR Conso (Apr 25-Sep 25)'!$P:$P,'[9]PR Conso (Apr 25-Sep 25)'!$Z:$Z) -> #N/A | AA79: =VLOOKUP(M79,[8]!Table2[Concatenate],1,0) -> #REF! | AB79: =AB78+1 -> 74 | AC79: =CONCATENATE(M79,AB79) -> 27AAEFP1428R1ZS1922607763674
A80: 45931 | B80: 27AAACT2209D2ZT | C80: TUV INDIA PVT LTD. | D80: MH2526015870 | E80: 27/10/2025 | F80: 0.17985612 | G80: 1045480 | H80: 886000 | I80: 0 | J80: 79740 | K80: 79740 | L80: 159480 | M80: 27AAACT2209D2ZTMH2526015870 | N80: 998346 | O80: Professional Fees | P80: Input Service | Q80: 2727 | R80: 45931 | S80: 45931 | T80: Yes | U80: Matched with 2B | W80: All other ITC | Z80: =_xlfn.XLOOKUP(AC80,'[9]PR Conso (Apr 25-Sep 25)'!$P:$P,'[9]PR Conso (Apr 25-Sep 25)'!$Z:$Z) -> #N/A | AA80: =VLOOKUP(M80,[8]!Table2[Concatenate],1,0) -> #REF! | AB80: =AB79+1 -> 75 | AC80: =CONCATENATE(M80,AB80) -> 27AAACT2209D2ZTMH252601587075
A81: 45931 | B81: 27AAACA4269Q1Z6 | C81: MIZUHO CAPSAVE FINANCE PRIVATE LIMITED | D81: B1MH2526/005845 | E81: 01/10/2025 | F81: 0.17985612 | G81: 834440.41 | H81: 707152.89 | I81: 0 | J81: 63643.76 | K81: 63643.76 | L81: 127287.52 | M81: 27AAACA4269Q1Z6B1MH2526/005845 | N81: 997315 | O81: Rent - Equipment | P81: Input Service | Q81: 2682 | R81: 45931 | S81: 45931 | T81: Yes | U81: Matched with 2B | W81: All other ITC | Z81: =_xlfn.XLOOKUP(AC81,'[9]PR Conso (Apr 25-Sep 25)'!$P:$P,'[9]PR Conso (Apr 25-Sep 25)'!$Z:$Z) -> #N/A | AA81: =VLOOKUP(M81,[8]!Table2[Concatenate],1,0) -> #REF! | AB81: =AB80+1 -> 76 | AC81: =CONCATENATE(M81,AB81) -> 27AAACA4269Q1Z6B1MH2526/00584576
A82: 45931 | B82: 27AABCM2461K1ZF | C82: MAGARPATTA TOWNSHIP DEVP & CONST COMPANY LTD | D82: PM012610/019446 | E82: 03/10/2025 | F82: 0.17985612 | G82: 506.8 | H82: 428.8 | I82: 0 | J82: 39 | K82: 39 | L82: 78 | M82: 27AABCM2461K1ZFPM012610/019446 | N82: 997221 | O82: Repairs & Maintenance-Leasehold premises | P82: Input Service | Q82: 2708 | R82: 45931 | S82: 45931 | T82: Yes | U82: Matched with 2B | W82: All other ITC | Z82: =_xlfn.XLOOKUP(AC82,'[9]PR Conso (Apr 25-Sep 25)'!$P:$P,'[9]PR Conso (Apr 25-Sep 25)'!$Z:$Z) -> #N/A | AA82: =VLOOKUP(M82,[8]!Table2[Concatenate],1,0) -> #REF! | AB82: =AB81+1 -> 77 | AC82: =CONCATENATE(M82,AB82) -> 27AABCM2461K1ZFPM012610/01944677
A83: 45931 | B83: 27AABCK3418J1ZK | C83: KANJI FOREX PRIVATE LIMITED | D83: SP/2526/2/2449 | E83: 09/10/2025 | F83: 0.17985612 | G83: 531 | H83: 450 | I83: 0 | J83: 40.5 | K83: 40.5 | L83: 81 | M83: 27AABCK3418J1ZKSP/2526/2/2449 | N83: 997157 | O83: Foreign exchange services | P83: Input Service | Q83: 2734 | R83: 45931 | S83: 45931 | T83: Yes | U83: Matched with 2B | W83: All other ITC | Z83: =_xlfn.XLOOKUP(AC83,'[9]PR Conso (Apr 25-Sep 25)'!$P:$P,'[9]PR Conso (Apr 25-Sep 25)'!$Z:$Z) -> #N/A | AA83: =VLOOKUP(M83,[8]!Table2[Concatenate],1,0) -> #REF! | AB83: =AB82+1 -> 78 | AC83: =CONCATENATE(M83,AB83) -> 27AABCK3418J1ZKSP/2526/2/244978
A84: 45931 | B84: 07AAACJ0054A1ZD | C84: JETWAYS TRAVELS PVT.LTD. | D84: IP502500 | E84: 08/10/2025 | F84: 0.17985612 | G84: 826 | H84: 700 | I84: 126 | J84: 0 | K84: 0 | L84: 126 | M84: 07AAACJ0054A1ZDIP502500 | N84: 998551 | O84: Travel Expenses | P84: Input Service | Q84: 2721 | R84: 45931 | S84: 45931 | T84: Yes | U84: Matched with 2B | W84: All other ITC | Z84: =_xlfn.XLOOKUP(AC84,'[9]PR Conso (Apr 25-Sep 25)'!$P:$P,'[9]PR Conso (Apr 25-Sep 25)'!$Z:$Z) -> #N/A | AA84: =VLOOKUP(M84,[8]!Table2[Concatenate],1,0) -> #REF! | AB84: =AB83+1 -> 79 | AC84: =CONCATENATE(M84,AB84) -> 07AAACJ0054A1ZDIP50250079
A85: 45931 | B85: 07AAACJ0054A1ZD | C85: JETWAYS TRAVELS PVT.LTD. | D85: IP502470 | E85: 07/10/2025 | F85: 0.17985612 | G85: 826 | H85: 700 | I85: 126 | J85: 0 | K85: 0 | L85: 126 | M85: 07AAACJ0054A1ZDIP502470 | N85: 998551 | O85: Travel Expenses | P85: Input Service | Q85: 2720 | R85: 45931 | S85: 45931 | T85: Yes | U85: Matched with 2B | W85: All other ITC | Z85: =_xlfn.XLOOKUP(AC85,'[9]PR Conso (Apr 25-Sep 25)'!$P:$P,'[9]PR Conso (Apr 25-Sep 25)'!$Z:$Z) -> #N/A | AA85: =VLOOKUP(M85,[8]!Table2[Concatenate],1,0) -> #REF! | AB85: =AB84+1 -> 80 | AC85: =CONCATENATE(M85,AB85) -> 07AAACJ0054A1ZDIP50247080
A86: 45931 | B86: 27AABCK3418J1ZK | C86: KANJI FOREX PRIVATE LIMITED | D86: SP/2526/2/2311 | E86: 03/10/2025 | F86: 0.17985612 | G86: 860.62 | H86: 729.34 | I86: 0 | J86: 65.64 | K86: 65.64 | L86: 131.28 | M86: 27AABCK3418J1ZKSP/2526/2/2311 | N86: 997157 | O86: Foreign exchange services | P86: Input Service | Q86: 2733 | R86: 45931 | S86: 45931 | T86: Yes | U86: Matched with 2B | W86: All other ITC | Z86: =_xlfn.XLOOKUP(AC86,'[9]PR Conso (Apr 25-Sep 25)'!$P:$P,'[9]PR Conso (Apr 25-Sep 25)'!$Z:$Z) -> #N/A | AA86: =VLOOKUP(M86,[8]!Table2[Concatenate],1,0) -> #REF! | AB86: =AB85+1 -> 81 | AC86: =CONCATENATE(M86,AB86) -> 27AABCK3418J1ZKSP/2526/2/231181
A87: 45931 | B87: 27AABCK3418J1ZK | C87: KANJI FOREX PRIVATE LIMITED | D87: SP/2526/2/2557 | E87: 15/10/2025 | F87: 0.17985612 | G87: 1052.56 | H87: 892 | I87: 0 | J87: 80.28 | K87: 80.28 | L87: 160.56 | M87: 27AABCK3418J1ZKSP/2526/2/2557 | N87: 997157 | O87: Foreign exchange services | P87: Input Service | Q87: 2735 | R87: 45931 | S87: 45931 | T87: Yes | U87: Matched with 2B | W87: All other ITC | Z87: =_xlfn.XLOOKUP(AC87,'[9]PR Conso (Apr 25-Sep 25)'!$P:$P,'[9]PR Conso (Apr 25-Sep 25)'!$Z:$Z) -> #N/A | AA87: =VLOOKUP(M87,[8]!Table2[Concatenate],1,0) -> #REF! | AB87: =AB86+1 -> 82 | AC87: =CONCATENATE(M87,AB87) -> 27AABCK3418J1ZKSP/2526/2/255782
A88: 45931 | B88: 36AABCI2726B1Z3 | C88: INTER GLOBE AVIATION LIMITED INDIGO | D88: TS1252610BE70683 | E88: 08/10/2025 | F88: 0.060837664 | G88: 3470 | H88: 3271 | I88: 199 | J88: 0 | K88: 0 | L88: 199 | M88: 36AABCI2726B1Z3TS1252610BE70683 | N88: 996425 | O88: Travel Expenses | P88: Input Service | Q88: 2668 | R88: 45931 | S88: 45931 | T88: Yes | U88: Matched with 2B | W88: All other ITC | Z88: =_xlfn.XLOOKUP(AC88,'[9]PR Conso (Apr 25-Sep 25)'!$P:$P,'[9]PR Conso (Apr 25-Sep 25)'!$Z:$Z) -> #N/A | AA88: =VLOOKUP(M88,[8]!Table2[Concatenate],1,0) -> #REF! | AB88: =AB87+1 -> 83 | AC88: =CONCATENATE(M88,AB88) -> 36AABCI2726B1Z3TS1252610BE7068383
A89: 45931 | B89: 27AAECG2483J1ZE | C89: GNR SOLUTION PRIVATE LIMITED | D89: GNR/R/25-26/2657 | E89: 10/10/2025 | F89: 0.17985612 | G89: 1770 | H89: 1500 | I89: 0 | J89: 135 | K89: 135 | L89: 270 | M89: 27AAECG2483J1ZEGNR/R/25-26/2657 | N89: 997315 | O89: Rent - Equipment | P89: Input Service | Q89: 2697 | R89: 45931 | S89: 45931 | T89: Yes | U89: Matched with 2B | W89: All other ITC | Z89: =_xlfn.XLOOKUP(AC89,'[9]PR Conso (Apr 25-Sep 25)'!$P:$P,'[9]PR Conso (Apr 25-Sep 25)'!$Z:$Z) -> #N/A | AA89: =VLOOKUP(M89,[8]!Table2[Concatenate],1,0) -> #REF! | AB89: =AB88+1 -> 84 | AC89: =CONCATENATE(M89,AB89) -> 27AAECG2483J1ZEGNR/R/25-26/265784
A90: 45931 | B90: 27AABCR0111M1ZN | C90: ROYAL ORCHID HOTELS LIMITED | D90: ROCP-2526-12574 | E90: 16/10/2025 | F90: 0.05 | G90: 6037.52 | H90: 5750 | I90: 0 | J90: 143.76 | K90: 143.76 | L90: 287.52 | M90: 27AABCR0111M1ZNROCP-2526-12574 | N90: 996311 | O90: Hotel & Lodging Expenses | P90: Input Service | Q90: 2635 | R90: 45931 | S90: 45931 | T90: Yes | U90: Matched with 2B | W90: All other ITC | Z90: =_xlfn.XLOOKUP(AC90,'[9]PR Conso (Apr 25-Sep 25)'!$P:$P,'[9]PR Conso (Apr 25-Sep 25)'!$Z:$Z) -> #N/A | AA90: =VLOOKUP(M90,[8]!Table2[Concatenate],1,0) -> #REF! | AB90: =AB89+1 -> 85 | AC90: =CONCATENATE(M90,AB90) -> 27AABCR0111M1ZNROCP-2526-1257485
A91: 45931 | B91: 07AALCC6699P1ZJ | C91: COMMBITZ ESIM PRIVATE LIMITED | D91: CM202526000413 | E91: 07/10/2025 | F91: 0.17985612 | G91: 1904.52 | H91: 1614 | I91: 290.52 | J91: 0 | K91: 0 | L91: 290.52 | M91: 07AALCC6699P1ZJCM202526000413 | N91: 9984 | O91: Internet Connectivity charges | P91: Input Service | Q91: 2739 | R91: 45931 | S91: 45931 | T91: Yes | U91: Matched with 2B | W91: All other ITC | Z91: =_xlfn.XLOOKUP(AC91,'[9]PR Conso (Apr 25-Sep 25)'!$P:$P,'[9]PR Conso (Apr 25-Sep 25)'!$Z:$Z) -> #N/A | AA91: =VLOOKUP(M91,[8]!Table2[Concatenate],1,0) -> #REF! | AB91: =AB90+1 -> 86 | AC91: =CONCATENATE(M91,AB91) -> 07AALCC6699P1ZJCM20252600041386
... A94: 45931 | B94: 07AACCN6194P2ZQ | C94: AIR INDIA LIMITED | D94: 072612BP10AFD825 | E94: 25/10/2025 | F94: 0.05 | G94: 7353 | H94: 7002 | I94: 351 | J94: 0 | K94: 0 | L94: 351 | M94: 07AACCN6194P2ZQ072612BP10AFD825 | N94: 996425 | O94: Travel Expenses | P94: Input Service | Q94: 2681 | R94: 45931 | S94: 45931 | T94: Yes | U94: Matched with 2B | W94: All other ITC | Z94: =_xlfn.XLOOKUP(AC94,'[9]PR Conso (Apr 25-Sep 25)'!$P:$P,'[9]PR Conso (Apr 25-Sep 25)'!$Z:$Z) -> #N/A | AA94: =VLOOKUP(M94,[8]!Table2[Concatenate],1,0) -> #REF! | AB94: =AB93+1 -> 89 | AC94: =CONCATENATE(M94,AB94) -> 07AACCN6194P2ZQ072612BP10AFD82589
A95: 45931 | B95: 27AAGCJ1813R1Z5 | C95: JYT LOGISTICS PRIVATE LIMITED | D95: 9520 | E95: 11/10/2025 | F95: 0.17985612 | G95: 3540 | H95: 3000 | I95: 0 | J95: 270 | K95: 270 | L95: 540 | M95: 27AAGCJ1813R1Z59520 | N95: 996712 | O95: Postage and Courier | P95: Input Service | Q95: 2726 | R95: 45931 | S95: 45931 | T95: Yes | U95: Matched with 2B | W95: All other ITC | Z95: =_xlfn.XLOOKUP(AC95,'[9]PR Conso (Apr 25-Sep 25)'!$P:$P,'[9]PR Conso (Apr 25-Sep 25)'!$Z:$Z) -> #N/A | AA95: =VLOOKUP(M95,[8]!Table2[Concatenate],1,0) -> #REF! | AB95: =AB94+1 -> 90 | AC95: =CONCATENATE(M95,AB95) -> 27AAGCJ1813R1Z5952090
A96: 45931 | B96: 27BMWPD2551E2ZZ | C96: ROOTS OFFICE SOLUTIONS | D96: S0006119 | E96: 21/09/2025 | F96: 0.16846737 | G96: 4620.12 | H96: 3954 | I96: 0 | J96: 333.06 | K96: 333.06 | L96: 666.12 | M96: 27BMWPD2551E2ZZS0006119 | N96: 3926 | O96: Houskeeping Material Charges | P96: Inputs | Q96: 2689 | R96: 45931 | S96: 45931 | T96: Yes | U96: Matched with 2B | W96: All other ITC | Z96: =_xlfn.XLOOKUP(AC96,'[9]PR Conso (Apr 25-Sep 25)'!$P:$P,'[9]PR Conso (Apr 25-Sep 25)'!$Z:$Z) -> #N/A | AA96: =VLOOKUP(M96,[8]!Table2[Concatenate],1,0) -> #REF! | AB96: =AB95+1 -> 91 | AC96: =CONCATENATE(M96,AB96) -> 27BMWPD2551E2ZZS000611991
A97: 45931 | B97: 27AADCP7742E1ZD | C97: PRODUCT DOSSIER SOLUTIONS INDIA PRIVATE LIMITED | D97: PDS-25186 | E97: 03/10/2025 | F97: 0.17985612 | G97: 610896.38 | H97: 517708.8 | I97: 0 | J97: 46593.79 | K97: 46593.79 | L97: 93187.58 | M97: 27AADCP7742E1ZDPDS-25186 | N97: 998313 | O97: Professional Fees | P97: Input Service | Q97: 2693 | R97: 45931 | S97: 45931 | T97: Yes | U97: Matched with 2B | W97: All other ITC | Z97: =_xlfn.XLOOKUP(AC97,'[9]PR Conso (Apr 25-Sep 25)'!$P:$P,'[9]PR Conso (Apr 25-Sep 25)'!$Z:$Z) -> #N/A | AA97: =VLOOKUP(M97,[8]!Table2[Concatenate],1,0) -> #REF! | AB97: =AB96+1 -> 92 | AC97: =CONCATENATE(M97,AB97) -> 27AADCP7742E1ZDPDS-2518692
A98: 45931 | B98: 27AAECG2483J1ZE | C98: GNR SOLUTION PRIVATE LIMITED | D98: GNR/R/25-26/2660 | E98: 10/10/2025 | F98: 0.17985612 | G98: 473126.9 | H98: 400955 | I98: 0 | J98: 36085.95 | K98: 36085.95 | L98: 72171.9 | M98: 27AAECG2483J1ZEGNR/R/25-26/2660 | N98: 997315 | O98: Rent - Equipment | P98: Input Service | Q98: 2700 | R98: 45931 | S98: 45931 | T98: Yes | U98: Matched with 2B | W98: All other ITC | Z98: =_xlfn.XLOOKUP(AC98,'[9]PR Conso (Apr 25-Sep 25)'!$P:$P,'[9]PR Conso (Apr 25-Sep 25)'!$Z:$Z) -> #N/A | AA98: =VLOOKUP(M98,[8]!Table2[Concatenate],1,0) -> #REF! | AB98: =AB97+1 -> 93 | AC98: =CONCATENATE(M98,AB98) -> 27AAECG2483J1ZEGNR/R/25-26/266093
A99: 45931 | B99: 27AATPE1292M1Z7 | C99: ERAGAM SIDHANTH REDDY | D99: OCT-2025-302 | E99: 01/10/2025 | F99: 0.17985612 | G99: 413877.92 | H99: 350744 | I99: 0 | J99: 31566.96 | K99: 31566.96 | L99: 63133.92 | M99: 27AATPE1292M1Z7OCT-2025-302 | N99: 997212 | O99: Rent-Office | P99: Input Service | Q99: 2665 | R99: 45931 | S99: 45931 | T99: Yes | U99: Matched with 2B | W99: All other ITC | Z99: =_xlfn.XLOOKUP(AC99,'[9]PR Conso (Apr 25-Sep 25)'!$P:$P,'[9]PR Conso (Apr 25-Sep 25)'!$Z:$Z) -> #N/A | AA99: =VLOOKUP(M99,[8]!Table2[Concatenate],1,0) -> #REF! | AB99: =AB98+1 -> 94 | AC99: =CONCATENATE(M99,AB99) -> 27AATPE1292M1Z7OCT-2025-30294
A100: 45931 | B100: 27AATPE1295N1Z2 | C100: ERAGAM SANJEETH REDDY | D100: OCT-2025-303 | E100: 01/10/2025 | F100: 0.17985612 | G100: 413877.92 | H100: 350744 | I100: 0 | J100: 31566.96 | K100: 31566.96 | L100: 63133.92 | M100: 27AATPE1295N1Z2OCT-2025-303 | N100: 997212 | O100: Rent-Office | P100: Input Service | Q100: 2701 | R100: 45931 | S100: 45931 | T100: Yes | U100: Matched with 2B | W100: All other ITC | Z100: =_xlfn.XLOOKUP(AC100,'[9]PR Conso (Apr 25-Sep 25)'!$P:$P,'[9]PR Conso (Apr 25-Sep 25)'!$Z:$Z) -> #N/A | AA100: =VLOOKUP(M100,[8]!Table2[Concatenate],1,0) -> #REF! | AB100: =AB99+1 -> 95 | AC100: =CONCATENATE(M100,AB100) -> 27AATPE1295N1Z2OCT-2025-30395
A101: 45931 | B101: 27AATPE1292M1Z7 | C101: ERAGAM SIDHANTH REDDY | D101: OCT-2025-301 | E101: 01/10/2025 | F101: 0.17985612 | G101: 393496.96 | H101: 333472 | I101: 0 | J101: 30012.48 | K101: 30012.48 | L101: 60024.96 | M101: 27AATPE1292M1Z7OCT-2025-301 | N101: 997212 | O101: Rent-Office | P101: Input Service | Q101: 2664 | R101: 45931 | S101: 45931 | T101: Yes | U101: Matched with 2B | W101: All other ITC | Z101: =_xlfn.XLOOKUP(AC101,'[9]PR Conso (Apr 25-Sep 25)'!$P:$P,'[9]PR Conso (Apr 25-Sep 25)'!$Z:$Z) -> #N/A | AA101: =VLOOKUP(M101,[8]!Table2[Concatenate],1,0) -> #REF! | AB101: =AB100+1 -> 96 | AC101: =CONCATENATE(M101,AB101) -> 27AATPE1292M1Z7OCT-2025-30196
A102: 45931 | B102: 27AATPE1295N1Z2 | C102: ERAGAM SANJEETH REDDY | D102: OCT-2025-304 | E102: 01/10/2025 | F102: 0.17985612 | G102: 393496.96 | H102: 333472 | I102: 0 | J102: 30012.48 | K102: 30012.48 | L102: 60024.96 | M102: 27AATPE1295N1Z2OCT-2025-304 | N102: 997212 | O102: Rent-Office | P102: Input Service | Q102: 2702 | R102: 45931 | S102: 45931 | T102: Yes | U102: Matched with 2B | W102: All other ITC | Z102: =_xlfn.XLOOKUP(AC102,'[9]PR Conso (Apr 25-Sep 25)'!$P:$P,'[9]PR Conso (Apr 25-Sep 25)'!$Z:$Z) -> #N/A | AA102: =VLOOKUP(M102,[8]!Table2[Concatenate],1,0) -> #REF! | AB102: =AB101+1 -> 97 | AC102: =CONCATENATE(M102,AB102) -> 27AATPE1295N1Z2OCT-2025-30497
A103: 45931 | B103: 27ABJCS6128G1Z4 | C103: SSBC GLOBAL LOGISTICS PRIVATE LIMITED | D103: 955/2025-26 | E103: 24/10/2025 | F103: 0.17985612 | G103: 5254.54 | H103: 4453 | I103: 0 | J103: 400.77 | K103: 400.77 | L103: 801.54 | M103: 27ABJCS6128G1Z4955/2025-26 | N103: 996812 | O103: Postage & Courier | P103: Input Service | Q103: 2637 | R103: 45931 | S103: 45931 | T103: Yes | U103: Matched with 2B | W103: All other ITC | Z103: =_xlfn.XLOOKUP(AC103,'[9]PR Conso (Apr 25-Sep 25)'!$P:$P,'[9]PR Conso (Apr 25-Sep 25)'!$Z:$Z) -> #N/A | AA103: =VLOOKUP(M103,[8]!Table2[Concatenate],1,0) -> #REF! | AB103: =AB102+1 -> 98 | AC103: =CONCATENATE(M103,AB103) -> 27ABJCS6128G1Z4955/2025-2698
A104: 45931 | B104: 27AAACH1458C1ZZ | C104: TATA TELESERVICES MAHARASHTRA LIMITED | D104: 2171776949 | E104: 15/10/2025 | F104: 0.17985612 | G104: 6478.2 | H104: 5490 | I104: 0 | J104: 494.1 | K104: 494.1 | L104: 988.2 | M104: 27AAACH1458C1ZZ2171776949 | N104: 998412 | O104: Internet Connectivity charges | P104: Input Service | Q104: 2630 | R104: 45931 | S104: 45931 | T104: Yes | U104: Matched with 2B | W104: All other ITC | Z104: =_xlfn.XLOOKUP(AC104,'[9]PR Conso (Apr 25-Sep 25)'!$P:$P,'[9]PR Conso (Apr 25-Sep 25)'!$Z:$Z) -> #N/A | AA104: =VLOOKUP(M104,[8]!Table2[Concatenate],1,0) -> #REF! | AB104: =AB103+1 -> 99 | AC104: =CONCATENATE(M104,AB104) -> 27AAACH1458C1ZZ217177694999
A105: 45931 | B105: 27AAACE6958L1Z4 | C105: EMBEE SOFTWARE P LTD | D105: MEGSI26/20548 | E105: 30/10/2025 | F105: 0.17985612 | G105: 287580.94 | H105: 243712.66 | I105: 0 | J105: 21934.14 | K105: 21934.14 | L105: 43868.28 | M105: 27AAACE6958L1Z4MEGSI26/20548 | N105: 997331 | O105: Membership & Subscription | P105: Input Service | Q105: 2673 | R105: 45931 | S105: 45931 | T105: Yes | U105: Matched with 2B | W105: All other ITC | Z105: =_xlfn.XLOOKUP(AC105,'[9]PR Conso (Apr 25-Sep 25)'!$P:$P,'[9]PR Conso (Apr 25-Sep 25)'!$Z:$Z) -> #N/A | AA105: =VLOOKUP(M105,[8]!Table2[Concatenate],1,0) -> #REF! | AB105: =AB104+1 -> 100 | AC105: =CONCATENATE(M105,AB105) -> 27AAACE6958L1Z4MEGSI26/20548100
A106: 45931 | B106: 36AAFCK5835K1Z6 | C106: KEKA TECHNOLOGIES | D106: K06613-0009 | E106: 14/10/2025 | F106: 0.17985612 | G106: 271178.51 | H106: 229812.3 | I106: 41366.21 | J106: 0 | K106: 0 | L106: 41366.21 | M106: 36AAFCK5835K1Z6K06613-0009 | N106: 997331 | O106: Membership & Subscription | P106: Input Service | Q106: 2602 | R106: 45931 | S106: 45931 | T106: Yes | U106: Matched with 2B | W106: All other ITC | Z106: =_xlfn.XLOOKUP(AC106,'[9]PR Conso (Apr 25-Sep 25)'!$P:$P,'[9]PR Conso (Apr 25-Sep 25)'!$Z:$Z) -> #N/A | AA106: =VLOOKUP(M106,[8]!Table2[Concatenate],1,0) -> #REF! | AB106: =AB105+1 -> 101 | AC106: =CONCATENATE(M106,AB106) -> 36AAFCK5835K1Z6K06613-0009101
A107: 45931 | B107: 07AAJCA9880A1ZL | C107: AMAZON WEB SERVICES INDIA PRIVATE LIMITED | D107: AIN2526002290554 | E107: 02/10/2025 | F107: 0.17985612 | G107: 181764.97 | H107: 154038.11 | I107: 27726.86 | J107: 0 | K107: 0 | L107: 27726.86 | M107: 07AAJCA9880A1ZLAIN2526002290554 | N107: 998315 | O107: Membership & Subscription | P107: Input Service | Q107: 2674 | R107: 45931 | S107: 45931 | T107: Yes | U107: Matched with 2B | W107: All other ITC | Z107: =_xlfn.XLOOKUP(AC107,'[9]PR Conso (Apr 25-Sep 25)'!$P:$P,'[9]PR Conso (Apr 25-Sep 25)'!$Z:$Z) -> #N/A | AA107: =VLOOKUP(M107,[8]!Table2[Concatenate],1,0) -> #REF! | AB107: =AB106+1 -> 102 | AC107: =CONCATENATE(M107,AB107) -> 07AAJCA9880A1ZLAIN2526002290554102
...

Sheet 2B Listing 
A5: Type | B5: GSTIN and Invoice Number | C5: Sr. No. | D5: GSTIN of supplier | E5: Trade/Legal name of the supplier | F5: Invoice number | G5: Invoice type | H5: Invoice Date | I5: Invoice Value(₹) | J5: Place of supply | K5: Supply Attract Reverse Charge | L5: Rate(%) | M5: Taxable Value (₹) | N5: Integrated Tax(₹) | O5: Central Tax(₹) | P5: State/UT Tax(₹) | Q5: Cess(₹) | R5: GSTR-1/IFF/GSTR-1A/GSTR-5 Period | S5: GSTR-1/IFF/GSTR-1A/GSTR-5 Filing Date | T5: ITC Availability | U5: Reason | V5: Applicable % of Tax Rate | W5: Source | X5: IRN | Y5: IRN Date | Z5: Debit Note/Credit Note | AA5: Total Tax
A6: B2B | B6: =CONCATENATE(D6,F6) -> 29AAGCI4343D1ZOTI-206002 | C6: 1 | D6: 29AAGCI4343D1ZO | E6: Legal Name of the Business INTERNATIONAL KNOWLEDGE ACADEMY PRIVATE LIMITED | F6: TI-206002 | G6: Regular | H6: 45762 | I6: 53100 | J6: Maharashtra | K6: No | M6: 45000 | N6: 8100 | O6: 0 | P6: 0 | Q6: 0 | R6: Apr'25 | S6: 10/05/2025 | T6: Yes | V6: 100%
A7: B2B | B7: =CONCATENATE(D7,F7) -> 36AEUPV4314A1ZE002/2025-2026 | C7: =C6+1 -> 2 | D7: 36AEUPV4314A1ZE | E7: Vegesna Akshaya Avyanga Industries | F7: 002/2025-2026 | G7: Regular | H7: 45777 | I7: 324500 | J7: Maharashtra | K7: No | M7: 275000 | N7: 49500 | O7: 0 | P7: 0 | Q7: 0 | R7: Apr'25 | S7: 10/05/2025 | T7: Yes | V7: 100%
A8: B2B | B8: =CONCATENATE(D8,F8) -> 29AAECC4477E1ZJIN-14409-6 | C8: =C7+1 -> 3 | D8: 29AAECC4477E1ZJ | E8: CART2INDIA ONLINE RETAIL PRIVATE LIMITED | F8: IN-14409-6 | G8: Regular | H8: 45720 | I8: 3948 | J8: Maharashtra | K8: No | M8: 3345.76 | N8: 602.24 | O8: 0 | P8: 0 | Q8: 0 | R8: Mar'25 | S8: 20/04/2025 | T8: Yes | V8: 100%
A9: B2B | B9: =CONCATENATE(D9,F9) -> 27AADCN9802F1ZGUCF/DT0425/17644 | C9: =C8+1 -> 4 | D9: 27AADCN9802F1ZG | E9: NATIONAL SECURITIES DEPOSITORY LIMITED | F9: UCF/DT0425/17644 | G9: Regular | H9: 45762 | I9: 26550 | J9: Maharashtra | K9: No | M9: 22500 | N9: 0 | O9: 2025 | P9: 2025 | Q9: 0 | R9: Apr'25 | S9: 11/05/2025 | T9: Yes | V9: 100%
A10: B2B | B10: =CONCATENATE(D10,F10) -> 27BMWPD2551E2ZZS0005621 | C10: =C9+1 -> 5 | D10: 27BMWPD2551E2ZZ | E10: ROOTS OFFICE SOLUTIONS | F10: S0005621 | G10: Regular | H10: 45775 | I10: 4446 | J10: Maharashtra | K10: No | M10: 3856.5 | N10: 0 | O10: 294.52 | P10: 294.52 | Q10: 0 | R10: Apr'25 | S10: 10/05/2025 | T10: Yes | V10: 100%
A11: B2B | B11: =CONCATENATE(D11,F11) -> 27BMWPD2551E2ZZS0005622 | C11: =C10+1 -> 6 | D11: 27BMWPD2551E2ZZ | E11: ROOTS OFFICE SOLUTIONS | F11: S0005622 | G11: Regular | H11: 45775 | I11: 13273 | J11: Maharashtra | K11: No | M11: 11276.5 | N11: 0 | O11: 998.34 | P11: 998.34 | Q11: 0 | R11: Apr'25 | S11: 10/05/2025 | T11: Yes | V11: 100%
A12: B2B | B12: =CONCATENATE(D12,F12) -> 27AAJCC9783E1Z7BOM5-286762 | C12: =C11+1 -> 7 | D12: 27AAJCC9783E1Z7 | E12: CLICKTECH RETAIL PRIVATE LIMITED | F12: BOM5-286762 | G12: Regular | H12: 45769 | I12: 2976.98 | J12: Maharashtra | K12: No | M12: 2522.86 | N12: 0 | O12: 227.06 | P12: 227.06 | Q12: 0 | R12: Apr'25 | S12: 10/05/2025 | T12: Yes | V12: 100%
A13: B2B | B13: =CONCATENATE(D13,F13) -> 27AABCE6624L1ZGMH/APR25/118886 | C13: =C12+1 -> 8 | D13: 27AABCE6624L1ZG | E13: ETIHAD AIRWAYS | F13: MH/APR25/118886 | G13: Regular | H13: 45777 | I13: 178838 | J13: Maharashtra | K13: No | M13: 154206 | N13: 0 | O13: 9252.5 | P13: 9252.5 | Q13: 0 | R13: Apr'25 | S13: 11/05/2025 | T13: Yes | V13: 100%
A14: B2B | B14: =CONCATENATE(D14,F14) -> 33ACTFS8937K1Z7MAA4-122 | C14: =C13+1 -> 9 | D14: 33ACTFS8937K1Z7 | E14: STOK INTERNATIONAL | F14: MAA4-122 | G14: Regular | H14: 45772 | I14: 4974 | J14: Maharashtra | K14: No | M14: 4215.26 | N14: 758.74 | O14: 0 | P14: 0 | Q14: 0 | R14: Apr'25 | S14: 07/05/2025 | T14: Yes | V14: 100%
A15: B2B | B15: =CONCATENATE(D15,F15) -> 27AAACE6958L1Z4MEGSI26/20052 | C15: =C14+1 -> 10 | D15: 27AAACE6958L1Z4 | E15: EMBEE SOFTWARE P LTD | F15: MEGSI26/20052 | G15: Regular | H15: 45775 | I15: 270939.9 | J15: Maharashtra | K15: No | M15: 229610.08 | N15: 0 | O15: 20664.91 | P15: 20664.91 | Q15: 0 | R15: Apr'25 | S15: 07/05/2025 | T15: Yes | V15: 100%
A16: B2B | B16: =CONCATENATE(D16,F16) -> 27AAGCJ1813R1Z56276 | C16: =C15+1 -> 11 | D16: 27AAGCJ1813R1Z5 | E16: JYT LOGISTICS PRIVATE LIMITED | F16: 6276 | G16: Regular | H16: 45755 | I16: 3540 | J16: Maharashtra | K16: No | M16: 3000 | N16: 0 | O16: 270 | P16: 270 | Q16: 0 | R16: Apr'25 | S16: 10/05/2025 | T16: Yes | V16: 100%
A17: B2B | B17: =CONCATENATE(D17,F17) -> 27AAGCJ1813R1Z56361 | C17: =C16+1 -> 12 | D17: 27AAGCJ1813R1Z5 | E17: JYT LOGISTICS PRIVATE LIMITED | F17: 6361 | G17: Regular | H17: 45759 | I17: 11800 | J17: Maharashtra | K17: No | M17: 10000 | N17: 0 | O17: 900 | P17: 900 | Q17: 0 | R17: Apr'25 | S17: 10/05/2025 | T17: Yes | V17: 100%
A18: B2B | B18: =CONCATENATE(D18,F18) -> 27AAGCJ1813R1Z56381 | C18: =C17+1 -> 13 | D18: 27AAGCJ1813R1Z5 | E18: JYT LOGISTICS PRIVATE LIMITED | F18: 6381 | G18: Regular | H18: 45759 | I18: 5310 | J18: Maharashtra | K18: No | M18: 4500 | N18: 0 | O18: 405 | P18: 405 | Q18: 0 | R18: Apr'25 | S18: 10/05/2025 | T18: Yes | V18: 100%
A19: B2B | B19: =CONCATENATE(D19,F19) -> 33AAACZ4322M2Z91025260013651 | C19: =C18+1 -> 14 | D19: 33AAACZ4322M2Z9 | E19: ZOHO CORPORATION PRIVATE LIMITED | F19: 1025260013651 | G19: Regular | H19: 45756 | I19: 12673.2 | J19: Maharashtra | K19: No | M19: 10740 | N19: 1933.2 | O19: 0 | P19: 0 | Q19: 0 | R19: Apr'25 | S19: 11/05/2025 | T19: Yes | V19: 100% | W19: E-Invoice | X19: 3fc3bbcd33510d53af58c61981acced7b981b1ea446e5ee0c3737bd4f60af1c1 | Y19: 09/04/2025
A20: B2B | B20: =CONCATENATE(D20,F20) -> 33AAACZ4322M2Z91025260034545 | C20: =C19+1 -> 15 | D20: 33AAACZ4322M2Z9 | E20: ZOHO CORPORATION PRIVATE LIMITED | F20: 1025260034545 | G20: Regular | H20: 45770 | I20: 408.37 | J20: Maharashtra | K20: No | M20: 346.08 | N20: 62.29 | O20: 0 | P20: 0 | Q20: 0 | R20: Apr'25 | S20: 11/05/2025 | T20: Yes | V20: 100% | W20: E-Invoice | X20: df446f31896b6d91daff95c079fc6daf7313aaef5962ca2d42f83c8dc6c27f8d | Y20: 23/04/2025
A21: B2B | B21: =CONCATENATE(D21,F21) -> 27ACTPJ8193Q1ZCBOM7-142 | C21: =C20+1 -> 16 | D21: 27ACTPJ8193Q1ZC | E21: PARSHVA LIGHTS | F21: BOM7-142 | G21: Regular | H21: 45710 | I21: 449 | J21: Maharashtra | K21: No | M21: 380.51 | N21: 0 | O21: 34.25 | P21: 34.25 | Q21: 0 | R21: Mar'25 | S21: 08/05/2025 | T21: Yes | V21: 100%
A22: B2B | B22: =CONCATENATE(D22,F22) -> 27ACTPJ8193Q1ZCBOM7-179 | C22: =C21+1 -> 17 | D22: 27ACTPJ8193Q1ZC | E22: PARSHVA LIGHTS | F22: BOM7-179 | G22: Regular | H22: 45716 | I22: 499 | J22: Maharashtra | K22: No | M22: 422.88 | N22: 0 | O22: 38.06 | P22: 38.06 | Q22: 0 | R22: Mar'25 | S22: 08/05/2025 | T22: Yes | V22: 100%
A23: B2B | B23: =CONCATENATE(D23,F23) -> 27AAECI7859N1ZQSOFT/009/25-26 | C23: =C22+1 -> 18 | D23: 27AAECI7859N1ZQ | E23: Maars Creative Concepts Private Limited | F23: SOFT/009/25-26 | G23: Regular | H23: 45750 | I23: 218.3 | J23: Maharashtra | K23: No | M23: 185 | N23: 0 | O23: 16.65 | P23: 16.65 | Q23: 0 | R23: Apr'25 | S23: 07/05/2025 | T23: Yes | V23: 100%
A24: B2B | B24: =CONCATENATE(D24,F24) -> 27AAECI7859N1ZQSOFT/045/25-26 | C24: =C23+1 -> 19 | D24: 27AAECI7859N1ZQ | E24: Maars Creative Concepts Private Limited | F24: SOFT/045/25-26 | G24: Regular | H24: 45765 | I24: 371.7 | J24: Maharashtra | K24: No | M24: 315 | N24: 0 | O24: 28.35 | P24: 28.35 | Q24: 0 | R24: Apr'25 | S24: 07/05/2025 | T24: Yes | V24: 100%
A25: B2B | B25: =CONCATENATE(D25,F25) -> 27AAECI7859N1ZQSOFT/070/25-26 | C25: =C24+1 -> 20 | D25: 27AAECI7859N1ZQ | E25: Maars Creative Concepts Private Limited | F25: SOFT/070/25-26 | G25: Regular | H25: 45775 | I25: 123.9 | J25: Maharashtra | K25: No | M25: 105 | N25: 0 | O25: 9.45 | P25: 9.45 | Q25: 0 | R25: Apr'25 | S25: 07/05/2025 | T25: Yes | V25: 100%
A26: B2B | B26: =CONCATENATE(D26,F26) -> 27AAECI7859N1ZQSOFT/071/25-26 | C26: =C25+1 -> 21 | D26: 27AAECI7859N1ZQ | E26: Maars Creative Concepts Private Limited | F26: SOFT/071/25-26 | G26: Regular | H26: 45775 | I26: 850 | J26: Maharashtra | K26: No | M26: 720 | N26: 0 | O26: 64.8 | P26: 64.8 | Q26: 0 | R26: Apr'25 | S26: 07/05/2025 | T26: Yes | V26: 100%
A27: B2B | B27: =CONCATENATE(D27,F27) -> 27AAFCL6396Q1ZIInvoice56 | C27: =C26+1 -> 22 | D27: 27AAFCL6396Q1ZI | E27: LEISTUNG CORE INDIA PRIVATE LIMITED | F27: Invoice56 | G27: Regular | H27: 45761 | I27: 79650 | J27: Maharashtra | K27: No | M27: 67500 | N27: 0 | O27: 6075 | P27: 6075 | Q27: 0 | R27: Apr'25 | S27: 10/05/2025 | T27: Yes | V27: 100%
A28: B2B | B28: =CONCATENATE(D28,F28) -> 27AAFCL6396Q1ZIInvoice57 | C28: =C27+1 -> 23 | D28: 27AAFCL6396Q1ZI | E28: LEISTUNG CORE INDIA PRIVATE LIMITED | F28: Invoice57 | G28: Regular | H28: 45761 | I28: 5882 | J28: Maharashtra | K28: No | M28: 4985 | N28: 0 | O28: 448.65 | P28: 448.65 | Q28: 0 | R28: Apr'25 | S28: 10/05/2025 | T28: Yes | V28: 100%
A29: B2B | B29: =CONCATENATE(D29,F29) -> 27AANCA4062G1ZN252240001264A008 | C29: =C28+1 -> 24 | D29: 27AANCA4062G1ZN | E29: M/s ADITYA BIRLA HEALTH INSURANCE CO LIMITED | F29: 252240001264A008 | G29: Regular | H29: 45754 | I29: 777.33 | J29: Maharashtra | K29: No | M29: 658.76 | N29: 0 | O29: 59.28 | P29: 59.28 | Q29: 0 | R29: Apr'25 | S29: 10/05/2025 | T29: Yes | V29: 100%
A30: B2B | B30: =CONCATENATE(D30,F30) -> 27AANCA4062G1ZN252240001264A010 | C30: =C29+1 -> 25 | D30: 27AANCA4062G1ZN | E30: M/s ADITYA BIRLA HEALTH INSURANCE CO LIMITED | F30: 252240001264A010 | G30: Regular | H30: 45776 | I30: 337.09 | J30: Maharashtra | K30: No | M30: 285.67 | N30: 0 | O30: 25.71 | P30: 25.71 | Q30: 0 | R30: Apr'25 | S30: 10/05/2025 | T30: Yes | V30: 100%
A31: B2B | B31: =CONCATENATE(D31,F31) -> 27AANCA4062G1ZN252240001264A011 | C31: =C30+1 -> 26 | D31: 27AANCA4062G1ZN | E31: M/s ADITYA BIRLA HEALTH INSURANCE CO LIMITED | F31: 252240001264A011 | G31: Regular | H31: 45776 | I31: 269.26 | J31: Maharashtra | K31: No | M31: 228.19 | N31: 0 | O31: 20.53 | P31: 20.53 | Q31: 0 | R31: Apr'25 | S31: 10/05/2025 | T31: Yes | V31: 100%
A32: B2B | B32: =CONCATENATE(D32,F32) -> 27AANCA4062G1ZN281240001894A009 | C32: =C31+1 -> 27 | D32: 27AANCA4062G1ZN | E32: M/s ADITYA BIRLA HEALTH INSURANCE CO LIMITED | F32: 281240001894A009 | G32: Regular | H32: 45770 | I32: 6907.42 | J32: Maharashtra | K32: No | M32: 5853.75 | N32: 0 | O32: 526.83 | P32: 526.83 | Q32: 0 | R32: Apr'25 | S32: 10/05/2025 | T32: Yes | V32: 100%
... A38: B2B | B38: =CONCATENATE(D38,F38) -> 27AATPE1292M1Z7MAR-2025-302 | C38: =C37+1 -> 33 | D38: 27AATPE1292M1Z7 | E38: ERAGAM SIDHANTH REDDY | F38: MAR-2025-302 | G38: Regular | H38: 45717 | I38: 413878 | J38: Maharashtra | K38: No | M38: 350744 | N38: 0 | O38: 31566.96 | P38: 31566.96 | Q38: 0 | R38: Mar'25 | S38: 16/04/2025 | T38: Yes | V38: 100%
A39: B2B | B39: =CONCATENATE(D39,F39) -> 27AIVPC4737D1Z5427 | C39: =C38+1 -> 34 | D39: 27AIVPC4737D1Z5 | E39: R. V. FURNITURE & REPAIRING | F39: 427 | G39: Regular | H39: 45757 | I39: 8142 | J39: Maharashtra | K39: No | M39: 6900 | N39: 0 | O39: 621 | P39: 621 | Q39: 0 | R39: Apr'25 | S39: 12/05/2025 | T39: Yes | V39: 100%
A40: B2B | B40: =CONCATENATE(D40,F40) -> 27AIVPC4737D1Z5428 | C40: =C39+1 -> 35 | D40: 27AIVPC4737D1Z5 | E40: R. V. FURNITURE & REPAIRING | F40: 428 | G40: Regular | H40: 45757 | I40: 16909.4 | J40: Maharashtra | K40: No | M40: 14330 | N40: 0 | O40: 1289.7 | P40: 1289.7 | Q40: 0 | R40: Apr'25 | S40: 12/05/2025 | T40: Yes | V40: 100%
A41: B2B | B41: =CONCATENATE(D41,F41) -> 27AIVPC4737D1Z5429 | C41: =C40+1 -> 36 | D41: 27AIVPC4737D1Z5 | E41: R. V. FURNITURE & REPAIRING | F41: 429 | G41: Regular | H41: 45775 | I41: 9440 | J41: Maharashtra | K41: No | M41: 8000 | N41: 0 | O41: 720 | P41: 720 | Q41: 0 | R41: Apr'25 | S41: 12/05/2025 | T41: Yes | V41: 100%
A42: B2B | B42: =CONCATENATE(D42,F42) -> 27AISPB8261G1Z0SH0038-0002074 | C42: =C41+1 -> 37 | D42: 27AISPB8261G1Z0 | E42: BHUTADA ENTERPRISES | F42: SH0038-0002074 | G42: Regular | H42: 45771 | I42: 2185 | J42: Maharashtra | K42: No | M42: 1851.68 | N42: 0 | O42: 166.66 | P42: 166.66 | Q42: 0 | R42: Apr'25 | S42: 02/05/2025 | T42: Yes | V42: 100%
A43: B2B | B43: =CONCATENATE(D43,F43) -> 27ACTFS8903M1Z6SIS/2025-26/020 | C43: =C42+1 -> 38 | D43: 27ACTFS8903M1Z6 | E43: SAAS INFOSOLUTIONS | F43: SIS/2025-26/020 | G43: Regular | H43: 45761 | I43: 31388 | J43: Maharashtra | K43: No | M43: 26600 | N43: 0 | O43: 2394 | P43: 2394 | Q43: 0 | R43: Apr'25 | S43: 10/05/2025 | T43: Yes | V43: 100% | W43: E-Invoice | X43: 070251905b201d68f115c03b1c202d6a7b8c4db57d1a24f0526f37f48df1c32a | Y43: 14/04/2025
A44: B2B | B44: =CONCATENATE(D44,F44) -> 27ACTFS8903M1Z6SIS/2025-26/033 | C44: =C43+1 -> 39 | D44: 27ACTFS8903M1Z6 | E44: SAAS INFOSOLUTIONS | F44: SIS/2025-26/033 | G44: Regular | H44: 45768 | I44: 1123360 | J44: Maharashtra | K44: No | M44: 952000 | N44: 0 | O44: 85680 | P44: 85680 | Q44: 0 | R44: Apr'25 | S44: 10/05/2025 | T44: Yes | V44: 100% | W44: E-Invoice | X44: c4c4fce9c8b7fc9f3e5a689afa2c433ab1a40f32c3e8630f82235fc83b4d6d5d | Y44: 21/04/2025
A45: B2B | B45: =CONCATENATE(D45,F45) -> 27AALCM3536H1ZAINV2526/21591 | C45: =C44+1 -> 40 | D45: 27AALCM3536H1ZA | E45: MACFOS LIMITED | F45: INV2526/21591 | G45: Regular | H45: 45763 | I45: 540 | J45: Maharashtra | K45: No | M45: 457.63 | N45: 0 | O45: 41.19 | P45: 41.19 | Q45: 0 | R45: Apr'25 | S45: 10/05/2025 | T45: Yes | V45: 100% | W45: E-Invoice | X45: 436b1be01dc1bab9343448d8968c6552d48ce30e318d182ea8c599a0069e0135 | Y45: 16/04/2025
A46: B2B | B46: =CONCATENATE(D46,F46) -> 27AALCM3536H1ZAINV2526/29755 | C46: =C45+1 -> 41 | D46: 27AALCM3536H1ZA | E46: MACFOS LIMITED | F46: INV2526/29755 | G46: Regular | H46: 45770 | I46: 39835 | J46: Maharashtra | K46: No | M46: 33878.09 | N46: 0 | O46: 2978.48 | P46: 2978.48 | Q46: 0 | R46: Apr'25 | S46: 10/05/2025 | T46: Yes | V46: 100% | W46: E-Invoice | X46: 2e7f75940ec763884214a99ff68f43feb891f61673ebd2cb5eb5b873bdeb18b4 | Y46: 23/04/2025
A47: B2B | B47: =CONCATENATE(D47,F47) -> 27AAWCS5258F1ZQPUN06/SC25/00014 | C47: =C46+1 -> 42 | D47: 27AAWCS5258F1ZQ | E47: SMARTWORKS COWORKING SPACES LIMITED | F47: PUN06/SC25/00014 | G47: Regular | H47: 45748 | I47: 3274717.3 | J47: Maharashtra | K47: No | M47: 2775184.2 | N47: 0 | O47: 249766.57 | P47: 249766.57 | Q47: 0 | R47: Apr'25 | S47: 09/05/2025 | T47: Yes | V47: 100%
A48: B2B | B48: =CONCATENATE(D48,F48) -> 27AAWCS5258F1ZQPUN06/SC25/00079 | C48: =C47+1 -> 43 | D48: 27AAWCS5258F1ZQ | E48: SMARTWORKS COWORKING SPACES LIMITED | F48: PUN06/SC25/00079 | G48: Regular | H48: 45768 | I48: 3404409.7 | J48: Maharashtra | K48: No | M48: 2885093 | N48: 0 | O48: 259658.37 | P48: 259658.37 | Q48: 0 | R48: Apr'25 | S48: 09/05/2025 | T48: Yes | V48: 100%
A49: B2B | B49: =CONCATENATE(D49,F49) -> 27AALCS9822Q1ZC2526CI0000011754 | C49: =C48+1 -> 44 | D49: 27AALCS9822Q1ZC | E49: PLUXEE INDIA PRIVATE LIMITED | F49: 2526CI0000011754 | G49: Regular | H49: 45777 | I49: 467.28 | J49: Maharashtra | K49: No | M49: 396 | N49: 0 | O49: 35.64 | P49: 35.64 | Q49: 0 | R49: Apr'25 | S49: 11/05/2025 | T49: Yes | V49: 100% | W49: E-Invoice | X49: 1d98156427fb17ec972db60bf6c75831d02d5bc8fcc60c8d2be24dc791e893a2 | Y49: 30/04/2025
A50: B2B | B50: =CONCATENATE(D50,F50) -> 07AAACJ0054A1ZDDP502584 | C50: =C49+1 -> 45 | D50: 07AAACJ0054A1ZD | E50: JETWAYS TRAVELS PVT.LTD. | F50: DP502584 | G50: Regular | H50: 45769 | I50: 6255 | J50: Maharashtra | K50: No | M50: 100 | N50: 18 | O50: 0 | P50: 0 | Q50: 0 | R50: Apr'25 | S50: 11/05/2025 | T50: Yes | V50: 100%
A51: B2B | B51: =CONCATENATE(D51,F51) -> 07AAACJ0054A1ZDDP502585 | C51: =C50+1 -> 46 | D51: 07AAACJ0054A1ZD | E51: JETWAYS TRAVELS PVT.LTD. | F51: DP502585 | G51: Regular | H51: 45769 | I51: 6255 | J51: Maharashtra | K51: No | M51: 100 | N51: 18 | O51: 0 | P51: 0 | Q51: 0 | R51: Apr'25 | S51: 11/05/2025 | T51: Yes | V51: 100%
A52: B2B | B52: =CONCATENATE(D52,F52) -> 07AAACJ0054A1ZDDP502586 | C52: =C51+1 -> 47 | D52: 07AAACJ0054A1ZD | E52: JETWAYS TRAVELS PVT.LTD. | F52: DP502586 | G52: Regular | H52: 45769 | I52: 6255 | J52: Maharashtra | K52: No | M52: 100 | N52: 18 | O52: 0 | P52: 0 | Q52: 0 | R52: Apr'25 | S52: 11/05/2025 | T52: Yes | V52: 100%
A53: B2B | B53: =CONCATENATE(D53,F53) -> 07AAACJ0054A1ZDDP502587 | C53: =C52+1 -> 48 | D53: 07AAACJ0054A1ZD | E53: JETWAYS TRAVELS PVT.LTD. | F53: DP502587 | G53: Regular | H53: 45769 | I53: 6255 | J53: Maharashtra | K53: No | M53: 100 | N53: 18 | O53: 0 | P53: 0 | Q53: 0 | R53: Apr'25 | S53: 11/05/2025 | T53: Yes | V53: 100%
A54: B2B | B54: =CONCATENATE(D54,F54) -> 07AAACJ0054A1ZDDP503081 | C54: =C53+1 -> 49 | D54: 07AAACJ0054A1ZD | E54: JETWAYS TRAVELS PVT.LTD. | F54: DP503081 | G54: Regular | H54: 45773 | I54: 8559 | J54: Maharashtra | K54: No | M54: 100 | N54: 18 | O54: 0 | P54: 0 | Q54: 0 | R54: Apr'25 | S54: 11/05/2025 | T54: Yes | V54: 100%
A55: B2B | B55: =CONCATENATE(D55,F55) -> 07AAACJ0054A1ZDDP503088 | C55: =C54+1 -> 50 | D55: 07AAACJ0054A1ZD | E55: JETWAYS TRAVELS PVT.LTD. | F55: DP503088 | G55: Regular | H55: 45773 | I55: 10329 | J55: Maharashtra | K55: No | M55: 100 | N55: 18 | O55: 0 | P55: 0 | Q55: 0 | R55: Apr'25 | S55: 11/05/2025 | T55: Yes | V55: 100%
A56: B2B | B56: =CONCATENATE(D56,F56) -> 07AAACJ0054A1ZDHP500142 | C56: =C55+1 -> 51 | D56: 07AAACJ0054A1ZD | E56: JETWAYS TRAVELS PVT.LTD. | F56: HP500142 | G56: Regular | H56: 45777 | I56: 46728 | J56: Maharashtra | K56: No | M56: 39600 | N56: 7128 | O56: 0 | P56: 0 | Q56: 0 | R56: Apr'25 | S56: 11/05/2025 | T56: Yes | V56: 100%
A57: B2B | B57: =CONCATENATE(D57,F57) -> 07AAACJ0054A1ZDIP500174 | C57: =C56+1 -> 52 | D57: 07AAACJ0054A1ZD | E57: JETWAYS TRAVELS PVT.LTD. | F57: IP500174 | G57: Regular | H57: 45758 | I57: 17269 | J57: Maharashtra | K57: No | M57: 700 | N57: 126 | O57: 0 | P57: 0 | Q57: 0 | R57: Apr'25 | S57: 11/05/2025 | T57: Yes | V57: 100%
A58: B2B | B58: =CONCATENATE(D58,F58) -> 07AAACJ0054A1ZDIP500322 | C58: =C57+1 -> 53 | D58: 07AAACJ0054A1ZD | E58: JETWAYS TRAVELS PVT.LTD. | F58: IP500322 | G58: Regular | H58: 45766 | I58: 135928 | J58: Maharashtra | K58: No | M58: 700 | N58: 126 | O58: 0 | P58: 0 | Q58: 0 | R58: Apr'25 | S58: 11/05/2025 | T58: Yes | V58: 100%
A59: B2B | B59: =CONCATENATE(D59,F59) -> 07AAACJ0054A1ZDIP500351 | C59: =C58+1 -> 54 | D59: 07AAACJ0054A1ZD | E59: JETWAYS TRAVELS PVT.LTD. | F59: IP500351 | G59: Regular | H59: 45769 | I59: 84855 | J59: Maharashtra | K59: No | M59: 700 | N59: 126 | O59: 0 | P59: 0 | Q59: 0 | R59: Apr'25 | S59: 11/05/2025 | T59: Yes | V59: 100%
A60: B2B | B60: =CONCATENATE(D60,F60) -> 07AAACJ0054A1ZDIP500352 | C60: =C59+1 -> 55 | D60: 07AAACJ0054A1ZD | E60: JETWAYS TRAVELS PVT.LTD. | F60: IP500352 | G60: Regular | H60: 45769 | I60: 84855 | J60: Maharashtra | K60: No | M60: 700 | N60: 126 | O60: 0 | P60: 0 | Q60: 0 | R60: Apr'25 | S60: 11/05/2025 | T60: Yes | V60: 100%
A61: B2B | B61: =CONCATENATE(D61,F61) -> 07AAACJ0054A1ZDIP500353 | C61: =C60+1 -> 56 | D61: 07AAACJ0054A1ZD | E61: JETWAYS TRAVELS PVT.LTD. | F61: IP500353 | G61: Regular | H61: 45769 | I61: 84855 | J61: Maharashtra | K61: No | M61: 700 | N61: 126 | O61: 0 | P61: 0 | Q61: 0 | R61: Apr'25 | S61: 11/05/2025 | T61: Yes | V61: 100%
... A64: B2B | B64: =CONCATENATE(D64,F64) -> 27DLQPP2518L1ZGNE/2526/013 | C64: =C63+1 -> 59 | D64: 27DLQPP2518L1ZG | E64: NIYATI ENTERPRISES | F64: NE/2526/013 | G64: Regular | H64: 45770 | I64: 3127 | J64: Maharashtra | K64: No | M64: 2650 | N64: 0 | O64: 238.5 | P64: 238.5 | Q64: 0 | R64: Apr'25 | S64: 09/05/2025 | T64: Yes | V64: 100%
A65: B2B | B65: =CONCATENATE(D65,F65) -> 36AAJCA3639B1ZXAE-INV-2526-0129 | C65: =C64+1 -> 60 | D65: 36AAJCA3639B1ZX | E65: M/S ARGUS EMBEDDED SYSTEMS PRIVATE LIMITED | F65: AE-INV-2526-0129 | G65: Regular | H65: 45777 | I65: 5947 | J65: Maharashtra | K65: No | M65: 5040 | N65: 907.2 | O65: 0 | P65: 0 | Q65: 0 | R65: Apr'25 | S65: 08/05/2025 | T65: Yes | V65: 100% | W65: E-Invoice | X65: af1026cecd3b40212a6f7145825c67c5c5f282989997e2d60c1ab4118233a5ea | Y65: 30/04/2025
A66: B2B | B66: =CONCATENATE(D66,F66) -> 36AAJCA3639B1ZXAE-INV-2526-0130 | C66: =C65+1 -> 61 | D66: 36AAJCA3639B1ZX | E66: M/S ARGUS EMBEDDED SYSTEMS PRIVATE LIMITED | F66: AE-INV-2526-0130 | G66: Regular | H66: 45777 | I66: 65419 | J66: Maharashtra | K66: No | M66: 55440 | N66: 9979.2 | O66: 0 | P66: 0 | Q66: 0 | R66: Apr'25 | S66: 08/05/2025 | T66: Yes | V66: 100% | W66: E-Invoice | X66: 84b073e68303e41f68dd9fac34515edad42528457a8a0d7a17e7068a272f8a52 | Y66: 30/04/2025
A67: B2B | B67: =CONCATENATE(D67,F67) -> 27AAECG2483J1ZEGNR/S/25-26/183 | C67: =C66+1 -> 62 | D67: 27AAECG2483J1ZE | E67: GNR SOLUTION PRIVATE LIMITED | F67: GNR/S/25-26/183 | G67: Regular | H67: 45756 | I67: 14160 | J67: Maharashtra | K67: No | M67: 12000 | N67: 0 | O67: 1080 | P67: 1080 | Q67: 0 | R67: Apr'25 | S67: 10/05/2025 | T67: Yes | V67: 100% | W67: E-Invoice | X67: 81e5e02ff55544d5c3bb77d0e82fafba041a1a29b76adb3a3f9fef94c095e129 | Y67: 09/04/2025
A68: B2B | B68: =CONCATENATE(D68,F68) -> 27AAECG2483J1ZEGNR/S/25-26/235 | C68: =C67+1 -> 63 | D68: 27AAECG2483J1ZE | E68: GNR SOLUTION PRIVATE LIMITED | F68: GNR/S/25-26/235 | G68: Regular | H68: 45758 | I68: 5416 | J68: Maharashtra | K68: No | M68: 4590 | N68: 0 | O68: 413.1 | P68: 413.1 | Q68: 0 | R68: Apr'25 | S68: 10/05/2025 | T68: Yes | V68: 100% | W68: E-Invoice | X68: 26c5e86f9dbc14ef5d67f1ab4f8daa7295ed1c81199ca741efeef657ef4ccc2e | Y68: 11/04/2025
A69: B2B | B69: =CONCATENATE(D69,F69) -> 27AAECG2483J1ZEGNR/S/25-26/309 | C69: =C68+1 -> 64 | D69: 27AAECG2483J1ZE | E69: GNR SOLUTION PRIVATE LIMITED | F69: GNR/S/25-26/309 | G69: Regular | H69: 45762 | I69: 750 | J69: Maharashtra | K69: No | M69: 636 | N69: 0 | O69: 57.24 | P69: 57.24 | Q69: 0 | R69: Apr'25 | S69: 10/05/2025 | T69: Yes | V69: 100% | W69: E-Invoice | X69: 7085380766c82a0edbd233060fb78b5da5cb558de5648496c1a586db6379e1db | Y69: 15/04/2025
A70: B2B | B70: =CONCATENATE(D70,F70) -> 27AAECG2483J1ZEGNR/S/25-26/362 | C70: =C69+1 -> 65 | D70: 27AAECG2483J1ZE | E70: GNR SOLUTION PRIVATE LIMITED | F70: GNR/S/25-26/362 | G70: Regular | H70: 45764 | I70: 873 | J70: Maharashtra | K70: No | M70: 740 | N70: 0 | O70: 66.6 | P70: 66.6 | Q70: 0 | R70: Apr'25 | S70: 10/05/2025 | T70: Yes | V70: 100% | W70: E-Invoice | X70: c8d86f5ce107ff273500075c53b92562d8f113e592e2394dd8ec0eeaaf5f588f | Y70: 17/04/2025
A71: B2B | B71: =CONCATENATE(D71,F71) -> 27AATPE1292M1Z7APR-2025-301 | C71: =C70+1 -> 66 | D71: 27AATPE1292M1Z7 | E71: ERAGAM SIDHANTH REDDY | F71: APR-2025-301 | G71: Regular | H71: 45748 | I71: 393497 | J71: Maharashtra | K71: No | M71: 333472 | N71: 0 | O71: 30012.48 | P71: 30012.48 | Q71: 0 | R71: Apr'25 | S71: 06/05/2025 | T71: Yes | V71: 100%
A72: B2B | B72: =CONCATENATE(D72,F72) -> 27AATPE1292M1Z7APR-2025-302 | C72: =C71+1 -> 67 | D72: 27AATPE1292M1Z7 | E72: ERAGAM SIDHANTH REDDY | F72: APR-2025-302 | G72: Regular | H72: 45748 | I72: 413878 | J72: Maharashtra | K72: No | M72: 350744 | N72: 0 | O72: 31566.96 | P72: 31566.96 | Q72: 0 | R72: Apr'25 | S72: 06/05/2025 | T72: Yes | V72: 100%
A73: B2B | B73: =CONCATENATE(D73,F73) -> 27AAOFA7053K1Z219198 | C73: =C72+1 -> 68 | D73: 27AAOFA7053K1Z2 | E73: Ahuja Valecha & Associates LLP | F73: 19198 | G73: Regular | H73: 45754 | I73: 53199 | J73: Maharashtra | K73: No | M73: 45084 | N73: 0 | O73: 4057.56 | P73: 4057.56 | Q73: 0 | R73: Apr'25 | S73: 10/05/2025 | T73: Yes | V73: 100% | W73: E-Invoice | X73: 2d7debf4d06f5d8a8dd4dec879d1b685191d9ca38cbbc007952c4e832bf14928 | Y73: 07/04/2025
A74: B2B | B74: =CONCATENATE(D74,F74) -> 27AAOFA7053K1Z219332 | C74: =C73+1 -> 69 | D74: 27AAOFA7053K1Z2 | E74: Ahuja Valecha & Associates LLP | F74: 19332 | G74: Regular | H74: 45772 | I74: 23600 | J74: Maharashtra | K74: No | M74: 20000 | N74: 0 | O74: 1800 | P74: 1800 | Q74: 0 | R74: Apr'25 | S74: 10/05/2025 | T74: Yes | V74: 100% | W74: E-Invoice | X74: 67a3b5c4724157f97123fce504858c734d1315964fbe6ccde4ce260c909308db | Y74: 25/04/2025
A75: B2B | B75: =CONCATENATE(D75,F75) -> 27AAIFR9573K1ZEHCA29591 | C75: =C74+1 -> 70 | D75: 27AAIFR9573K1ZE | E75: RAJIV ELECTRONICS | F75: HCA29591 | G75: Regular | H75: 45752 | I75: 142 | J75: Maharashtra | K75: No | M75: 120 | N75: 0 | O75: 10.8 | P75: 10.8 | Q75: 0 | R75: Apr'25 | S75: 10/05/2025 | T75: Yes | V75: 100%
A76: B2B | B76: =CONCATENATE(D76,F76) -> 27AAIFR9573K1ZEHCA30841 | C76: =C75+1 -> 71 | D76: 27AAIFR9573K1ZE | E76: RAJIV ELECTRONICS | F76: HCA30841 | G76: Regular | H76: 45772 | I76: 248 | J76: Maharashtra | K76: No | M76: 210 | N76: 0 | O76: 18.9 | P76: 18.9 | Q76: 0 | R76: Apr'25 | S76: 10/05/2025 | T76: Yes | V76: 100%
A77: B2B | B77: =CONCATENATE(D77,F77) -> 27AAIFR9573K1ZEHCA31030 | C77: =C76+1 -> 72 | D77: 27AAIFR9573K1ZE | E77: RAJIV ELECTRONICS | F77: HCA31030 | G77: Regular | H77: 45772 | I77: 65 | J77: Maharashtra | K77: No | M77: 55 | N77: 0 | O77: 4.95 | P77: 4.95 | Q77: 0 | R77: Apr'25 | S77: 10/05/2025 | T77: Yes | V77: 100%
A78: B2B | B78: =CONCATENATE(D78,F78) -> 27AAFCV0171M1Z3VB-137/25-26 | C78: =C77+1 -> 73 | D78: 27AAFCV0171M1Z3 | E78: VEEBHA BEVERAGES PRIVATE LIMITED | F78: VB-137/25-26 | G78: Regular | H78: 45773 | I78: 3776 | J78: Maharashtra | K78: No | M78: 3200 | N78: 0 | O78: 288 | P78: 288 | Q78: 0 | R78: Apr'25 | S78: 11/05/2025 | T78: Yes | V78: 100% | W78: E-Invoice | X78: 8eef1a7866dba6542674216ab9b9938be6fbb313ef95a43c98cb52d15ef6dd3a | Y78: 26/04/2025
A79: B2B | B79: =CONCATENATE(D79,F79) -> 27AAFCV0171M1Z3VB-145/25-26 | C79: =C78+1 -> 74 | D79: 27AAFCV0171M1Z3 | E79: VEEBHA BEVERAGES PRIVATE LIMITED | F79: VB-145/25-26 | G79: Regular | H79: 45775 | I79: 5664 | J79: Maharashtra | K79: No | M79: 4800 | N79: 0 | O79: 432 | P79: 432 | Q79: 0 | R79: Apr'25 | S79: 11/05/2025 | T79: Yes | V79: 100% | W79: E-Invoice | X79: 27465b0b9b3fffc937e766509e0e7dbff02a2ea672843179d4489dd1d1319944 | Y79: 28/04/2025
A80: B2B | B80: =CONCATENATE(D80,F80) -> 27AABCF6516A1Z3BOM-C-241484 | C80: =C79+1 -> 75 | D80: 27AABCF6516A1Z3 | E80: FEDEX EXPRESS TRANSPORTATION AND SUPPLY CHAIN SERVICES (I) PRIVATE LIMITED | F80: BOM-C-241484 | G80: Regular | H80: 45748 | I80: 5035 | J80: Maharashtra | K80: No | M80: 800 | N80: 0 | O80: 72 | P80: 72 | Q80: 0 | R80: Apr'25 | S80: 10/05/2025 | T80: Yes | V80: 100% | W80: E-Invoice | X80: 551c5752c417a6fd0676d2de6f77dcd576bcead2f2f6afbdefcbf57e0f85861b | Y80: 01/04/2025
A81: B2B | B81: =CONCATENATE(D81,F81) -> 27AABCF6516A1Z3BOM-C-242810 | C81: =C80+1 -> 76 | D81: 27AABCF6516A1Z3 | E81: FEDEX EXPRESS TRANSPORTATION AND SUPPLY CHAIN SERVICES (I) PRIVATE LIMITED | F81: BOM-C-242810 | G81: Regular | H81: 45755 | I81: 120604.3 | J81: Maharashtra | K81: No | M81: 6452.8 | N81: 0 | O81: 580.75 | P81: 580.75 | Q81: 0 | R81: Apr'25 | S81: 10/05/2025 | T81: Yes | V81: 100% | W81: E-Invoice | X81: 0408e9d6133cbdad34b921e9bfbd88d212fa54849e534805a6adf9548322d355 | Y81: 08/04/2025
A82: B2B | B82: =CONCATENATE(D82,F82) -> 27AACCN6194P1ZP272612BP04AGL540 | C82: =C81+1 -> 77 | D82: 27AACCN6194P1ZP | E82: AIR INDIA LIMITED | F82: 272612BP04AGL540 | G82: Regular | H82: 45773 | I82: 8441 | J82: Maharashtra | K82: No | M82: 7316 | N82: 0 | O82: 183 | P82: 183 | Q82: 0 | R82: Apr'25 | S82: 11/05/2025 | T82: Yes | V82: 100%
A83: B2B | B83: =CONCATENATE(D83,F83) -> 27AANCP4234F1ZCCASHMEMO-179 | C83: =C82+1 -> 78 | D83: 27AANCP4234F1ZC | E83: PRIME SWITCHGEAR PRIVATE LIMITED | F83: CASHMEMO-179 | G83: Regular | H83: 45755 | I83: 631 | J83: Maharashtra | K83: No | M83: 535 | N83: 0 | O83: 48.15 | P83: 48.15 | Q83: 0 | R83: Apr'25 | S83: 09/05/2025 | T83: Yes | V83: 100% | W83: E-Invoice | X83: 987a3f232d8c470cd26090b73316a279986ce28ec648718779563699d2ab4525 | Y83: 09/04/2025
A84: B2B | B84: =CONCATENATE(D84,F84) -> 27AAMFS2232C1ZGSK/1056/2526 | C84: =C83+1 -> 79 | D84: 27AAMFS2232C1ZG | E84: S. K. INTERNATIONAL | F84: SK/1056/2526 | G84: Regular | H84: 45755 | I84: 17700 | J84: Maharashtra | K84: No | M84: 15000 | N84: 0 | O84: 1350 | P84: 1350 | Q84: 0 | R84: Apr'25 | S84: 07/05/2025 | T84: Yes | V84: 100% | W84: E-Invoice | X84: 23c77b251378cf45f923cc2e0c6044543a4586a0d2e78eb70f190e36a962c27b | Y84: 08/04/2025
A85: B2B | B85: =CONCATENATE(D85,F85) -> 27AAMFS2232C1ZGSK/1090/2526 | C85: =C84+1 -> 80 | D85: 27AAMFS2232C1ZG | E85: S. K. INTERNATIONAL | F85: SK/1090/2526 | G85: Regular | H85: 45762 | I85: 8850 | J85: Maharashtra | K85: No | M85: 7500 | N85: 0 | O85: 675 | P85: 675 | Q85: 0 | R85: Apr'25 | S85: 07/05/2025 | T85: Yes | V85: 100% | W85: E-Invoice | X85: 6adf8e9e0d310de44944cae627b68287c7c15086592553c4b22c1fa3d9a16ac8 | Y85: 15/04/2025
A86: B2B | B86: =CONCATENATE(D86,F86) -> 27AAACA4269Q1Z6B1MH2526/000021 | C86: =C85+1 -> 81 | D86: 27AAACA4269Q1Z6 | E86: CAPSAVE FINANCE PRIVATE LIMITED | F86: B1MH2526/000021 | G86: Regular | H86: 45748 | I86: 6136.43 | J86: Maharashtra | K86: No | M86: 4838.07 | N86: 0 | O86: 649.18 | P86: 649.18 | Q86: 0 | R86: Apr'25 | S86: 07/05/2025 | T86: Yes | V86: 100%
A87: B2B | B87: =CONCATENATE(D87,F87) -> 27AAACA4269Q1Z6B1MH2526/000069 | C87: =C86+1 -> 82 | D87: 27AAACA4269Q1Z6 | E87: CAPSAVE FINANCE PRIVATE LIMITED | F87: B1MH2526/000069 | G87: Regular | H87: 45748 | I87: 11595.86 | J87: Maharashtra | K87: No | M87: 9827 | N87: 0 | O87: 884.43 | P87: 884.43 | Q87: 0 | R87: Apr'25 | S87: 07/05/2025 | T87: Yes | V87: 100%
A88: B2B | B88: =CONCATENATE(D88,F88) -> 27AAACA4269Q1Z6B1MH2526/000070 | C88: =C87+1 -> 83 | D88: 27AAACA4269Q1Z6 | E88: CAPSAVE FINANCE PRIVATE LIMITED | F88: B1MH2526/000070 | G88: Regular | H88: 45748 | I88: 18659.73 | J88: Maharashtra | K88: No | M88: 15813.33 | N88: 0 | O88: 1423.2 | P88: 1423.2 | Q88: 0 | R88: Apr'25 | S88: 07/05/2025 | T88: Yes | V88: 100%
A89: B2B | B89: =CONCATENATE(D89,F89) -> 27AAACA4269Q1Z6B1MH2526/000071 | C89: =C88+1 -> 84 | D89: 27AAACA4269Q1Z6 | E89: CAPSAVE FINANCE PRIVATE LIMITED | F89: B1MH2526/000071 | G89: Regular | H89: 45748 | I89: 19132.67 | J89: Maharashtra | K89: No | M89: 16214.67 | N89: 0 | O89: 1459 | P89: 1459 | Q89: 0 | R89: Apr'25 | S89: 07/05/2025 | T89: Yes | V89: 100%
A90: B2B | B90: =CONCATENATE(D90,F90) -> 27AAACA4269Q1Z6B1MH2526/000072 | C90: =C89+1 -> 85 | D90: 27AAACA4269Q1Z6 | E90: CAPSAVE FINANCE PRIVATE LIMITED | F90: B1MH2526/000072 | G90: Regular | H90: 45748 | I90: 383426.65 | J90: Maharashtra | K90: No | M90: 314677.65 | N90: 0 | O90: 34374.5 | P90: 34374.5 | Q90: 0 | R90: Apr'25 | S90: 07/05/2025 | T90: Yes | V90: 100%
A91: B2B | B91: =CONCATENATE(D91,F91) -> 27AAACA4269Q1Z6B1MH2526/000073 | C91: =C90+1 -> 86 | D91: 27AAACA4269Q1Z6 | E91: CAPSAVE FINANCE PRIVATE LIMITED | F91: B1MH2526/000073 | G91: Regular | H91: 45748 | I91: 48703.71 | J91: Maharashtra | K91: No | M91: 41274.33 | N91: 0 | O91: 3714.69 | P91: 3714.69 | Q91: 0 | R91: Apr'25 | S91: 07/05/2025 | T91: Yes | V91: 100%
A92: B2B | B92: =CONCATENATE(D92,F92) -> 27AAACA4269Q1Z6B1MH2526/000074 | C92: =C91+1 -> 87 | D92: 27AAACA4269Q1Z6 | E92: CAPSAVE FINANCE PRIVATE LIMITED | F92: B1MH2526/000074 | G92: Regular | H92: 45748 | I92: 95303.88 | J92: Maharashtra | K92: No | M92: 80766 | N92: 0 | O92: 7268.94 | P92: 7268.94 | Q92: 0 | R92: Apr'25 | S92: 07/05/2025 | T92: Yes | V92: 100%
A93: B2B | B93: =CONCATENATE(D93,F93) -> 27AAACA4269Q1Z6B1MH2526/000106 | C93: =C92+1 -> 88 | D93: 27AAACA4269Q1Z6 | E93: CAPSAVE FINANCE PRIVATE LIMITED | F93: B1MH2526/000106 | G93: Regular | H93: 45748 | I93: 834440.41 | J93: Maharashtra | K93: No | M93: 707152.89 | N93: 0 | O93: 63643.76 | P93: 63643.76 | Q93: 0 | R93: Apr'25 | S93: 07/05/2025 | T93: Yes | V93: 100%
A94: B2B | B94: =CONCATENATE(D94,F94) -> 27AAACA4269Q1Z6B1MH2526/000149 | C94: =C93+1 -> 89 | D94: 27AAACA4269Q1Z6 | E94: CAPSAVE FINANCE PRIVATE LIMITED | F94: B1MH2526/000149 | G94: Regular | H94: 45748 | I94: 17840.81 | J94: Maharashtra | K94: No | M94: 15119.33 | N94: 0 | O94: 1360.74 | P94: 1360.74 | Q94: 0 | R94: Apr'25 | S94: 07/05/2025 | T94: Yes | V94: 100%
A95: B2B | B95: =CONCATENATE(D95,F95) -> 27AAACA4269Q1Z6B1MH2526/000150 | C95: =C94+1 -> 90 | D95: 27AAACA4269Q1Z6 | E95: CAPSAVE FINANCE PRIVATE LIMITED | F95: B1MH2526/000150 | G95: Regular | H95: 45748 | I95: 30113.08 | J95: Maharashtra | K95: No | M95: 25519.56 | N95: 0 | O95: 2296.76 | P95: 2296.76 | Q95: 0 | R95: Apr'25 | S95: 07/05/2025 | T95: Yes | V95: 100%
A96: B2B | B96: =CONCATENATE(D96,F96) -> 27AATPE1295N1Z2APR-2025-303 | C96: =C95+1 -> 91 | D96: 27AATPE1295N1Z2 | E96: ERAGAM SANJEETH REDDY | F96: APR-2025-303 | G96: Regular | H96: 45748 | I96: 413878 | J96: Maharashtra | K96: No | M96: 350744 | N96: 0 | O96: 31566.96 | P96: 31566.96 | Q96: 0 | R96: Apr'25 | S96: 06/05/2025 | T96: Yes | V96: 100%
A97: B2B | B97: =CONCATENATE(D97,F97) -> 27AATPE1295N1Z2APR-2025-304 | C97: =C96+1 -> 92 | D97: 27AATPE1295N1Z2 | E97: ERAGAM SANJEETH REDDY | F97: APR-2025-304 | G97: Regular | H97: 45748 | I97: 393497 | J97: Maharashtra | K97: No | M97: 333472 | N97: 0 | O97: 30012.48 | P97: 30012.48 | Q97: 0 | R97: Apr'25 | S97: 06/05/2025 | T97: Yes | V97: 100%
... A102: B2B | B102: =CONCATENATE(D102,F102) -> 07AAJCA9880A1ZLAIN2526000288128 | C102: =C101+1 -> 97 | D102: 07AAJCA9880A1ZL | E102: AMAZON WEB SERVICES INDIA PRIVATE LIMITED | F102: AIN2526000288128 | G102: Regular | H102: 45749 | I102: 17513.44 | J102: Maharashtra | K102: No | M102: 14841.9 | N102: 2671.54 | O102: 0 | P102: 0 | Q102: 0 | R102: Apr'25 | S102: 10/05/2025 | T102: Yes | V102: 100%
A103: B2B | B103: =CONCATENATE(D103,F103) -> 27AABCK3418J1ZKPP/2526/2/27 | C103: =C102+1 -> 98 | D103: 27AABCK3418J1ZK | E103: KANJI FOREX PRIVATE LIMITED | F103: PP/2526/2/27 | G103: Regular | H103: 45756 | I103: 44495 | J103: Maharashtra | K103: No | M103: 445.75 | N103: 0 | O103: 40.12 | P103: 40.12 | Q103: 0 | R103: Apr'25 | S103: 07/05/2025 | T103: Yes | V103: 100% | W103: E-Invoice | X103: f4a9e7a237b7a746be647c4aba018a09ceea5ee6d31db0fd2be64bc9e14ae7e7 | Y103: 09/04/2025
A104: B2B | B104: =CONCATENATE(D104,F104) -> 27AABCK3418J1ZKPP/2526/2/28 | C104: =C103+1 -> 99 | D104: 27AABCK3418J1ZK | E104: KANJI FOREX PRIVATE LIMITED | F104: PP/2526/2/28 | G104: Regular | H104: 45756 | I104: 27385 | J104: Maharashtra | K104: No | M104: 274.34 | N104: 0 | O104: 24.69 | P104: 24.69 | Q104: 0 | R104: Apr'25 | S104: 07/05/2025 | T104: Yes | V104: 100% | W104: E-Invoice | X104: 0b0f7a9394e548df6b905ea644b0e4fcfebe9fb1c6f7cb73c270f185e14690e4 | Y104: 09/04/2025
A105: B2B | B105: =CONCATENATE(D105,F105) -> 27AABCK3418J1ZKPP/2526/2/53 | C105: =C104+1 -> 100 | D105: 27AABCK3418J1ZK | E105: KANJI FOREX PRIVATE LIMITED | F105: PP/2526/2/53 | G105: Regular | H105: 45772 | I105: 36589 | J105: Maharashtra | K105: No | M105: 366.55 | N105: 0 | O105: 32.99 | P105: 32.99 | Q105: 0 | R105: Apr'25 | S105: 07/05/2025 | T105: Yes | V105: 100% | W105: E-Invoice | X105: 50ebf1ecb633bf1a4db3f024238dec3da8f4310d471d8e25d7e83f421edb2832 | Y105: 25/04/2025
A106: B2B | B106: =CONCATENATE(D106,F106) -> 27AABCK3418J1ZKSP/2526/2/145 | C106: =C105+1 -> 101 | D106: 27AABCK3418J1ZK | E106: KANJI FOREX PRIVATE LIMITED | F106: SP/2526/2/145 | G106: Regular | H106: 45763 | I106: 122500 | J106: Maharashtra | K106: No | M106: 1111.5 | N106: 0 | O106: 100.04 | P106: 100.04 | Q106: 0 | R106: Apr'25 | S106: 07/05/2025 | T106: Yes | V106: 100% | W106: E-Invoice | X106: d2d78be51ad1fb201b379fbfebffd692e7e5071a9607345fac20e26358ee775b | Y106: 16/04/2025
A107: B2B | B107: =CONCATENATE(D107,F107) -> 27AABCK3418J1ZKSP/2526/2/159 | C107: =C106+1 -> 102 | D107: 27AABCK3418J1ZK | E107: KANJI FOREX PRIVATE LIMITED | F107: SP/2526/2/159 | G107: Regular | H107: 45763 | I107: 32959 | J107: Maharashtra | K107: No | M107: 329 | N107: 0 | O107: 29.61 | P107: 29.61 | Q107: 0 | R107: Apr'25 | S107: 07/05/2025 | T107: Yes | V107: 100% | W107: E-Invoice | X107: 18ed0403ac1ab6a45a8bda66cbdfafefb5e6eb7fd26f5f0e36e2e25ba431c941 | Y107: 16/04/2025
A108: B2B | B108: =CONCATENATE(D108,F108) -> 27AABCK3418J1ZKSP/2526/2/262 | C108: =C107+1 -> 103 | D108: 27AABCK3418J1ZK | E108: KANJI FOREX PRIVATE LIMITED | F108: SP/2526/2/262 | G108: Regular | H108: 45771 | I108: 108683 | J108: Maharashtra | K108: No | M108: 1042.48 | N108: 0 | O108: 93.82 | P108: 93.82 | Q108: 0 | R108: Apr'25 | S108: 07/05/2025 | T108: Yes | V108: 100% | W108: E-Invoice | X108: 7ebe08a5eddc06cce64a264e8fb57ff0f47400ce2f571a117e59247828ad72f8 | Y108: 24/04/2025
A109: B2B | B109: =CONCATENATE(D109,F109) -> 36AAKCM6764E1Z6HYD8-27014 | C109: =C108+1 -> 104 | D109: 36AAKCM6764E1Z6 | E109: MFS WHOLESALE PRIVATE LIMITED | F109: HYD8-27014 | G109: Regular | H109: 45727 | I109: 250.99 | J109: Maharashtra | K109: No | M109: 212.71 | N109: 38.28 | O109: 0 | P109: 0 | Q109: 0 | R109: Mar'25 | S109: 12/04/2025 | T109: Yes | V109: 100% | W109: E-Invoice | X109: 1cfb20a2d035ef938be39a3fe0338b667da928feddd4d8a79ec7c11dfd0fa76c | Y109: 11/03/2025
A110: B2B | B110: =CONCATENATE(D110,F110) -> 27AAACA4136A1ZDIS/0000054 | C110: =C109+1 -> 105 | D110: 27AAACA4136A1ZD | E110: AMON-RA TRAVELS PVT. LTD. | F110: IS/0000054 | G110: Regular | H110: 45763 | I110: 1180 | J110: Maharashtra | K110: No | M110: 1000 | N110: 0 | O110: 90 | P110: 90 | Q110: 0 | R110: Apr'25 | S110: 06/05/2025 | T110: Yes | V110: 100%
A111: B2B | B111: =CONCATENATE(D111,F111) -> 27AAACA4136A1ZDIS/0000055 | C111: =C110+1 -> 106 | D111: 27AAACA4136A1ZD | E111: AMON-RA TRAVELS PVT. LTD. | F111: IS/0000055 | G111: Regular | H111: 45763 | I111: 1180 | J111: Maharashtra | K111: No | M111: 1000 | N111: 0 | O111: 90 | P111: 90 | Q111: 0 | R111: Apr'25 | S111: 06/05/2025 | T111: Yes | V111: 100%
A112: B2B | B112: =CONCATENATE(D112,F112) -> 27AAACA4136A1ZDIS/0000066 | C112: =C111+1 -> 107 | D112: 27AAACA4136A1ZD | E112: AMON-RA TRAVELS PVT. LTD. | F112: IS/0000066 | G112: Regular | H112: 45775 | I112: 1180 | J112: Maharashtra | K112: No | M112: 1000 | N112: 0 | O112: 90 | P112: 90 | Q112: 0 | R112: Apr'25 | S112: 06/05/2025 | T112: Yes | V112: 100%
A113: B2B | B113: =CONCATENATE(D113,F113) -> 36AAFCK5835K1Z6K06613-0007 | C113: =C112+1 -> 108 | D113: 36AAFCK5835K1Z6 | E113: KEKA TECHNOLOGIES | F113: K06613-0007 | G113: Regular | H113: 45751 | I113: 272421 | J113: Maharashtra | K113: No | M113: 230865.3 | N113: 41555.75 | O113: 0 | P113: 0 | Q113: 0 | R113: Apr'25 | S113: 10/05/2025 | T113: Yes | V113: 100% | W113: E-Invoice | X113: df1136e9eaaa8747c399379dfc27ed46ec845b4ba2c5b70e8fc101ff2dc7714a | Y113: 04/04/2025
A114: B2B | B114: =CONCATENATE(D114,F114) -> 07BNPPR1197A1ZTIN-265 | C114: =C113+1 -> 109 | D114: 07BNPPR1197A1ZT | E114: R and D Control Systems | F114: IN-265 | G114: Regular | H114: 45763 | I114: 1049.04 | J114: Maharashtra | K114: No | M114: 889.02 | N114: 160.02 | O114: 0 | P114: 0 | Q114: 0 | R114: Apr'25 | S114: 11/05/2025 | T114: Yes | V114: 100%
A115: B2B | B115: =CONCATENATE(D115,F115) -> 27AAACH1458C1ZZ2171182208 | C115: =C114+1 -> 110 | D115: 27AAACH1458C1ZZ | E115: TATA TELESERVICES MAHARASHTRA LIMITED | F115: 2171182208 | G115: Regular | H115: 45750 | I115: 18960.24 | J115: Maharashtra | K115: No | M115: 16068 | N115: 0 | O115: 1446.12 | P115: 1446.12 | Q115: 0 | R115: Apr'25 | S115: 11/05/2025 | T115: Yes | V115: 100%
...

Sheet ITC summery
A1: Softdel System Limited Refund Working
A2: ='PR Conso (Oct 25-dec 2025)'!A2 -> Purchase Register
A3: ='PR Conso (Oct 25-dec 2025)'!A3 -> Period: October-25 to December-25
A5: Annual Purchase in GSTR-3B Extract
A6: GSTR 3B remarks | B6: Major Remarks | C6: Sum of Taxable Value (₹) | D6: Sum of Integrated Tax(₹) | E6: Sum of Central Tax(₹) | F6: Sum of State/UT Tax(₹) | G6: Sum of Total Tax
A7: All other ITC | B7: Matched with 2B | C7: 61820272 | D7: 1433264.5 | E7: 4772670.7 | F7: 4772670.7 | G7: 10978606
A8: IMPS | B8: IMPS | C8: 745321.13 | D8: 134158 | E8: 0 | F8: 0 | G8: 134158
A9: Ineligible u/s 17 (5) | B9: Matched with 2B | C9: 334157.46 | D9: 0 | E9: -22299.15 | F9: -22299.15 | G9: -44598.3
B10: Rule 42 Reversal | D10: -186075.98 | E10: -431689.21 | F10: -431689.21 | G10: -1049454.4
A11: Other Reversal | B11: Matched with 2B | C11: 22920392 | D11: -307737.43 | E11: -1878673.6 | F11: -1878673.6 | G11: -4065084.7
A12: RCM | B12: RCM | C12: 14500 | D12: 0 | E12: 1305 | F12: 1305 | G12: 2610
A13: Grand Total | C13: 85834642 | D13: 1073609.1 | E13: 2441313.7 | F13: 2441313.7 | G13: 5956236.5
D14: 1073610 | E14: 2441314 | F14: 2441314
D15: =D13-D14 -> -0.89669506 | E15: =E13-E14 -> -0.31744398 | F15: =F13-F14 -> -0.31744398
A17: ITC excluded for the calculation of "Net ITC for the purpose of Refund"
A18: - IMPG | B18: 0 | C18: 0 | D18: 0 | E18: =SUM(B18:D18) -> 0
A19: - Ineligible ITC u/s 17(5) | B19: =D12 -> 0 | C19: =E12 -> 1305 | D19: =F12 -> 1305 | E19: =SUM(B19:D19) -> 2610
A20: - Capital Goods | B20: 0 | C20: 0 | D20: 0 | E20: =SUM(B20:D20) -> 0
A21: Net ITC for the purpose of Refund | B21: =SUM(B18:B20) -> 0 | C21: =SUM(C18:C20) -> 1305 | D21: =SUM(D18:D20) -> 1305 | E21: =SUM(B21:D21) -> 2610
A24: Description of "Net ITC for the purpose of Refund"
A25: Particulars | B25: IGST | C25: CGST | D25: SGST | E25: Total Tax
A26: - ITC availed on Domestic transactions, Matched with 2B | B26: =D7+D9+D11 -> 1125527.1 | C26: =E7+E9+E11 -> 2871697.9 | D26: =F7+F9+F11 -> 2871697.9 | E26: =SUM(B26:D26) -> 6868922.9 | F26: Domestic ITC Availed
A27: - ITC availed on Import of Services | B27: =D8 -> 134158 | C27: =E8 -> 0 | D27: =F8 -> 0 | E27: =SUM(B27:D27) -> 134158 | F27: IMPS
A28: - ITC availed on RCM transactions | B28: =D12 -> 0 | C28: =E12 -> 1305 | D28: =F12 -> 1305 | E28: =SUM(B28:D28) -> 2610 | F28: RCM-Domestic
A29: - ITC reversed - Rule 42 Reversal | B29: =D10 -> -186075.98 | C29: =E10 -> -431689.21 | D29: =F10 -> -431689.21 | E29: =SUM(B29:D29) -> -1049454.4 | F29: Rule-42 Reversal
A30: Net ITC for the purpose of Refund | B30: =SUM(B26:B29) -> 1073609.1 | C30: =SUM(C26:C29) -> 2441313.7 | D30: =SUM(D26:D29) -> 2441313.7 | E30: =SUM(E26:E29) -> 5956236.5 | F30: Check | G30: =G13-E21-E30 -> -2610
E31: =E30+G30 -> 5953626.5
E32: =E30-E31 -> 2610

Sheet Domestic ITC Availed
A1: Softdel Private Limited
A2: ITC availed on Domestic transactions, Matched with 2B
A3: ='PR Conso (Oct 25-dec 2025)'!A3 -> Period: October-25 to December-25
A5: Month | B5: GSTIN of supplier | C5: Trade/Legal name | D5: Invoice number | E5: Invoice Date | F5: Rate(%) | G5: Invoice Value(₹) | H5: Taxable Value (₹) | I5: Integrated Tax(₹) | J5: Central Tax(₹) | K5: State/UT Tax(₹) | L5: Total Tax | M5: GSTN and invoice number | N5: HSN Code | O5: Description of service | P5: Nature of Purchase | Q5: Serial No. in GSTR-2B | R5: ITC Taken in the month of / GSTR-2B month | S5: GSTR-3B month | T5: Eligibility
A6: 45931 | B6: 27AASCS3903K1ZV | C6: SEMSYS PRIVATE LIMITED | D6: 2526350 | E6: 01/10/2025 | F6: 0.17985612 | G6: 11564 | H6: 9800 | I6: 0 | J6: 882 | K6: 882 | L6: 1764 | M6: 27AASCS3903K1ZV2526350 | N6: 998332 | O6: Professional Fees | P6: Input Service | Q6: 2596 | R6: 45931 | S6: 45931 | T6: Yes
A7: 45931 | B7: 27AASCS3903K1ZV | C7: SEMSYS PRIVATE LIMITED | D7: 2526351 | E7: 01/10/2025 | F7: 0.17985612 | G7: 9440 | H7: 8000 | I7: 0 | J7: 720 | K7: 720 | L7: 1440 | M7: 27AASCS3903K1ZV2526351 | N7: 998332 | O7: Professional Fees | P7: Input Service | Q7: 2597 | R7: 45931 | S7: 45931 | T7: Yes
A8: 45931 | B8: 27AASCS3903K1ZV | C8: SEMSYS PRIVATE LIMITED | D8: 2526352 | E8: 01/10/2025 | F8: 0.17985612 | G8: 9440 | H8: 8000 | I8: 0 | J8: 720 | K8: 720 | L8: 1440 | M8: 27AASCS3903K1ZV2526352 | N8: 998332 | O8: Professional Fees | P8: Input Service | Q8: 2598 | R8: 45931 | S8: 45931 | T8: Yes
A9: 45931 | B9: 27AASCS3903K1ZV | C9: SEMSYS PRIVATE LIMITED | D9: 2526353 | E9: 01/10/2025 | F9: 0.17985612 | G9: 4720 | H9: 4000 | I9: 0 | J9: 360 | K9: 360 | L9: 720 | M9: 27AASCS3903K1ZV2526353 | N9: 998332 | O9: Professional Fees | P9: Input Service | Q9: 2599 | R9: 45931 | S9: 45931 | T9: Yes
A10: 45931 | B10: 27AASCS3903K1ZV | C10: SEMSYS PRIVATE LIMITED | D10: 2526354 | E10: 01/10/2025 | F10: 0.17985612 | G10: 4720 | H10: 4000 | I10: 0 | J10: 360 | K10: 360 | L10: 720 | M10: 27AASCS3903K1ZV2526354 | N10: 998332 | O10: Professional Fees | P10: Input Service | Q10: 2600 | R10: 45931 | S10: 45931 | T10: Yes
A11: 45931 | B11: 27AASCS3903K1ZV | C11: SEMSYS PRIVATE LIMITED | D11: 2526355 | E11: 01/10/2025 | F11: 0.17985612 | G11: 23600 | H11: 20000 | I11: 0 | J11: 1800 | K11: 1800 | L11: 3600 | M11: 27AASCS3903K1ZV2526355 | N11: 998332 | O11: Professional Fees | P11: Input Service | Q11: 2601 | R11: 45931 | S11: 45931 | T11: Yes
A12: 45931 | B12: 27AAGCR8772D1Z2 | C12: Porter | D12: CRN1267653331 | E12: 30/09/2025 | F12: 0.17985612 | G12: 118 | H12: 100 | I12: 0 | J12: 9 | K12: 9 | L12: 18 | M12: 27AAGCR8772D1Z2CRN1267653331 | N12: 996511 | O12: Courior Services | P12: Input Service | Q12: 877 | R12: 45931 | S12: 45931 | T12: Yes
A13: 45931 | B13: 27AIFPK3096H1Z3 | C13: RAJ ELECTRICALS | D13: 63210 | E13: 10/10/2025 | F13: 0.17985612 | G13: 413 | H13: 350 | I13: 0 | J13: 31.5 | K13: 31.5 | L13: 63 | M13: 27AIFPK3096H1Z363210 | N13: 0 | O13: Hardware/Software Expenses | P13: Inputs | Q13: 2728 | R13: 45931 | S13: 45931 | T13: Yes
A14: 45931 | B14: 27AAMFD2812K1ZC | C14: DESIGNSTYLE STUDIOS | D14: 69 | E14: 11/08/2025 | F14: 0.17985612 | G14: 1770 | H14: 1500 | I14: 0 | J14: 135 | K14: 135 | L14: 270 | M14: 27AAMFD2812K1ZC69 | N14: 0 | O14: 0 | Q14: 2724 | R14: 45931 | S14: 45931 | T14: Yes
A15: 45931 | B15: 03ACCPS7232A1Z5 | C15: ELECTRO SALES | D15: ES-ECOM-179 | E15: 06/10/2025 | F15: 0.17985612 | G15: 1330 | H15: 1127.12 | I15: 202.88 | J15: 0 | K15: 0 | L15: 202.88 | M15: 03ACCPS7232A1Z5ES-ECOM-179 | N15: 0 | O15: 0 | Q15: 2605 | R15: 45931 | S15: 45931 | T15: Yes
A16: 45931 | B16: 27AAACU4322N1Z6 | C16: UPS EXPRESS PRIVATE LIMITED | D16: 427100363393 | E16: 29/10/2025 | F16: 0.17985612 | G16: 5272.24 | H16: 4468 | I16: 0 | J16: 402.12 | K16: 402.12 | L16: 804.24 | M16: 27AAACU4322N1Z6427100363393 | N16: 996813 | O16: Courior Services | P16: Input Service | Q16: 2723 | R16: 45931 | S16: 45931 | T16: Yes
A17: 45931 | B17: 27AAACU4322N1Z6 | C17: UPS EXPRESS PRIVATE LIMITED | D17: 427100360338 | E17: 05/10/2025 | F17: 0.17985612 | G17: 929.84 | H17: 788 | I17: 0 | J17: 70.92 | K17: 70.92 | L17: 141.84 | M17: 27AAACU4322N1Z6427100360338 | N17: 996813 | O17: Courior Services | P17: Input Service | Q17: 2722 | R17: 45931 | S17: 45931 | T17: Yes
A18: 45931 | B18: 07AAACJ0054A1ZD | C18: JETWAYS TRAVELS PVT.LTD. | D18: HP501130 | E18: 31/10/2025 | F18: 0.17985612 | G18: 16402 | H18: 13900 | I18: 2502 | J18: 0 | K18: 0 | L18: 2502 | M18: 07AAACJ0054A1ZDHP501130 | N18: 998551 | O18: Travel Expenses | P18: Input Service | Q18: 2719 | R18: 45931 | S18: 45931 | T18: Yes
A19: 45931 | B19: 07AAACJ0054A1ZD | C19: JETWAYS TRAVELS PVT.LTD. | D19: HP501109 | E19: 27/10/2025 | F19: 0.17985612 | G19: 8260 | H19: 7000 | I19: 1260 | J19: 0 | K19: 0 | L19: 1260 | M19: 07AAACJ0054A1ZDHP501109 | N19: 998551 | O19: Travel Expenses | P19: Input Service | Q19: 2718 | R19: 45931 | S19: 45931 | T19: Yes
A20: 45931 | B20: 07AAACJ0054A1ZD | C20: JETWAYS TRAVELS PVT.LTD. | D20: HP501108 | E20: 27/10/2025 | F20: 0.17985612 | G20: 8968 | H20: 7600 | I20: 1368 | J20: 0 | K20: 0 | L20: 1368 | M20: 07AAACJ0054A1ZDHP501108 | N20: 998551 | O20: Travel Expenses | P20: Input Service | Q20: 2717 | R20: 45931 | S20: 45931 | T20: Yes
A21: 45931 | B21: 07AAACJ0054A1ZD | C21: JETWAYS TRAVELS PVT.LTD. | D21: DP525244 | E21: 25/10/2025 | F21: 0.17985612 | G21: 118 | H21: 100 | I21: 18 | J21: 0 | K21: 0 | L21: 18 | M21: 07AAACJ0054A1ZDDP525244 | N21: 998551 | O21: Travel Expenses | P21: Input Service | Q21: 2712 | R21: 45931 | S21: 45931 | T21: Yes
A22: 45931 | B22: 07AAACJ0054A1ZD | C22: JETWAYS TRAVELS PVT.LTD. | D22: DP525243 | E22: 25/10/2025 | F22: 0.17985612 | G22: 118 | H22: 100 | I22: 18 | J22: 0 | K22: 0 | L22: 18 | M22: 07AAACJ0054A1ZDDP525243 | N22: 998551 | O22: Travel Expenses | P22: Input Service | Q22: 2711 | R22: 45931 | S22: 45931 | T22: Yes
A23: 45931 | B23: 27AAWCS5258F1ZQ | C23: SMARTWORKS COWORKING SPACES LIMITED | D23: PUN06/SC25/00761 | E23: 22/10/2025 | F23: 0.17985612 | G23: 3404409.7 | H23: 2885093 | I23: 0 | J23: 259658.37 | K23: 259658.37 | L23: 519316.74 | M23: 27AAWCS5258F1ZQPUN06/SC25/00761 | N23: 997212 | O23: Rent-Office | P23: Input Service | Q23: 2703 | R23: 45931 | S23: 45931 | T23: Yes
A24: 45931 | B24: 06AADCH6128C1ZZ | C24: Handy Online Solutions Private Limited | D24: ONGRID061722397 | E24: 29/10/2025 | F24: 0.17985612 | G24: 7278.24 | H24: 6168 | I24: 1110.24 | J24: 0 | K24: 0 | L24: 1110.24 | M24: 06AADCH6128C1ZZONGRID061722397 | N24: 853669 | O24: Professional Fees | P24: Inputs | Q24: 2695 | R24: 45931 | S24: 45931 | T24: Yes
A25: 45931 | B25: 27ARCPK9149B1ZU | C25: UNIVERSAL ELECTRICALS | D25: 8919 | E25: 15/10/2025 | F25: 0.17985612 | G25: 2076.8 | H25: 1760 | I25: 0 | J25: 158.4 | K25: 158.4 | L25: 316.8 | M25: 27ARCPK9149B1ZU8919 | N25: 0 | O25: Hardware/Software Expenses | P25: Inputs | Q25: 2692 | R25: 45931 | S25: 45931 | T25: Yes
A26: 45931 | B26: 27AAACB2100P1ZX | C26: Vodafone Idea Limited | D26: MHI1410526435759 | E26: 09/10/2025 | F26: 0.17985612 | G26: 411.82 | H26: 349 | I26: 0 | J26: 31.41 | K26: 31.41 | L26: 62.82 | M26: 27AAACB2100P1ZXMHI1410526435759 | N26: 998413 | O26: Internet Connectivity charges | P26: Input Service | Q26: 2691 | R26: 45931 | S26: 45931 | T26: Yes
A27: 45931 | B27: 36AEUPV4314A1ZE | C27: Vegesna Akshaya Avyanga Industries | D27: 014/2025-2026 | E27: 30/10/2025 | F27: 0.17985612 | G27: 295000 | H27: 250000 | I27: 45000 | J27: 0 | K27: 0 | L27: 45000 | M27: 36AEUPV4314A1ZE014/2025-2026 | N27: 998313 | O27: Professional Fees | P27: Input Service | Q27: 2686 | R27: 45931 | S27: 45931 | T27: Yes
A28: 45931 | B28: 27AABCC7181N2Z7 | C28: SWISS INTERNATIONAL AIR LINES LTD. | D28: LXBOM251000654 | E28: 08/10/2025 | F28: 0.05 | G28: 105483 | H28: 100460 | I28: 0 | J28: 2511.5 | K28: 2511.5 | L28: 5023 | M28: 27AABCC7181N2Z7LXBOM251000654 | N28: 440362 | O28: Travel Expenses | P28: Inputs | Q28: 2680 | R28: 45931 | S28: 45931 | T28: Yes
A29: 45931 | B29: 27AABCF6516A1Z3 | C29: FEDEX EXPRESS TRANSPORTATION AND SUPPLY CHAIN SERVICES (I) PRIVATE LIMITED | D29: BOM-C-279329 | E29: 25/10/2025 | F29: 0.17985612 | G29: 944 | H29: 800 | I29: 0 | J29: 72 | K29: 72 | L29: 144 | M29: 27AABCF6516A1Z3BOM-C-279329 | N29: 996812 | O29: Courior Services | P29: Input Service | Q29: 2679 | R29: 45931 | S29: 45931 | T29: Yes
A30: 45931 | B30: 06AAACM5586C1ZL | C30: Microsoft Corporation (India) Pvt Ltd | D30: TIO26HR101264303 | E30: 27/10/2025 | F30: 0.17985612 | G30: 1253.16 | H30: 1062 | I30: 191.16 | J30: 0 | K30: 0 | L30: 191.16 | M30: 06AAACM5586C1ZLTIO26HR101264303 | N30: 998313 | O30: Software Services | P30: Input Service | Q30: 2678 | R30: 45931 | S30: 45931 | T30: Yes
A31: 45931 | B31: 27AABCD3611Q1ZI | C31: DHL EXPRESS (INDIA) PRIVATE LIMITED | D31: BOM160246 | E31: 07/10/2025 | F31: 0.17985612 | G31: 1298 | H31: 1100 | I31: 0 | J31: 99 | K31: 99 | L31: 198 | M31: 27AABCD3611Q1ZIBOM160246 | N31: 996812 | O31: Courior Services | P31: Input Service | Q31: 2677 | R31: 45931 | S31: 45931 | T31: Yes
A32: 45931 | B32: 27AAECI7859N1ZQ | C32: Maars Creative Concepts Private Limited | D32: SOFT/594/25-26 | E32: 30/10/2025 | F32: 0.17985612 | G32: 743.4 | H32: 630 | I32: 0 | J32: 56.7 | K32: 56.7 | L32: 113.4 | M32: 27AAECI7859N1ZQSOFT/594/25-26 | N32: 482090 | O32: Printing & Stationery | P32: Inputs | Q32: 2672 | R32: 45931 | S32: 45931 | T32: Yes
A33: 45931 | B33: 27AAECI7859N1ZQ | C33: Maars Creative Concepts Private Limited | D33: SOFT/581/25-26 | E33: 18/10/2025 | F33: 0.17985612 | G33: 247.8 | H33: 210 | I33: 0 | J33: 18.9 | K33: 18.9 | L33: 37.8 | M33: 27AAECI7859N1ZQSOFT/581/25-26 | N33: 482090 | O33: Printing & Stationery | P33: Inputs | Q33: 2671 | R33: 45931 | S33: 45931 | T33: Yes
A34: 45931 | B34: 27AAECI7859N1ZQ | C34: Maars Creative Concepts Private Limited | D34: SOFT/560/25-26 | E34: 13/10/2025 | F34: 0.17985612 | G34: 826 | H34: 700 | I34: 0 | J34: 63 | K34: 63 | L34: 126 | M34: 27AAECI7859N1ZQSOFT/560/25-26 | N34: 482090 | O34: Printing & Stationery | P34: Inputs | Q34: 2670 | R34: 45931 | S34: 45931 | T34: Yes
A35: 45931 | B35: 27AAECI7859N1ZQ | C35: Maars Creative Concepts Private Limited | D35: SOFT/540/25-26 | E35: 06/10/2025 | F35: 0.17985612 | G35: 123.9 | H35: 105 | I35: 0 | J35: 9.45 | K35: 9.45 | L35: 18.9 | M35: 27AAECI7859N1ZQSOFT/540/25-26 | N35: 482090 | O35: Printing & Stationery | P35: Inputs | Q35: 2669 | R35: 45931 | S35: 45931 | T35: Yes
A36: 45931 | B36: 27DBRPP0459R1ZK | C36: Shree Caterers | D36: 2025-26/476 | E36: 31/10/2025 | F36: 0.05 | G36: 2520 | H36: 2400 | I36: 0 | J36: 60 | K36: 60 | L36: 120 | M36: 27DBRPP0459R1ZK2025-26/476 | N36: 99633 | O36: Staff Welfare | P36: Input Service | Q36: 2626 | R36: 45931 | S36: 45931 | T36: Yes
A37: 45931 | B37: 27AAACC2498P1Z3 | C37: CENTRAL BANK OF INDIA | D37: 26271C0003803394 | E37: 31/10/2025 | F37: 0.16666667 | G37: 0.56 | H37: 0.48 | I37: 0 | J37: 0.04 | K37: 0.04 | L37: 0.08 | M37: 27AAACC2498P1Z326271C0003803394 | N37: 440173 | O37: Bank Charges | P37: Inputs | Q37: 2627 | R37: 45931 | S37: 45931 | T37: Yes
... A43: 45931 | B43: 27AISPB8261G1Z0 | C43: BHUTADA ENTERPRISES | D43: SH0038-0019417 | E43: 29/10/2025 | F43: 0.05 | G43: 1820 | H43: 1725.98 | I43: 0 | J43: 47.01 | K43: 47.01 | L43: 94.02 | M43: 27AISPB8261G1Z0SH0038-0019417 | N43: 29152100 | O43: ACETIC ACID | P43: Inputs | Q43: 2633 | R43: 45931 | S43: 45931 | T43: Yes
A44: 45931 | B44: 27AZJPG1481H1ZC | C44: OM SAI SECURITY AND MANPOWER SERVICES / OM SAI TOURS AND TRAVELS | D44: 5904 | E44: 31/10/2025 | F44: 0.05 | G44: 10269 | H44: 9780 | I44: 0 | J44: 244.5 | K44: 244.5 | L44: 489 | M44: 27AZJPG1481H1ZC5904 | N44: 996813 | O44: Cab rent charges | P44: Input Service | Q44: 2660 | R44: 45931 | S44: 45931 | T44: Yes
A45: 45931 | B45: 27AZJPG1481H1ZC | C45: OM SAI SECURITY AND MANPOWER SERVICES / OM SAI TOURS AND TRAVELS | D45: 5824 | E45: 31/10/2025 | F45: 0.05 | G45: 4925.56 | H45: 4691 | I45: 0 | J45: 117.28 | K45: 117.28 | L45: 234.56 | M45: 27AZJPG1481H1ZC5824 | N45: 996813 | O45: Cab rent charges | P45: Input Service | Q45: 2659 | R45: 45931 | S45: 45931 | T45: Yes
A46: 45931 | B46: 27AABCR0111M1ZN | C46: ROYAL ORCHID HOTELS LIMITED | D46: ROCP-2526-12575 | E46: 16/10/2025 | F46: 0.17985612 | G46: 791.73 | H46: 670.95 | I46: 0 | J46: 60.39 | K46: 60.39 | L46: 120.78 | M46: 27AABCR0111M1ZNROCP-2526-12575 | N46: 996311 | O46: Hotel & Lodging Expenses | P46: Input Service | Q46: 2636 | R46: 45931 | S46: 45931 | T46: Yes
A47: 45931 | B47: 27AZJPG1481H1ZC | C47: OM SAI SECURITY AND MANPOWER SERVICES / OM SAI TOURS AND TRAVELS | D47: 5796 | E47: 31/10/2025 | F47: 0.05 | G47: 5187 | H47: 4940 | I47: 0 | J47: 123.5 | K47: 123.5 | L47: 247 | M47: 27AZJPG1481H1ZC5796 | N47: 996813 | O47: Cab rent charges | P47: Input Service | Q47: 2658 | R47: 45931 | S47: 45931 | T47: Yes
A48: 45931 | B48: 27AZJPG1481H1ZC | C48: OM SAI SECURITY AND MANPOWER SERVICES / OM SAI TOURS AND TRAVELS | D48: 5795 | E48: 31/10/2025 | F48: 0.05 | G48: 5234.26 | H48: 4985 | I48: 0 | J48: 124.63 | K48: 124.63 | L48: 249.26 | M48: 27AZJPG1481H1ZC5795 | N48: 996813 | O48: Cab rent charges | P48: Input Service | Q48: 2657 | R48: 45931 | S48: 45931 | T48: Yes
A49: 45931 | B49: 27AZJPG1481H1ZC | C49: OM SAI SECURITY AND MANPOWER SERVICES / OM SAI TOURS AND TRAVELS | D49: 5763 | E49: 31/10/2025 | F49: 0.05 | G49: 10958.86 | H49: 10437 | I49: 0 | J49: 260.93 | K49: 260.93 | L49: 521.86 | M49: 27AZJPG1481H1ZC5763 | N49: 996813 | O49: Cab rent charges | P49: Input Service | Q49: 2656 | R49: 45931 | S49: 45931 | T49: Yes
A50: 45931 | B50: 27ABBPM0253H1ZZ | C50: J RAY HARDWARE / J RAY ENGINEERING CO. | D50: JRH-15960 | E50: 10/10/2025 | F50: 0.17985612 | G50: 426.22 | H50: 361.2 | I50: 0 | J50: 32.51 | K50: 32.51 | L50: 65.02 | M50: 27ABBPM0253H1ZZJRH-15960 | N50: 0 | O50: 0 | Q50: 2640 | R50: 45931 | S50: 45931 | T50: Yes
A51: 45931 | B51: 27AAACI1195H1ZM | C51: ICICI BANK LIMITED | D51: 135251007031815 | E51: 07/10/2025 | F51: 0.17985612 | G51: 13463.32 | H51: 11409.6 | I51: 0 | J51: 1026.86 | K51: 1026.86 | L51: 2053.72 | M51: 27AAACI1195H1ZM135251007031815 | N51: 997157 | O51: Bank charges | P51: Input Service | Q51: 2641 | R51: 45931 | S51: 45931 | T51: Yes
A52: 45931 | B52: 27AAACI1195H1ZM | C52: ICICI BANK LIMITED | D52: 135251013059916 | E52: 13/10/2025 | F52: 0.17985612 | G52: 17866.26 | H52: 15140.9 | I52: 0 | J52: 1362.68 | K52: 1362.68 | L52: 2725.36 | M52: 27AAACI1195H1ZM135251013059916 | N52: 997157 | O52: Bank charges | P52: Input Service | Q52: 2642 | R52: 45931 | S52: 45931 | T52: Yes
A53: 45931 | B53: 27AAACI1195H1ZM | C53: ICICI BANK LIMITED | D53: 135251017090732 | E53: 17/10/2025 | F53: 0.17985612 | G53: 16702.81 | H53: 14154.93 | I53: 0 | J53: 1273.94 | K53: 1273.94 | L53: 2547.88 | M53: 27AAACI1195H1ZM135251017090732 | N53: 997157 | O53: Bank charges | P53: Input Service | Q53: 2643 | R53: 45931 | S53: 45931 | T53: Yes
A54: 45931 | B54: 27AAACI1195H1ZM | C54: ICICI BANK LIMITED | D54: 135251024114788 | E54: 24/10/2025 | F54: 0.17985612 | G54: 17728.95 | H54: 15024.53 | I54: 0 | J54: 1352.21 | K54: 1352.21 | L54: 2704.42 | M54: 27AAACI1195H1ZM135251024114788 | N54: 997157 | O54: Bank charges | P54: Input Service | Q54: 2644 | R54: 45931 | S54: 45931 | T54: Yes
A55: 45931 | B55: 27AAACI1195H1ZM | C55: ICICI BANK LIMITED | D55: 135251024114824 | E55: 24/10/2025 | F55: 0.17985612 | G55: 17728.95 | H55: 15024.53 | I55: 0 | J55: 1352.21 | K55: 1352.21 | L55: 2704.42 | M55: 27AAACI1195H1ZM135251024114824 | N55: 997157 | O55: Bank charges | P55: Input Service | Q55: 2645 | R55: 45931 | S55: 45931 | T55: Yes
A56: 45931 | B56: 27AAACI1195H1ZM | C56: ICICI BANK LIMITED | D56: 135251031156281 | E56: 31/10/2025 | F56: 0.17985612 | G56: 16814.42 | H56: 14249.5 | I56: 0 | J56: 1282.46 | K56: 1282.46 | L56: 2564.92 | M56: 27AAACI1195H1ZM135251031156281 | N56: 997157 | O56: Bank charges | P56: Input Service | Q56: 2646 | R56: 45931 | S56: 45931 | T56: Yes
A57: 45931 | B57: 27AAACI1195H1ZM | C57: ICICI BANK LIMITED | D57: TS61315298202510 | E57: 31/10/2025 | F57: 0.17985612 | G57: 590 | H57: 500 | I57: 0 | J57: 45 | K57: 45 | L57: 90 | M57: 27AAACI1195H1ZMTS61315298202510 | N57: 997157 | O57: Bank charges | P57: Input Service | Q57: 2647 | R57: 45931 | S57: 45931 | T57: Yes
A58: 45931 | B58: 27AAACI1195H1ZM | C58: ICICI BANK LIMITED | D58: TS61898693202510 | E58: 31/10/2025 | F58: 0.17985612 | G58: 2360 | H58: 2000 | I58: 0 | J58: 180 | K58: 180 | L58: 360 | M58: 27AAACI1195H1ZMTS61898693202510 | N58: 997157 | O58: Bank charges | P58: Input Service | Q58: 2648 | R58: 45931 | S58: 45931 | T58: Yes
A59: 45931 | B59: 27AAACI1195H1ZM | C59: ICICI BANK LIMITED | D59: TS63153615202510 | E59: 31/10/2025 | F59: 0.17985612 | G59: 4720 | H59: 4000 | I59: 0 | J59: 360 | K59: 360 | L59: 720 | M59: 27AAACI1195H1ZMTS63153615202510 | N59: 997157 | O59: Bank charges | P59: Input Service | Q59: 2649 | R59: 45931 | S59: 45931 | T59: Yes
A60: 45931 | B60: 27AAIFR9573K1ZE | C60: RAJIV ELECTRONICS | D60: HCA6254 | E60: 13/10/2025 | F60: 0.17985612 | G60: 575.26 | H60: 487.5 | I60: 0 | J60: 43.88 | K60: 43.88 | L60: 87.76 | M60: 27AAIFR9573K1ZEHCA6254 | N60: 773833 | O60: Hardware/Software Expenses | P60: Inputs | Q60: 2650 | R60: 45931 | S60: 45931 | T60: Yes
A61: 45931 | B61: 36AAJCA3639B1ZX | C61: M/S ARGUS EMBEDDED SYSTEMS PRIVATE LIMITED | D61: AE-INV-2526-0899 | E61: 31/10/2025 | F61: 0.17985612 | G61: 275553.6 | H61: 233520 | I61: 42033.6 | J61: 0 | K61: 0 | L61: 42033.6 | M61: 36AAJCA3639B1ZXAE-INV-2526-0899 | N61: 998112 | O61: Professional Fees | P61: Input Service | Q61: 2651 | R61: 45931 | S61: 45931 | T61: Yes
A62: 45931 | B62: 36AAJCA3639B1ZX | C62: M/S ARGUS EMBEDDED SYSTEMS PRIVATE LIMITED | D62: AE-INV-2526-0900 | E62: 31/10/2025 | F62: 0.17985612 | G62: 75331.2 | H62: 63840 | I62: 11491.2 | J62: 0 | K62: 0 | L62: 11491.2 | M62: 36AAJCA3639B1ZXAE-INV-2526-0900 | N62: 998112 | O62: Professional Fees | P62: Input Service | Q62: 2652 | R62: 45931 | S62: 45931 | T62: Yes
